{
  "populacao": 10012,
  "votosValidos": 8122,
  "abstencao": 11.76,
  "prefeito": {
    "nome": "MAURO SELMO OLIVEIRA VIEIRA",
    "nomeUrna": "MAURO VIEIRA",
    "partido": "PSD",
    "numero": "55",
    "votos": 6915,
    "percentual": 85.14,
    "situacao": "Eleito",
    "sqcand": "50002116768",
    "vice": "KARINE SANTOS RAMOS DA SILVA",
    "viceNomeUrna": "KARINE RAMOS",
    "partidoVice": "PSD",
    "sqcandVice": "50002116767",
    "coligacao": "PSD / REPUBLICANOS / PP / PL / AVANTE / CIDADANIA / PSDB"
  },
  "vereadores": [
    {
      "nome": "FELIPE MACHADO VIEIRA",
      "nomeUrna": "FELIPE VIEIRA",
      "partido": "PSD",
      "numero": "55000",
      "votos": 1229,
      "percentual": 14.54,
      "situacao": "Eleito por QP",
      "sqcand": "50002116773"
    },
    {
      "nome": "ANTÔNIO MÁRCIO SILVA VASCONCELOS",
      "nomeUrna": "MÁRCIO VASCONCELOS",
      "partido": "PSD",
      "numero": "55369",
      "votos": 1194,
      "percentual": 14.13,
      "situacao": "Eleito por QP",
      "sqcand": "50002116772"
    },
    {
      "nome": "REGINA COUTO DE OLIVEIRA NETA",
      "nomeUrna": "REGININHA DE ZE LUIZ",
      "partido": "PSD",
      "numero": "55111",
      "votos": 787,
      "percentual": 9.31,
      "situacao": "Eleito por QP",
      "sqcand": "50002116776"
    },
    {
      "nome": "JOSÉ AUGUSTO ARAÚJO FREITAS",
      "nomeUrna": "ZÉ AUGUSTO",
      "partido": "MDB",
      "numero": "15555",
      "votos": 583,
      "percentual": 6.9,
      "situacao": "Eleito por QP",
      "sqcand": "50001949829"
    },
    {
      "nome": "WILTON MELO SANTOS",
      "nomeUrna": "WILTON MELO",
      "partido": "PSD",
      "numero": "55666",
      "votos": 542,
      "percentual": 6.41,
      "situacao": "Eleito por QP",
      "sqcand": "50002116770"
    },
    {
      "nome": "JOSÉ RAIMUNDO SILVA SANTOS",
      "nomeUrna": "ZÉ FILÉ",
      "partido": "REPUBLICANOS",
      "numero": "10125",
      "votos": 489,
      "percentual": 5.79,
      "situacao": "Eleito por QP",
      "sqcand": "50002116216"
    },
    {
      "nome": "CARLOS ANTÔNIO ALMEIDA SAMPAIO",
      "nomeUrna": "CARLINHOS",
      "partido": "PSD",
      "numero": "55222",
      "votos": 463,
      "percentual": 5.48,
      "situacao": "Eleito por QP",
      "sqcand": "50002116775"
    },
    {
      "nome": "WILLIAN CARNEIRO SILVA",
      "nomeUrna": "WILLIAN DA AREIA",
      "partido": "PSD",
      "numero": "55444",
      "votos": 455,
      "percentual": 5.38,
      "situacao": "Eleito por QP",
      "sqcand": "50002116771"
    },
    {
      "nome": "ELVIA CRISTINA RODRIGUES DA SILVA",
      "nomeUrna": "ELVIA DE ELIAS",
      "partido": "REPUBLICANOS",
      "numero": "10615",
      "votos": 269,
      "percentual": 3.18,
      "situacao": "Eleito por média",
      "sqcand": "50002116215"
    }
  ],
  "senadores": [
    {
      "nome": "OTTO ROBERTO MENDONCA DE ALENCAR",
      "nomeUrna": "OTTO ALENCAR",
      "partido": "PSD",
      "numero": "555",
      "votos": 4680,
      "percentual": 77.38,
      "sqcand": "50001605790"
    },
    {
      "nome": "CARLOS FELIPE VAZQUEZ DE SOUZA LEÃO",
      "nomeUrna": "CACÁ LEÃO",
      "partido": "PP",
      "numero": "111",
      "votos": 758,
      "percentual": 12.53,
      "sqcand": "50001615121"
    },
    {
      "nome": "RAISSA OLIVEIRA AZEVEDO DE MELO SOARES",
      "nomeUrna": "DOUTORA RAISSA SOARES",
      "partido": "PL",
      "numero": "222",
      "votos": 540,
      "percentual": 8.93,
      "sqcand": "50001605325"
    }
  ],
  "deputadosFederais": [
    {
      "nome": "JOSÉ CERQUEIRA DE SANTANA NETO",
      "nomeUrna": "ZÉ NETO",
      "partido": "PT",
      "numero": "1323",
      "votos": 1668,
      "percentual": 25.97,
      "sqcand": "50001605365"
    },
    {
      "nome": "ROBERTA DE ARAÚJO COSTA ROMA",
      "nomeUrna": "ROBERTA ROMA",
      "partido": "PL",
      "numero": "2222",
      "votos": 1427,
      "percentual": 22.22,
      "sqcand": "50001609349"
    },
    {
      "nome": "CLAUDIO CAJADO SAMPAIO",
      "nomeUrna": "CLAUDIO CAJADO",
      "partido": "PP",
      "numero": "1122",
      "votos": 1116,
      "percentual": 17.38,
      "sqcand": "50001621019"
    },
    {
      "nome": "ADALBERTO ROSA BARRETO",
      "nomeUrna": "DEPUTADO DAL",
      "partido": "UNIÃO",
      "numero": "4488",
      "votos": 443,
      "percentual": 6.9,
      "sqcand": "50001634594"
    },
    {
      "nome": "MARCIO CARLOS MARINHO",
      "nomeUrna": "MARCIO MARINHO",
      "partido": "REPUBLICANOS",
      "numero": "1010",
      "votos": 107,
      "percentual": 1.67,
      "sqcand": "50001619869"
    },
    {
      "nome": "FLAVIO ARRUDA MORAIS",
      "nomeUrna": "GALEGUINHO",
      "partido": "PSB",
      "numero": "4044",
      "votos": 102,
      "percentual": 1.59,
      "sqcand": "50001606045"
    },
    {
      "nome": "JOSÉ FRANCISCO PINTO",
      "nomeUrna": "ZÉ CHICO",
      "partido": "UNIÃO",
      "numero": "4470",
      "votos": 92,
      "percentual": 1.43,
      "sqcand": "50001634607"
    }
  ],
  "deputadosEstaduais": [
    {
      "nome": "NELSON SOUZA LEAL",
      "nomeUrna": "NELSON LEAL",
      "partido": "PP",
      "numero": "11555",
      "votos": 1521,
      "percentual": 25.99,
      "sqcand": "50001647023"
    },
    {
      "nome": "ROBINSON SANTOS ALMEIDA",
      "nomeUrna": "ROBINSON",
      "partido": "PT",
      "numero": "13500",
      "votos": 1045,
      "percentual": 17.86,
      "sqcand": "50001606417"
    },
    {
      "nome": "VITOR VIANA PARANHOS DE AZEVEDO",
      "nomeUrna": "VITOR AZEVEDO",
      "partido": "PL",
      "numero": "22222",
      "votos": 802,
      "percentual": 13.7,
      "sqcand": "50001609449"
    },
    {
      "nome": "SANDRO DE OLIVEIRA RÉGIS",
      "nomeUrna": "SANDRO RÉGIS",
      "partido": "UNIÃO",
      "numero": "44444",
      "votos": 438,
      "percentual": 7.48,
      "sqcand": "50001648297"
    },
    {
      "nome": "KLEBER CRISTIAN ESCOLANO DE ALMEIDA",
      "nomeUrna": "BINHO GALINHA",
      "partido": "PATRIOTA",
      "numero": "51000",
      "votos": 300,
      "percentual": 5.13,
      "sqcand": "50001610379"
    },
    {
      "nome": "JHONATAS LIMA MONTEIRO",
      "nomeUrna": "JHONATAS MONTEIRO",
      "partido": "PSOL",
      "numero": "50050",
      "votos": 219,
      "percentual": 3.74,
      "sqcand": "50001600626"
    },
    {
      "nome": "PABLO ROBERTO GONÇALVES DA SILVA",
      "nomeUrna": "PABLO ROBERTO ",
      "partido": "PSDB",
      "numero": "45100",
      "votos": 192,
      "percentual": 3.28,
      "sqcand": "50001613913"
    }
  ]
}