{"populacao":8440,"votosValidos":7467,"abstencao":7.83,"prefeito":{"nome":"TADEU PRADO REBOUÇAS PRATES","nomeUrna":"TADEUZINHO PRATES","partido":"UNIÃO","numero":"44","votos":3992,"percentual":53.46,"situacao":"Eleito","sqcand":"50002079213","vice":"MARCOS ANTONIO FARIAS BRITO","viceNomeUrna":"MARQUINHOS","partidoVice":"PSD","sqcandVice":"50002079212","coligacao":"UNIÃO / PSD"},"vereadores":[{"nome":"VERONICA DOS SANTOS BRITO","nomeUrna":"VERÔNICA BRITO","partido":"PT","numero":"13444","votos":617,"percentual":8.2,"situacao":"Eleito por QP","sqcand":"50001901510"},{"nome":"JOAO FRANCISCO DAS NEVES","nomeUrna":"JOÃO DE HORÁCIO","partido":"PSD","numero":"55680","votos":593,"percentual":7.88,"situacao":"Eleito por QP","sqcand":"50002141519"},{"nome":"JUSSANDRA DE SOUSA SILVEIRA MATOS","nomeUrna":"JUSSANDRA","partido":"PT","numero":"13111","votos":487,"percentual":6.47,"situacao":"Eleito por QP","sqcand":"50001901511"},{"nome":"JULIO ANTONIO FARIAS","nomeUrna":"JULIO","partido":"UNIÃO","numero":"44444","votos":486,"percentual":6.46,"situacao":"Eleito por QP","sqcand":"50002087762"},{"nome":"JOSÉ PESSOA GONÇALVES","nomeUrna":"ZÉ DO OCULOS","partido":"UNIÃO","numero":"44369","votos":464,"percentual":6.17,"situacao":"Eleito por QP","sqcand":"50002087763"},{"nome":"ARNALDO MARQUES PEREIRA","nomeUrna":"ARNALDO","partido":"PSD","numero":"55666","votos":393,"percentual":5.22,"situacao":"Eleito por QP","sqcand":"50002141518"},{"nome":"NILTON ANTONIO DOS SANTOS","nomeUrna":"NINTON DE DERMIRO","partido":"PSD","numero":"55000","votos":360,"percentual":4.78,"situacao":"Eleito por média","sqcand":"50002141516"},{"nome":"WALDIR MARCOS SANTOS RODRIGUES","nomeUrna":"WALDIR","partido":"PSD","numero":"55123","votos":351,"percentual":4.66,"situacao":"Suplente","sqcand":"50002141521"},{"nome":"JESUS FARIAS CARDOSO","nomeUrna":"DUDU CARDOSO","partido":"MDB","numero":"15000","votos":302,"percentual":4.01,"situacao":"Eleito por QP","sqcand":"50001901558"},{"nome":"CUSTÓDIO MARCOS XAVIER DA SILVA","nomeUrna":"TOTÓ","partido":"UNIÃO","numero":"44123","votos":293,"percentual":3.89,"situacao":"Eleito por média","sqcand":"50002087760"},{"nome":"MANOEL TADEU DE BRITO","nomeUrna":"TADEUZINHO","partido":"PSD","numero":"55555","votos":288,"percentual":3.83,"situacao":"Suplente","sqcand":"50002141517"},{"nome":"JOSAPHAT FARIAS DOS SANTOS","nomeUrna":"JOSAPHAT","partido":"UNIÃO","numero":"44456","votos":272,"percentual":3.61,"situacao":"Suplente","sqcand":"50002087758"},{"nome":"JÉSUS MÁRIO CARDOSO SANTOS","nomeUrna":"PROFESSOR GÊ","partido":"PT","numero":"13999","votos":269,"percentual":3.57,"situacao":"Suplente","sqcand":"50001901514"},{"nome":"JOATHAN WAGNER FARIAS GOMES","nomeUrna":"JOATHAN","partido":"UNIÃO","numero":"44000","votos":262,"percentual":3.48,"situacao":"Suplente","sqcand":"50002087761"},{"nome":"JOSÉ TADEU DE FARIAS","nomeUrna":"ZÉ TADEU","partido":"PT","numero":"13456","votos":255,"percentual":3.39,"situacao":"Suplente","sqcand":"50001901506"},{"nome":"MARIA DE LOURDES BRITO","nomeUrna":"LOURDINHA","partido":"UNIÃO","numero":"44789","votos":249,"percentual":3.31,"situacao":"Suplente","sqcand":"50002087757"},{"nome":"JESUS APARECIDO PINHO PEREIRA","nomeUrna":"ZÚ DO BAR DO ZÚ","partido":"MDB","numero":"15589","votos":134,"percentual":1.78,"situacao":"Suplente","sqcand":"50001901557"},{"nome":"ANDERSON DA SILVA PIRES GOMES","nomeUrna":"DRINHO","partido":"PSD","numero":"55244","votos":128,"percentual":1.7,"situacao":"Suplente","sqcand":"50002141514"},{"nome":"ANTONINHO SOUSA DUCA","nomeUrna":"TONINHO DUCA","partido":"PT","numero":"13666","votos":121,"percentual":1.61,"situacao":"Suplente","sqcand":"50001901508"},{"nome":"ANA LÚCIA XAVIER ALVES SILVEIRA","nomeUrna":"ANA LÚCIA","partido":"PT","numero":"13123","votos":119,"percentual":1.58,"situacao":"Suplente","sqcand":"50001901512"},{"nome":"ALEX BRITO DA SILVA","nomeUrna":"ALEX BRITO","partido":"MDB","numero":"15015","votos":113,"percentual":1.5,"situacao":"Suplente","sqcand":"50001901553"},{"nome":"ZOMIR DE JESUS PACHECO","nomeUrna":"SAMIR","partido":"PT","numero":"13000","votos":107,"percentual":1.42,"situacao":"Suplente","sqcand":"50001901507"},{"nome":"JESUS BRITO DE SOUSA","nomeUrna":"ZÚ DO SANTO INÁCIO","partido":"MDB","numero":"15777","votos":94,"percentual":1.25,"situacao":"Suplente","sqcand":"50001901555"},{"nome":"ANGELINA NOVAIS DE FREITAS","nomeUrna":"ANGELINA LENA","partido":"MDB","numero":"15123","votos":83,"percentual":1.1,"situacao":"Suplente","sqcand":"50001901552"},{"nome":"MEIBE RAMOS DOS SANTOS","nomeUrna":"MEIBE","partido":"MDB","numero":"15555","votos":72,"percentual":0.96,"situacao":"Suplente","sqcand":"50001901551"},{"nome":"MARCIA MARIA GOMES DE ANDRADE","nomeUrna":"MARCIA ANDRADE","partido":"PT","numero":"13222","votos":72,"percentual":0.96,"situacao":"Suplente","sqcand":"50001901509"},{"nome":"ELIANO FREITAS DA SILVA","nomeUrna":"LILI","partido":"PSD","numero":"55700","votos":65,"percentual":0.86,"situacao":"Suplente","sqcand":"50002141515"},{"nome":"ANETE FARIAS DE ANDRADE","nomeUrna":"ANETE FARIAS","partido":"MDB","numero":"15789","votos":58,"percentual":0.77,"situacao":"Suplente","sqcand":"50001901554"},{"nome":"NOEL DE SOUZA SANTOS","nomeUrna":"NOEL DE SOUZA","partido":"PT","numero":"13555","votos":27,"percentual":0.36,"situacao":"Suplente","sqcand":"50001901505"},{"nome":"JANAÍNA CARDOSO RODRIGUES","nomeUrna":"JANAINA","partido":"PSD","numero":"55888","votos":26,"percentual":0.35,"situacao":"Suplente","sqcand":"50002141513"},{"nome":"NATÂNE CARDOSO SOUZA","nomeUrna":"NATÂNE","partido":"PSD","numero":"55044","votos":17,"percentual":0.23,"situacao":"Suplente","sqcand":"50002141520"},{"nome":"FLÁVIA BRITO RIBEIRO","nomeUrna":"FLÁVIA","partido":"PSD","numero":"55855","votos":16,"percentual":0.21,"situacao":"Suplente","sqcand":"50002141512"},{"nome":"IRANI RODRIGUES DE LIMA","nomeUrna":"IRANI","partido":"MDB","numero":"15680","votos":16,"percentual":0.21,"situacao":"Suplente","sqcand":"50001901550"},{"nome":"JORGE ALOISIO DE JESUS PACHÊCO","nomeUrna":"JORJÃO","partido":"MDB","numero":"15111","votos":16,"percentual":0.21,"situacao":"Suplente","sqcand":"50001901556"},{"nome":"JOÃO MARCELO DOS SANTOS CRUZ","nomeUrna":"JOÃO MARCELO","partido":"PT","numero":"13777","votos":15,"percentual":0.2,"situacao":"Suplente","sqcand":"50001901513"},{"nome":"MARIA ROSÁRIO FARIAS PINHEIRO","nomeUrna":"ZARA","partido":"UNIÃO","numero":"44970","votos":8,"percentual":0.11,"situacao":"Suplente","sqcand":"50002087759"},{"nome":"ROSANA CARDOSO DE FARIAS","nomeUrna":"ROSANA","partido":"UNIÃO","numero":"44044","votos":7,"percentual":0.09,"situacao":"Suplente","sqcand":"50002087764"},{"nome":"BARTHOLOMEU NEY SILVA PRADO","nomeUrna":"BARTOLO","partido":"UNIÃO","numero":"44999","votos":1,"percentual":0.01,"situacao":"Suplente","sqcand":"50002087756"}],"senadores":[{"nome":"OTTO ROBERTO MENDONCA DE ALENCAR","nomeUrna":"OTTO ALENCAR","partido":"PSD","numero":"555","votos":2923,"percentual":50.99,"sqcand":"50001605790"},{"nome":"CARLOS FELIPE VAZQUEZ DE SOUZA LEÃO","nomeUrna":"CACÁ LEÃO","partido":"PP","numero":"111","votos":2579,"percentual":44.99,"sqcand":"50001615121"},{"nome":"RAISSA OLIVEIRA AZEVEDO DE MELO SOARES","nomeUrna":"DOUTORA RAISSA SOARES","partido":"PL","numero":"222","votos":208,"percentual":3.63,"sqcand":"50001605325"},{"nome":"TAMARA AZEVEDO CARDOSO","nomeUrna":"TÂMARA AZEVEDO","partido":"PSOL","numero":"500","votos":17,"percentual":0.3,"sqcand":"50001600536"},{"nome":"MARCELO SIQUEIRA BARRETO","nomeUrna":"MARCELO BARRETO","partido":"PMN","numero":"333","votos":6,"percentual":0.1,"sqcand":"50001597051"}],"deputadosFederais":[{"nome":"PAULO VELLOSO DANTAS AZI","nomeUrna":"PAULO AZI","partido":"UNIÃO","numero":"4400","votos":2152,"percentual":34.05,"sqcand":"50001634593"},{"nome":"WALDENOR ALVES PEREIRA FILHO","nomeUrna":"WALDENOR PEREIRA","partido":"PT","numero":"1322","votos":1556,"percentual":24.62,"sqcand":"50001605361"},{"nome":"JOSÉ ALVES ROCHA","nomeUrna":"JOSÉ ROCHA","partido":"UNIÃO","numero":"4422","votos":567,"percentual":8.97,"sqcand":"50001634584"},{"nome":"CHARLES FERNANDES SILVEIRA SANTANA","nomeUrna":"CHARLES FERNANDES","partido":"PSD","numero":"5511","votos":523,"percentual":8.28,"sqcand":"50001607219"},{"nome":"ELANE ALVES DE ALMEIDA","nomeUrna":"DRA ELANE","partido":"PSD","numero":"5533","votos":445,"percentual":7.04,"sqcand":"50001607230"},{"nome":"ELISANGELA DOS SANTOS ARAUJO","nomeUrna":"ELISANGELA","partido":"PT","numero":"1334","votos":350,"percentual":5.54,"sqcand":"50001605364"},{"nome":"ALEX MARCO SANTANA SOUSA","nomeUrna":"ALEX SANTANA","partido":"REPUBLICANOS","numero":"1023","votos":67,"percentual":1.06,"sqcand":"50001619864"},{"nome":"JOSÉ FRANCISCO PINTO","nomeUrna":"ZÉ CHICO","partido":"UNIÃO","numero":"4470","votos":36,"percentual":0.57,"sqcand":"50001634607"},{"nome":"DIEGO HENRIQUE SILVA CERQUEIRA MARTINS","nomeUrna":"DIEGO CORONEL","partido":"PSD","numero":"5500","votos":35,"percentual":0.55,"sqcand":"50001607221"},{"nome":"TALITA SANTOS DE OLIVEIRA","nomeUrna":"TALITA OLIVEIRA","partido":"REPUBLICANOS","numero":"1022","votos":30,"percentual":0.47,"sqcand":"50001619835"},{"nome":"FRANCISCO FERNANDES NOGUEIRA","nomeUrna":"NOBRE FRANCISCO","partido":"NOVO","numero":"3033","votos":29,"percentual":0.46,"sqcand":"50001596238"},{"nome":"DANIEL GOMES DE ALMEIDA","nomeUrna":"DANIEL","partido":"PC do B","numero":"6565","votos":28,"percentual":0.44,"sqcand":"50001605367"},{"nome":"JOSIAS GOMES DA SILVA","nomeUrna":"JOSIAS GOMES","partido":"PT","numero":"1312","votos":27,"percentual":0.43,"sqcand":"50001605379"},{"nome":"ALEXANDRE ALELUIA DANTAS DA COSTA","nomeUrna":"ALEXANDRE ALELUIA","partido":"PL","numero":"2255","votos":23,"percentual":0.36,"sqcand":"50001609359"},{"nome":"ROBERTA DE ARAÚJO COSTA ROMA","nomeUrna":"ROBERTA ROMA","partido":"PL","numero":"2222","votos":22,"percentual":0.35,"sqcand":"50001609349"},{"nome":"ARTHUR DE OLIVEIRA MAIA DA SILVA","nomeUrna":"ARTHUR MAIA","partido":"UNIÃO","numero":"4412","votos":21,"percentual":0.33,"sqcand":"50001634596"},{"nome":"LUCAS GONÇALVES TORRES VASCONCELOS MOREIRA","nomeUrna":"LUCAS TORRES","partido":"PT","numero":"1333","votos":21,"percentual":0.33,"sqcand":"50001605383"},{"nome":"GEORGE CARLOS REIS PEREIRA","nomeUrna":"GEORGE O GORDINHO DA FAVELA","partido":"PP","numero":"1199","votos":20,"percentual":0.32,"sqcand":"50001621031"},{"nome":"ROGERIA DE ALMEIDA PEREIRA DOS SANTOS","nomeUrna":"ROGERIA SANTOS","partido":"REPUBLICANOS","numero":"1000","votos":17,"percentual":0.27,"sqcand":"50001619841"},{"nome":"ALEXANDRE GARCIA ARAÚJO","nomeUrna":"XANDÓ","partido":"PT","numero":"1350","votos":14,"percentual":0.22,"sqcand":"50001605373"},{"nome":"ADALBERTO ROSA BARRETO","nomeUrna":"DEPUTADO DAL","partido":"UNIÃO","numero":"4488","votos":13,"percentual":0.21,"sqcand":"50001634594"},{"nome":"MARIA APARECIDA NOGUEIRA COSTA","nomeUrna":"CIDA ","partido":"PSD","numero":"5545","votos":12,"percentual":0.19,"sqcand":"50001607225"},{"nome":"VILMA MARIA DOS SANTOS REIS","nomeUrna":"VILMA REIS","partido":"PT","numero":"1303","votos":12,"percentual":0.19,"sqcand":"50001605376"},{"nome":"SÉRGIO LUÍS LACERDA BRITO","nomeUrna":"SÉRGIO BRITO","partido":"PSD","numero":"5580","votos":11,"percentual":0.17,"sqcand":"50001607223"},{"nome":"ORLANDO SULZ DE ALMEIDA NETO","nomeUrna":"NETO CARLETTO","partido":"PP","numero":"1144","votos":10,"percentual":0.16,"sqcand":"50001621029"},{"nome":"MARCELO DE OLIVEIRA GUIMARAES FILHO","nomeUrna":"MARCELO GUIMARÃES FILHO","partido":"UNIÃO","numero":"4455","votos":10,"percentual":0.16,"sqcand":"50001634585"},{"nome":"DAYANE JAMILLE CARNEIRO DOS SANTOS PIMENTEL","nomeUrna":"PROFESSORA DAYANE PIMENTEL","partido":"UNIÃO","numero":"4444","votos":10,"percentual":0.16,"sqcand":"50001634573"},{"nome":"DANIELA CARDOSO DE CARVALHO","nomeUrna":"DANIELA CARVALHO","partido":"AVANTE","numero":"7040","votos":9,"percentual":0.14,"sqcand":"50001602952"},{"nome":"VALMIR CARLOS DA ASSUNÇÃO","nomeUrna":"VALMIR ASSUNÇÃO","partido":"PT","numero":"1310","votos":9,"percentual":0.14,"sqcand":"50001605371"},{"nome":"GLABY CARVALHO DE ANDRADE","nomeUrna":"GLEBÃO","partido":"PDT","numero":"1232","votos":9,"percentual":0.14,"sqcand":"50001620856"},{"nome":"AFONSO BANDEIRA FLORENCE","nomeUrna":"AFONSO FLORENCE","partido":"PT","numero":"1301","votos":9,"percentual":0.14,"sqcand":"50001605378"},{"nome":"ALDNEY BASTOS MARQUES","nomeUrna":"NEINHA BASTOS","partido":"PDT","numero":"1222","votos":8,"percentual":0.13,"sqcand":"50001620883"},{"nome":"ANDRÉ PORCIUNCULA ALAY ESTEVES","nomeUrna":"CAPITÃO ANDRÉ PORCIUNCULA","partido":"PL","numero":"2223","votos":7,"percentual":0.11,"sqcand":"50001609337"},{"nome":"MARTA RODRIGUES SOUSA DE BRITO COSTA","nomeUrna":"MARTA RODRIGUES","partido":"PT","numero":"1346","votos":7,"percentual":0.11,"sqcand":"50001605372"},{"nome":"KATIA MARIA ALVES SANTOS","nomeUrna":"KATIA ALVES","partido":"UNIÃO","numero":"4440","votos":7,"percentual":0.11,"sqcand":"50001634574"},{"nome":"HOLMES ROCHA DOS SANTOS FILHO","nomeUrna":"ENFERMEIRO HOLMES","partido":"PDT","numero":"1233","votos":6,"percentual":0.09,"sqcand":"50001620855"},{"nome":"LÍDICE DA MATA E SOUZA","nomeUrna":"LÍDICE DA MATA","partido":"PSB","numero":"4040","votos":5,"percentual":0.08,"sqcand":"50001606032"},{"nome":"MÁRIO SÍLVIO MENDES NEGROMONTE JÚNIOR","nomeUrna":"MÁRIO NEGROMONTE JR","partido":"PP","numero":"1111","votos":5,"percentual":0.08,"sqcand":"50001621035"},{"nome":"FÁBIO VILAS BOAS PINTO","nomeUrna":"DR FÁBIO VILAS BOAS","partido":"MDB","numero":"1513","votos":5,"percentual":0.08,"sqcand":"50001614025"},{"nome":"SEVERIANO ALVES DE SOUZA","nomeUrna":"SEVERIANO ALVES","partido":"PTB","numero":"1414","votos":5,"percentual":0.08,"sqcand":"50001645896"},{"nome":"JOCEVAL RODRIGUES DOS SANTOS","nomeUrna":"JOCEVAL RODRIGUES","partido":"CIDADANIA","numero":"2300","votos":5,"percentual":0.08,"sqcand":"50001613557"},{"nome":"JORGE JOSE SANTOS PEREIRA SOLLA","nomeUrna":"JORGE SOLLA","partido":"PT","numero":"1313","votos":5,"percentual":0.08,"sqcand":"50001605359"},{"nome":"KLEBER REBOUÇAS RANGEL","nomeUrna":"COMANDANTE RANGEL","partido":"PL","numero":"2211","votos":4,"percentual":0.06,"sqcand":"50001609372"},{"nome":"FELIX DE ALMEIDA MENDONCA JUNIOR","nomeUrna":"FELIX  MENDONÇA","partido":"PDT","numero":"1234","votos":4,"percentual":0.06,"sqcand":"50001620846"},{"nome":"CAMILA BARREIRA COUTO","nomeUrna":"CAMILA COUTO","partido":"MDB","numero":"1522","votos":4,"percentual":0.06,"sqcand":"50001614027"},{"nome":"ROSANA CABECEIRA LAGO","nomeUrna":"ROSANA LAGO","partido":"MDB","numero":"1588","votos":4,"percentual":0.06,"sqcand":"50001614033"},{"nome":"ADELMA SERENO SALUSTIANO","nomeUrna":"ADELMA DA SAÚDE","partido":"PP","numero":"1132","votos":4,"percentual":0.06,"sqcand":"50001621027"},{"nome":"OTTO ROBERTO MENDONCA DE ALENCAR FILHO","nomeUrna":"OTTO FILHO","partido":"PSD","numero":"5588","votos":4,"percentual":0.06,"sqcand":"50001607228"},{"nome":"JOSUE BRANDÃO AMORIM","nomeUrna":"PASTOR JOSUÉ BRANDÃO","partido":"PODE","numero":"1922","votos":4,"percentual":0.06,"sqcand":"50001615388"},{"nome":"LUIZ CARLOS ZANARDO LEMOS","nomeUrna":"PR. LUIZ LEMOS","partido":"REPUBLICANOS","numero":"1021","votos":4,"percentual":0.06,"sqcand":"50001619868"},{"nome":"LEUR ANTONIO DE BRITTO LOMANTO JUNIOR","nomeUrna":"LEUR LOMANTO JR","partido":"UNIÃO","numero":"4411","votos":3,"percentual":0.05,"sqcand":"50001634592"},{"nome":"RICARDO MAIA CHAVES DE SOUZA","nomeUrna":"RICARDO MAIA","partido":"MDB","numero":"1555","votos":3,"percentual":0.05,"sqcand":"50001614047"},{"nome":"JOSÉ PEREIRA DE LIMA","nomeUrna":"ZÉ LIMA DE CAFARNAUM","partido":"MDB","numero":"1580","votos":3,"percentual":0.05,"sqcand":"50001614037"},{"nome":"CLAUDIO BISPO SILVA","nomeUrna":"CAL ME AJUDE","partido":"PDT","numero":"1223","votos":3,"percentual":0.05,"sqcand":"50001620857"},{"nome":"IVAN CORDEIRO DA SILVA FILHO","nomeUrna":"IVAN CORDEIRO","partido":"PTB","numero":"1422","votos":3,"percentual":0.05,"sqcand":"50001645898"},{"nome":"PATRUSKA ROCHA BARREIRO","nomeUrna":"PATRUSKA","partido":"PDT","numero":"1251","votos":3,"percentual":0.05,"sqcand":"50001620879"},{"nome":"IVONEIDE SOUZA CAETANO","nomeUrna":"IVONEIDE CAETANO","partido":"PT","numero":"1300","votos":3,"percentual":0.05,"sqcand":"50001605353"},{"nome":"ALICE MAZZUCO PORTUGAL","nomeUrna":"ALICE PORTUGAL","partido":"PC do B","numero":"6522","votos":3,"percentual":0.05,"sqcand":"50001605368"},{"nome":"ANGÉLICA BITTENCOURT TEIXEIRA","nomeUrna":"PROFESSORA ANGÉLICA","partido":"PP","numero":"1133","votos":3,"percentual":0.05,"sqcand":"50001621013"},{"nome":"UBERDAN CARDOSO DOS SANTOS","nomeUrna":"PROFESSOR UBERDAN","partido":"PT","numero":"1344","votos":3,"percentual":0.05,"sqcand":"50001605382"},{"nome":"RAIMUNDO MOISÉS DA SILVA CALIXTO","nomeUrna":"RAIMUNDO CALIXTO","partido":"PSOL","numero":"5020","votos":3,"percentual":0.05,"sqcand":"50001600573"},{"nome":"ALDEN JOSÉ LÁZARO DA SILVA","nomeUrna":"CAPITÃO ALDEN","partido":"PL","numero":"2238","votos":3,"percentual":0.05,"sqcand":"50001609344"},{"nome":"JOSEILDO RIBEIRO RAMOS","nomeUrna":"JOSEILDO RAMOS","partido":"PT","numero":"1361","votos":2,"percentual":0.03,"sqcand":"50001605369"},{"nome":"ADEMOSANE QUINTINO MARTINS","nomeUrna":"KEILA","partido":"PL","numero":"2246","votos":2,"percentual":0.03,"sqcand":"50001609352"},{"nome":"GERALDO MÁRCIO MELO SOARES","nomeUrna":"GERALDO DE DRA. RAÍSSA","partido":"PL","numero":"2200","votos":2,"percentual":0.03,"sqcand":"50001609368"},{"nome":"ERNESTO DE SOUZA ANDRADE JÚNIOR","nomeUrna":"NETINHO DA BAHIA","partido":"PL","numero":"2210","votos":2,"percentual":0.03,"sqcand":"50001609365"},{"nome":"CLAUDIO CAJADO SAMPAIO","nomeUrna":"CLAUDIO CAJADO","partido":"PP","numero":"1122","votos":2,"percentual":0.03,"sqcand":"50001621019"},{"nome":"MÔNICA CORRÊA MARAPARA","nomeUrna":"MÔNICA MARAPARA","partido":"MDB","numero":"1577","votos":2,"percentual":0.03,"sqcand":"50001614044"},{"nome":"JOSE RAIMUNDO OLIVEIRA DOS SANTOS","nomeUrna":"ZE RAIMUNDO","partido":"PSB","numero":"4000","votos":2,"percentual":0.03,"sqcand":"50001606022"},{"nome":"EDSON SAMPAIO PIMENTA","nomeUrna":"EDSON PIMENTA","partido":"PDT","numero":"1212","votos":2,"percentual":0.03,"sqcand":"50001620873"},{"nome":"VINICIUS RODRIGUES DE ALCANTARA SILVA","nomeUrna":"VINÍCIUS ALCÂNTARA ","partido":"CIDADANIA","numero":"2323","votos":2,"percentual":0.03,"sqcand":"50001613581"},{"nome":"LEONARDO SILVA PRATES","nomeUrna":"LÉO PRATES","partido":"PDT","numero":"1244","votos":2,"percentual":0.03,"sqcand":"50001620881"},{"nome":"JOÃO CARLOS BACELAR BATISTA","nomeUrna":"BACELAR","partido":"PV","numero":"4343","votos":2,"percentual":0.03,"sqcand":"50001605351"},{"nome":"JOSÉ CERQUEIRA DE SANTANA NETO","nomeUrna":"ZÉ NETO","partido":"PT","numero":"1323","votos":2,"percentual":0.03,"sqcand":"50001605365"},{"nome":"CARLOS MACHADO DE ANDRADE FILHO","nomeUrna":"CACÁ COLCHÕES","partido":"PP","numero":"1156","votos":2,"percentual":0.03,"sqcand":"50001621009"},{"nome":"MARIA FERNANDES MARIGHELLA","nomeUrna":"MARIA MARIGHELLA","partido":"PT","numero":"1331","votos":2,"percentual":0.03,"sqcand":"50001605356"},{"nome":"MARIZE SOUZA CARVALHO","nomeUrna":"PROFESSORA MARIZE CARVALHO","partido":"PT","numero":"1377","votos":2,"percentual":0.03,"sqcand":"50001605358"},{"nome":"CHEYENNE AYALLA BRASIL BARRETO SANT ANNA SOBRINHO","nomeUrna":"CHEYENNE AYALLA","partido":"PCB","numero":"2121","votos":2,"percentual":0.03,"sqcand":"50001719591"},{"nome":"GEAN SOUZA SAMPAIO","nomeUrna":"GEAN","partido":"PATRIOTA","numero":"5111","votos":2,"percentual":0.03,"sqcand":"50001615788"},{"nome":"ANDERSON MACHADO DE JESUS","nomeUrna":"IGOR KANNÁRIO","partido":"UNIÃO","numero":"4499","votos":2,"percentual":0.03,"sqcand":"50001634588"},{"nome":"MARISETE DE SOUSA BASTOS","nomeUrna":"MARISETE","partido":"UNIÃO","numero":"4447","votos":2,"percentual":0.03,"sqcand":"50001634586"},{"nome":"SAULO ROBÉRIO LEAL DIAS","nomeUrna":"SAULO DE ZÉ DO GALO","partido":"UNIÃO","numero":"4454","votos":2,"percentual":0.03,"sqcand":"50001634600"},{"nome":"LAINA CRISÓSTOMO SOUZA DE QUEIROZ","nomeUrna":"LAINA CRISÓSTOMO","partido":"PSOL","numero":"5013","votos":2,"percentual":0.03,"sqcand":"50001600565"},{"nome":"MARCUS VINICIUS DE MORAIS OLIVEIRA","nomeUrna":"DELEGADO MARCUS VINICIUS","partido":"PODE","numero":"1999","votos":2,"percentual":0.03,"sqcand":"50001615369"},{"nome":"ANA RITA TAVARES TEIXEIRA","nomeUrna":"ANA RITA TAVARES","partido":"PODE","numero":"1991","votos":2,"percentual":0.03,"sqcand":"50001615398"},{"nome":"ALIPIO ALVES DE OLIVEIRA JUNIOR","nomeUrna":"ALIPINHO DA DOCE MEL","partido":"SOLIDARIEDADE","numero":"7777","votos":2,"percentual":0.03,"sqcand":"50001619929"},{"nome":"ELMAR JOSE VIEIRA NASCIMENTO","nomeUrna":"ELMAR NASCIMENTO","partido":"UNIÃO","numero":"4433","votos":1,"percentual":0.02,"sqcand":"50001634583"},{"nome":"ORLANDO RODRIGUES FERREIRA","nomeUrna":"ORLANDO FERREIRA","partido":"PSC","numero":"2058","votos":1,"percentual":0.02,"sqcand":"50001600775"},{"nome":"CARLOS TITO MARQUES CORDEIRO","nomeUrna":"TITO","partido":"AVANTE","numero":"7070","votos":1,"percentual":0.02,"sqcand":"50001602951"},{"nome":"DEBORA SANTOS DE SANTANA","nomeUrna":"DÉBORA SANTANA","partido":"AVANTE","numero":"7077","votos":1,"percentual":0.02,"sqcand":"50001602972"},{"nome":"OSNERIO CABRAL SOUZA","nomeUrna":"CABRAL","partido":"PROS","numero":"9044","votos":1,"percentual":0.02,"sqcand":"50001717850"},{"nome":"THIAGO MARTINS NASCIMENTO","nomeUrna":"THIAGO MARTINS","partido":"PL","numero":"2201","votos":1,"percentual":0.02,"sqcand":"50001609343"},{"nome":"ROSEMBERG FREITAS DOS SANTOS","nomeUrna":"ROSEMBERG FREITAS","partido":"PL","numero":"2244","votos":1,"percentual":0.02,"sqcand":"50001609350"},{"nome":"JONECI FERNANDES SOARES","nomeUrna":"PR JONECI FERNANDES","partido":"PL","numero":"2233","votos":1,"percentual":0.02,"sqcand":"50001609355"},{"nome":"LUIS VAZ DE CAMPOS MOREIRA TOURINHO","nomeUrna":"LUÍS TOURINHO","partido":"PL","numero":"2277","votos":1,"percentual":0.02,"sqcand":"50001609374"},{"nome":"EMILIO CARNEIRO BACELAR","nomeUrna":"EMILIO BACELAR","partido":"PL","numero":"2214","votos":1,"percentual":0.02,"sqcand":"50001609364"},{"nome":"GIRLENE SOUZA SANTOS","nomeUrna":"GICA SOUZA","partido":"PSD","numero":"5544","votos":1,"percentual":0.02,"sqcand":"50001607227"},{"nome":"LUANA DO BRASIL PEDRO","nomeUrna":"LUANA DO BRASIL","partido":"MDB","numero":"1511","votos":1,"percentual":0.02,"sqcand":"50001614042"},{"nome":"JOSÉ RAIMUNDO SAMPAIO OLIVEIRA","nomeUrna":"ZÉ RAIMUNDO MANDATO COLETIVO","partido":"MDB","numero":"1515","votos":1,"percentual":0.02,"sqcand":"50001614038"},{"nome":"JOELMA DE JESUS NASCIMENTO","nomeUrna":"JOELMA DE JESUS","partido":"PDT","numero":"1277","votos":1,"percentual":0.02,"sqcand":"50001732923"},{"nome":"ANTENOR ALVES COSTA DE JESUS","nomeUrna":"TENA DO POVÃO","partido":"MDB","numero":"1500","votos":1,"percentual":0.02,"sqcand":"50001614018"},{"nome":"JORGE LUIS ARAUJO COSTA","nomeUrna":"JOTA L","partido":"PDT","numero":"1213","votos":1,"percentual":0.02,"sqcand":"50001620854"},{"nome":"HECKEL HERBERT PEDREIRA SANTOS","nomeUrna":"PEDREIRA","partido":"PTB","numero":"1440","votos":1,"percentual":0.02,"sqcand":"50001645931"},{"nome":"WASHINGTON LUIS AIRES VELOSO","nomeUrna":"WASHINGTON VELOSO","partido":"PDT","numero":"1236","votos":1,"percentual":0.02,"sqcand":"50001620870"},{"nome":"VLADIMIR SANTOS DE SOUZA","nomeUrna":"NEN VLADIMIR","partido":"PDT","numero":"1210","votos":1,"percentual":0.02,"sqcand":"50001620862"},{"nome":"VALTER MOACIR REIS DOS SANTOS","nomeUrna":"VALTER MOACIR","partido":"PDT","numero":"1221","votos":1,"percentual":0.02,"sqcand":"50001620867"},{"nome":"JULIANA SANTOS DA SILVA","nomeUrna":"JULIANA SILVA","partido":"PSB","numero":"4069","votos":1,"percentual":0.02,"sqcand":"50001606047"},{"nome":"CHARLES COSTA DA PAIXÃO","nomeUrna":"CHARLES PAIXÃO","partido":"PSB","numero":"4010","votos":1,"percentual":0.02,"sqcand":"50001606050"},{"nome":"JOSE MARIO SILVA LIMA","nomeUrna":"ZÉ MARIO","partido":"PSB","numero":"4004","votos":1,"percentual":0.02,"sqcand":"50001606031"},{"nome":"EDENIR QUEIROZ SANTOS","nomeUrna":"CABO EDENIR","partido":"CIDADANIA","numero":"2332","votos":1,"percentual":0.02,"sqcand":"50001613565"},{"nome":"ISABELA DE SOUSA PEREIRA","nomeUrna":"ISABELA  SOUSA","partido":"CIDADANIA","numero":"2340","votos":1,"percentual":0.02,"sqcand":"50001613563"},{"nome":"MARLYLDA BARBUDA DOS SANTOS","nomeUrna":"PROF. MARLYLDA","partido":"PP","numero":"1113","votos":1,"percentual":0.02,"sqcand":"50001621023"},{"nome":"TAUÃ FERNANDES JUNQUEIRA","nomeUrna":"TAUÃ","partido":"PT","numero":"1373","votos":1,"percentual":0.02,"sqcand":"50001605362"},{"nome":"LUIZ CLAUDIO LEITE DE OLIVEIRA SANTOS","nomeUrna":"CLAUDIO LEITE-GALEGO ","partido":"PP","numero":"1114","votos":1,"percentual":0.02,"sqcand":"50001621016"},{"nome":"MARTA GUEDES SILVA","nomeUrna":"MARTA DE IRMÃO LÁZARO ","partido":"PT","numero":"1320","votos":1,"percentual":0.02,"sqcand":"50001605363"},{"nome":"ANAILDES CAMPOS SENA","nomeUrna":"ANAILDES","partido":"PT","numero":"1314","votos":1,"percentual":0.02,"sqcand":"50001605360"},{"nome":"GABRIEL JOSE MOURA NUNES SOARES","nomeUrna":"GABRIEL NUNES","partido":"PSD","numero":"5577","votos":1,"percentual":0.02,"sqcand":"50001607226"},{"nome":"THAIS SIQUEIRA DO ROSARIO","nomeUrna":"DELEGADA THAIS","partido":"UNIÃO","numero":"4474","votos":1,"percentual":0.02,"sqcand":"50001634579"},{"nome":"CÁTIA MARIA ARAÚJO RODRIGUES PENHA","nomeUrna":"CÁTIA RODRIGUES","partido":"UNIÃO","numero":"4477","votos":1,"percentual":0.02,"sqcand":"50001634578"},{"nome":"CAROLINE DE ARAÚJO LIMA","nomeUrna":"CAROL LIMA","partido":"PSOL","numero":"5018","votos":1,"percentual":0.02,"sqcand":"50001600554"},{"nome":"JOÃO CARLOS PAOLILO BACELAR FILHO","nomeUrna":"JOÃO CARLOS BACELAR","partido":"PL","numero":"2288","votos":1,"percentual":0.02,"sqcand":"50001609371"},{"nome":"ALINE PEREIRA NUNES","nomeUrna":"ALINE NUNES","partido":"REPUBLICANOS","numero":"1033","votos":1,"percentual":0.02,"sqcand":"50001619839"},{"nome":"JOSE MARCELO DO NASCIMENTO NILO","nomeUrna":"MARCELO NILO","partido":"REPUBLICANOS","numero":"1011","votos":1,"percentual":0.02,"sqcand":"50001619849"},{"nome":"WASHINGTON LUIZ LOPES","nomeUrna":"WASHINGTON LOPES","partido":"REPUBLICANOS","numero":"1025","votos":1,"percentual":0.02,"sqcand":"50001619838"},{"nome":"IGOR ANTONIO MAGALHÃES NOVAIS","nomeUrna":"IGOR MANASSÉS","partido":"REPUBLICANOS","numero":"1099","votos":1,"percentual":0.02,"sqcand":"50001619837"},{"nome":"IVANILDO ROCHA DA SILVA","nomeUrna":"CARTÃO VERMELHO","partido":"REPUBLICANOS","numero":"1045","votos":1,"percentual":0.02,"sqcand":"50001619859"},{"nome":"ANACLECIA FERREIRA DE SOUZA SILVA","nomeUrna":"CLÉCIA FRENTE AMPLA","partido":"SOLIDARIEDADE","numero":"7789","votos":1,"percentual":0.02,"sqcand":"50001619930"},{"nome":"ADRIANA GOMES MARTINS RENA","nomeUrna":"ADRIANA COLETIVO ENFERMAGEM","partido":"SOLIDARIEDADE","numero":"7763","votos":1,"percentual":0.02,"sqcand":"50001619927"}],"deputadosEstaduais":[{"nome":"JOSÉ LUCIANO SANTOS RIBEIRO","nomeUrna":"LUCIANO RIBEIRO","partido":"UNIÃO","numero":"44700","votos":2487,"percentual":43.22,"sqcand":"50001648289"},{"nome":"JOSÉ RAIMUNDO FONTES","nomeUrna":"ZÉ RAIMUNDO FONTES","partido":"PT","numero":"13222","votos":1387,"percentual":24.1,"sqcand":"50001606439"},{"nome":"IVANA TEIXEIRA BASTOS","nomeUrna":"IVANA BASTOS","partido":"PSD","numero":"55456","votos":803,"percentual":13.96,"sqcand":"50001607307"},{"nome":"ROSIVAL LEITE DA SILVA","nomeUrna":"ROSIVAL LEITE","partido":"PT","numero":"13333","votos":339,"percentual":5.89,"sqcand":"50001606387"},{"nome":"JOÃO VITOR DE CASTRO LINO BONFIM","nomeUrna":"VITOR BONFIM","partido":"PV","numero":"43700","votos":131,"percentual":2.28,"sqcand":"50001606406"},{"nome":"SAMUEL SANTANA COUTO JUNIOR","nomeUrna":"SAMUEL JUNIOR","partido":"REPUBLICANOS","numero":"10133","votos":65,"percentual":1.13,"sqcand":"50001619261"},{"nome":"MATHEUS DE OLIVEIRA FERREIRA","nomeUrna":"MATHEUS DE GERALDO JÚNIOR","partido":"MDB","numero":"15777","votos":63,"percentual":1.09,"sqcand":"50001614689"},{"nome":"JOSÉ CARLOS LADEIA","nomeUrna":"DOUTOR LADEIA","partido":"PDT","numero":"12222","votos":44,"percentual":0.76,"sqcand":"50001620948"},{"nome":"FELIPE GABRIEL DUARTE","nomeUrna":"FELIPE DUARTE","partido":"PP","numero":"11111","votos":28,"percentual":0.49,"sqcand":"50001647074"},{"nome":"MARCOS AGUIAR VIANA","nomeUrna":"MARQUINHO VIANA","partido":"PV","numero":"43888","votos":24,"percentual":0.42,"sqcand":"50001606436"},{"nome":"SOANE GALVÃO BARBOSA","nomeUrna":"SOANE GALVÃO","partido":"PSB","numero":"40123","votos":21,"percentual":0.36,"sqcand":"50001605984"},{"nome":"MARIA LUCIA SANTOS ROCHA","nomeUrna":"LÚCIA ROCHA","partido":"MDB","numero":"15888","votos":21,"percentual":0.36,"sqcand":"50001614679"},{"nome":"ANGELO MARIO CERQUEIRA DE ALMEIDA","nomeUrna":"ANGELO ALMEIDA","partido":"PSB","numero":"40100","votos":19,"percentual":0.33,"sqcand":"50001605968"},{"nome":"GLAUBER MAGALHAES MARQUES","nomeUrna":"GLAUBER MAGALHÃES","partido":"SOLIDARIEDADE","numero":"77888","votos":18,"percentual":0.31,"sqcand":"50001620020"},{"nome":"JEAN FABRÍCIO FALCÃO","nomeUrna":"FABRÍCIO","partido":"PC do B","numero":"65333","votos":17,"percentual":0.3,"sqcand":"50001606408"},{"nome":"WALTER SOUZA PEIXOTO JUNIOR","nomeUrna":"WALTER PEIXOTO","partido":"REPUBLICANOS","numero":"10222","votos":17,"percentual":0.3,"sqcand":"50001619263"},{"nome":"EURES RIBEIRO PEREIRA","nomeUrna":"EURES RIBEIRO","partido":"PSD","numero":"55444","votos":15,"percentual":0.26,"sqcand":"50001607295"},{"nome":"JURAILTON DE SOUSA SANTOS","nomeUrna":"JURAILTON SANTOS","partido":"REPUBLICANOS","numero":"10123","votos":14,"percentual":0.24,"sqcand":"50001619298"},{"nome":"FABIOLA MANSUR DE CARVALHO","nomeUrna":"DRA FABIOLA MANSUR","partido":"PSB","numero":"40040","votos":12,"percentual":0.21,"sqcand":"50001605970"},{"nome":"LEANDRO SILVA DE JESUS","nomeUrna":"LEANDRO DE JESUS","partido":"PL","numero":"22333","votos":9,"percentual":0.16,"sqcand":"50001609456"},{"nome":"EMANOEL ARAUJO LIMA","nomeUrna":"MANELÃO","partido":"REPUBLICANOS","numero":"10101","votos":9,"percentual":0.16,"sqcand":"50001619271"},{"nome":"DIEGO CASTRO BARBOSA","nomeUrna":"DR. DIEGO CASTRO","partido":"PL","numero":"22380","votos":8,"percentual":0.14,"sqcand":"50001609451"},{"nome":"ADRIANO ALMEIDA BRAGA","nomeUrna":"ADRIANO BRAGA","partido":"PL","numero":"22800","votos":8,"percentual":0.14,"sqcand":"50001609440"},{"nome":"GILSON SILVA MOURA","nomeUrna":"GILSON MOURA","partido":"PSC","numero":"20888","votos":8,"percentual":0.14,"sqcand":"50001604580"},{"nome":"NELSON SOUZA LEAL","nomeUrna":"NELSON LEAL","partido":"PP","numero":"11555","votos":8,"percentual":0.14,"sqcand":"50001647023"},{"nome":"IRAILSON WARNEAUX DE OLIVEIRA","nomeUrna":"GAZO","partido":"PSB","numero":"40013","votos":7,"percentual":0.12,"sqcand":"50001605965"},{"nome":"RUI OLIVEIRA","nomeUrna":"PROFESSOR RUI","partido":"PC do B","numero":"65222","votos":7,"percentual":0.12,"sqcand":"50001606407"},{"nome":"HILTON BARROS COELHO","nomeUrna":"HILTON COELHO","partido":"PSOL","numero":"50150","votos":6,"percentual":0.1,"sqcand":"50001600622"},{"nome":"RICARDO JASSON MAGALHÃES MACHADO DO CARMO","nomeUrna":"RICARDO MACHADO","partido":"PT","numero":"13555","votos":6,"percentual":0.1,"sqcand":"50001606440"},{"nome":"MARIA OLIVIA SANTANA","nomeUrna":"OLIVIA SANTANA","partido":"PC do B","numero":"65500","votos":5,"percentual":0.09,"sqcand":"50001606433"},{"nome":"PEDRO PAULO TAVARES BATISTA DE MELLO E SILVA","nomeUrna":"PEDRO TAVARES","partido":"UNIÃO","numero":"44000","votos":5,"percentual":0.09,"sqcand":"50001648327"},{"nome":"LUCIANO SIMOES DE CASTRO BARBOSA FILHO","nomeUrna":"LUCIANO SIMÕES","partido":"UNIÃO","numero":"44123","votos":5,"percentual":0.09,"sqcand":"50001648313"},{"nome":"MARCELO DANTAS VEIGA","nomeUrna":"MARCELINHO VEIGA","partido":"UNIÃO","numero":"44111","votos":5,"percentual":0.09,"sqcand":"50001648309"},{"nome":"MÁRCIA VIVIANE DE ARAÚJO SAMPAIO","nomeUrna":"VIVIANE","partido":"PT","numero":"13300","votos":5,"percentual":0.09,"sqcand":"50001606423"},{"nome":"MARCELO SAMPAIO OLIVEIRA","nomeUrna":"MARCELO OLIVEIRA","partido":"PSB","numero":"40444","votos":5,"percentual":0.09,"sqcand":"50001605976"},{"nome":"NATALIA CRISTINA BRITO DOS SANTOS","nomeUrna":"TINA FORÇA E CORAGEM","partido":"UNIÃO","numero":"44004","votos":4,"percentual":0.07,"sqcand":"50001727555"},{"nome":"VITOR VIANA PARANHOS DE AZEVEDO","nomeUrna":"VITOR AZEVEDO","partido":"PL","numero":"22222","votos":4,"percentual":0.07,"sqcand":"50001609449"},{"nome":"JOSE SIRINEU FILGUEIRAS BARBOSA","nomeUrna":"MISSIONÁRIO SIRINEU BARBOSA","partido":"REPUBLICANOS","numero":"10777","votos":4,"percentual":0.07,"sqcand":"50001619282"},{"nome":"JAILSON FERREIRA SANTOS","nomeUrna":"TENENTE JAILSON FERREIRA","partido":"PTB","numero":"14500","votos":4,"percentual":0.07,"sqcand":"50001696401"},{"nome":"CLEA MALTA DE OLIVEIRA ANDRADE","nomeUrna":"CLÉA MALTA ","partido":"CIDADANIA","numero":"23000","votos":4,"percentual":0.07,"sqcand":"50001613915"},{"nome":"CLAYTON COSTA OLIVEIRA","nomeUrna":"CLAYTON COSTA ","partido":"CIDADANIA","numero":"23059","votos":4,"percentual":0.07,"sqcand":"50001613910"},{"nome":"LUIS VASCONCELOS MELO","nomeUrna":"CAPITÃO VASCONCELOS","partido":"PSC","numero":"20999","votos":4,"percentual":0.07,"sqcand":"50001604568"},{"nome":"MÁRIO MARTINELLI JÚNIOR","nomeUrna":"MÁRIO MARTINELLI","partido":"PC do B","numero":"65777","votos":4,"percentual":0.07,"sqcand":"50001606434"},{"nome":"LUCIANO ARAUJO DE OLIVEIRA","nomeUrna":"LUCIANO ARAUJO","partido":"SOLIDARIEDADE","numero":"77777","votos":3,"percentual":0.05,"sqcand":"50001620001"},{"nome":"MARCO PRISCO CALDAS MACHADO","nomeUrna":"SOLDADO PRISCO","partido":"UNIÃO","numero":"44190","votos":3,"percentual":0.05,"sqcand":"50001648333"},{"nome":"CRISOSTOMO ANTONIO LIMA","nomeUrna":"ZÓ","partido":"PC do B","numero":"65456","votos":3,"percentual":0.05,"sqcand":"50001606432"},{"nome":"MARIA CAROLINA REBOUCAS SANTOS FIUZA","nomeUrna":"CAROL DOS ANIMAIS","partido":"SOLIDARIEDADE","numero":"77000","votos":3,"percentual":0.05,"sqcand":"50001620003"},{"nome":"JOSEFA PEREIRA DOS SANTOS","nomeUrna":"DRA JOSY ZEFA","partido":"REPUBLICANOS","numero":"10020","votos":3,"percentual":0.05,"sqcand":"50001619283"},{"nome":"BRUNO FERREIRA DE OLIVEIRA","nomeUrna":"DELEGADO BRUNO FERREIRA","partido":"PL","numero":"22269","votos":3,"percentual":0.05,"sqcand":"50001609467"},{"nome":"HELIO FRANCISCO ROCHA LINO","nomeUrna":"DR. HÉLIO ROCHA","partido":"MDB","numero":"15222","votos":3,"percentual":0.05,"sqcand":"50001614702"},{"nome":"VERA LÚCIA DA CRUZ BARBOSA","nomeUrna":"LUCINHA DO MST","partido":"PT","numero":"13100","votos":3,"percentual":0.05,"sqcand":"50001606399"},{"nome":"EUCLIDES NUNES FERNANDES","nomeUrna":"EUCLIDES FERNANDES","partido":"PT","numero":"13123","votos":2,"percentual":0.03,"sqcand":"50001606438"},{"nome":"EDIMARIO DAS NEVES DAMASCENO","nomeUrna":"NONON","partido":"UNIÃO","numero":"44456","votos":2,"percentual":0.03,"sqcand":"50001648331"},{"nome":"ADEMILTON DE JESUS","nomeUrna":"DÉNIS DE DOMINGAS","partido":"UNIÃO","numero":"44544","votos":2,"percentual":0.03,"sqcand":"50001648280"},{"nome":"CARLOS ROBSON RODRIGUES DA SILVA","nomeUrna":"ROBINHO","partido":"UNIÃO","numero":"44144","votos":2,"percentual":0.03,"sqcand":"50001648336"},{"nome":"JORGE AUGUSTO PORTELA BRAGA","nomeUrna":" BRAGA","partido":"PT","numero":"13420","votos":2,"percentual":0.03,"sqcand":"50001606441"},{"nome":"UBIRAJARA DA SILVA RAMOS COROA","nomeUrna":"BIRA COROA","partido":"PT","numero":"13613","votos":2,"percentual":0.03,"sqcand":"50001606397"},{"nome":"MARCELINO ANTÔNIO MARTINS GALO","nomeUrna":"MARCELINO GALO","partido":"PT","numero":"13140","votos":2,"percentual":0.03,"sqcand":"50001606398"},{"nome":"CEZAR FERREIRA LEITE","nomeUrna":"CEZAR LEITE","partido":"PSC","numero":"20022","votos":2,"percentual":0.03,"sqcand":"50001604557"},{"nome":"JHONATAS LIMA MONTEIRO","nomeUrna":"JHONATAS MONTEIRO","partido":"PSOL","numero":"50050","votos":2,"percentual":0.03,"sqcand":"50001600626"},{"nome":"EDUARDO SEIXAS DE SALLES","nomeUrna":"EDUARDO SALLES","partido":"PP","numero":"11222","votos":2,"percentual":0.03,"sqcand":"50001647028"},{"nome":"TIAGO BRANDAO CORREIA","nomeUrna":"TIAGO CORREIA","partido":"PSDB","numero":"45556","votos":2,"percentual":0.03,"sqcand":"50001613902"},{"nome":"PATRICIA GRANJA OLIVEIRA VIEIRA LIMA","nomeUrna":"BRANCA PATRICIA","partido":"PC do B","numero":"65555","votos":2,"percentual":0.03,"sqcand":"50001606412"},{"nome":"ROBINSON SANTOS ALMEIDA","nomeUrna":"ROBINSON","partido":"PT","numero":"13500","votos":1,"percentual":0.02,"sqcand":"50001606417"},{"nome":"MOIZÉS BARBOSA DA COSTA","nomeUrna":"MOIZÉS BARBOSA","partido":"UNIÃO","numero":"44122","votos":1,"percentual":0.02,"sqcand":"50001648295"},{"nome":"ABIMAEL GOMES DE LIMA","nomeUrna":"DR ABIMAEL","partido":"UNIÃO","numero":"44400","votos":1,"percentual":0.02,"sqcand":"50001648279"},{"nome":"MARIA JOSEFA MADERA ARREAL","nomeUrna":"NENA ARREAL","partido":"UNIÃO","numero":"44788","votos":1,"percentual":0.02,"sqcand":"50001648332"},{"nome":"GLAZIELY SALES DO NASCIMENTO","nomeUrna":"GRAZY SALES","partido":"UNIÃO","numero":"44225","votos":1,"percentual":0.02,"sqcand":"50001648286"},{"nome":"JOAQUIM DE OLIVEIRA CUNHA","nomeUrna":"JOAQUIM CUNHA","partido":"UNIÃO","numero":"44789","votos":1,"percentual":0.02,"sqcand":"50001648328"},{"nome":"ALAN EDUARDO SANCHES DOS SANTOS","nomeUrna":"ALAN SANCHES","partido":"UNIÃO","numero":"44100","votos":1,"percentual":0.02,"sqcand":"50001648281"},{"nome":"EWERTON CARNEIRO DA COSTA","nomeUrna":"PASTOR TOM","partido":"SOLIDARIEDADE","numero":"77444","votos":1,"percentual":0.02,"sqcand":"50001620031"},{"nome":"MANUEL AZEVEDO ROCHA","nomeUrna":"MANUEL ROCHA","partido":"UNIÃO","numero":"44222","votos":1,"percentual":0.02,"sqcand":"50001648303"},{"nome":"EDMILSON DA SILVA EVANGELISTA","nomeUrna":"NEGUINHO DO SINDICATO","partido":"PT","numero":"13258","votos":1,"percentual":0.02,"sqcand":"50001606420"},{"nome":"NILZA DA SILVA MARTINS","nomeUrna":"PROFESSORA NILZA","partido":"PT","numero":"13520","votos":1,"percentual":0.02,"sqcand":"50001606443"},{"nome":"CEUCI DE LIMA XAVIER NUNES","nomeUrna":"DR. CEUCI","partido":"PT","numero":"13192","votos":1,"percentual":0.02,"sqcand":"50001606418"},{"nome":"MARIO AUGUSTO DE ALMEIDA NETO","nomeUrna":"JACÓ","partido":"PT","numero":"13110","votos":1,"percentual":0.02,"sqcand":"50001606414"},{"nome":"RADIOVALDO COSTA SANTOS","nomeUrna":"RADIOVALDO","partido":"PT","numero":"13050","votos":1,"percentual":0.02,"sqcand":"50001606421"},{"nome":"RUBENALVA DOS SANTOS LIMA","nomeUrna":"RUBENALVA LIMA","partido":"PL","numero":"22200","votos":1,"percentual":0.02,"sqcand":"50001609473"},{"nome":"EDILSON GUSMÃO PEREIRA","nomeUrna":"EDILSON GUSMÃO","partido":"PL","numero":"22015","votos":1,"percentual":0.02,"sqcand":"50001609454"},{"nome":"IAGO COSTA DE CARVALHO","nomeUrna":"IAGO DE CARVALHO","partido":"PL","numero":"22777","votos":1,"percentual":0.02,"sqcand":"50001609452"},{"nome":"MANOEL RODRIGUES FILHO","nomeUrna":"CARCARÁ DO SERTÃO","partido":"REPUBLICANOS","numero":"10111","votos":1,"percentual":0.02,"sqcand":"50001619289"},{"nome":"MARIO SERGIO DOS SANTOS","nomeUrna":"PASTOR SERGIO SERTAO","partido":"PTB","numero":"14110","votos":1,"percentual":0.02,"sqcand":"50001696440"},{"nome":"EDIVALDO BARRETO DOS SANTOS","nomeUrna":"EDIVALDO CIGANO","partido":"PTB","numero":"14580","votos":1,"percentual":0.02,"sqcand":"50001696414"},{"nome":"RITA DE CÁSSIA DE ARAUJO","nomeUrna":"RITA DE CÁSSIA","partido":"PL","numero":"22221","votos":1,"percentual":0.02,"sqcand":"50001609464"},{"nome":"MARCOS SANTOS DA SILVA","nomeUrna":"MARCOLA DO GRAU","partido":"PSC","numero":"20244","votos":1,"percentual":0.02,"sqcand":"50001604583"},{"nome":"ADJALBAS PEREIRA SOUSA","nomeUrna":"ADJALBAS PEREIRA","partido":"PSC","numero":"20654","votos":1,"percentual":0.02,"sqcand":"50001604585"},{"nome":"PAULO FERNANDO RANGEL DE LIMA","nomeUrna":"PAULO RANGEL","partido":"PT","numero":"13113","votos":1,"percentual":0.02,"sqcand":"50001606403"},{"nome":"ROMULO CARVALHO FONTOURA","nomeUrna":"RÔMULO FONTOURA","partido":"REDE","numero":"18555","votos":1,"percentual":0.02,"sqcand":"50001600603"},{"nome":"ANA CLARA MOREIRA BASTOS PEREIRA","nomeUrna":"CLARA","partido":"MDB","numero":"15555","votos":1,"percentual":0.02,"sqcand":"50001614667"},{"nome":"AMADEU DE JESUS OLIVEIRA","nomeUrna":"AMADEU OLIVEIRA","partido":"MDB","numero":"15333","votos":1,"percentual":0.02,"sqcand":"50001614694"},{"nome":"HASSAN ANDRADE IOSSEF","nomeUrna":"HASSAN DE ZÉ COCÁ","partido":"PP","numero":"11122","votos":1,"percentual":0.02,"sqcand":"50001647026"},{"nome":"JOSE EDUARDO MENDONCA DE ALENCAR","nomeUrna":"EDUARDO ALENCAR","partido":"PSD","numero":"55333","votos":1,"percentual":0.02,"sqcand":"50001607296"},{"nome":"ANGELO MARIO CORONEL DE AZEVEDO MARTINS II","nomeUrna":"ANGELO CORONEL FILHO","partido":"PSD","numero":"55255","votos":1,"percentual":0.02,"sqcand":"50001607294"},{"nome":"NEUSA CADORE","nomeUrna":"NEUSA CADORE","partido":"PT","numero":"13690","votos":1,"percentual":0.02,"sqcand":"50001606395"},{"nome":"DANIEL COUTINHO DO ROSARIO","nomeUrna":"DANIEL COUTINHO","partido":"PDT","numero":"12322","votos":1,"percentual":0.02,"sqcand":"50001620946"},{"nome":"CLARISSA CRISTINA OLIVEIRA GONÇALVES","nomeUrna":"CRISTINA GONÇALVES","partido":"PSB","numero":"40044","votos":1,"percentual":0.02,"sqcand":"50001605977"},{"nome":"ANDERSON SANTOS ROCHA","nomeUrna":"ANDERSON ROCHA","partido":"PDT","numero":"12888","votos":1,"percentual":0.02,"sqcand":"50001620952"},{"nome":"MARCONE AMARAL COSTA JUNIOR","nomeUrna":"MARCONE AMARAL","partido":"PSD","numero":"55123","votos":1,"percentual":0.02,"sqcand":"50001607304"},{"nome":"SILVIO HUMBERTO DOS PASSOS CUNHA","nomeUrna":"SILVIO HUMBERTO","partido":"PSB","numero":"40012","votos":1,"percentual":0.02,"sqcand":"50001605962"},{"nome":"ROBSON RIBEIRO DAS NEVES","nomeUrna":"ROBSON RIBEIRO","partido":"PMN","numero":"33321","votos":1,"percentual":0.02,"sqcand":"50001597078"},{"nome":"YVONILTON BORGES GONÇALVES","nomeUrna":"VONCA GONÇALVES","partido":"PP","numero":"11556","votos":1,"percentual":0.02,"sqcand":"50001647056"},{"nome":"EDIVALDO SILVA PINHO FILHO","nomeUrna":"EDIVALDINHO","partido":"PP","numero":"11334","votos":1,"percentual":0.02,"sqcand":"50001647050"},{"nome":"EDCARLOS DA CONCEIÇÃO SANTOS","nomeUrna":"EDCITY","partido":"PP","numero":"11012","votos":1,"percentual":0.02,"sqcand":"50001647058"},{"nome":"MAIZA FERNANDES LEITE","nomeUrna":"MAÍZA LEÃO","partido":"PP","numero":"11233","votos":1,"percentual":0.02,"sqcand":"50001647033"},{"nome":"ELIVALDO DA SILVA COSTA","nomeUrna":"LIVA DA ROSA DO PRADO","partido":"PP","numero":"11144","votos":1,"percentual":0.02,"sqcand":"50001647051"},{"nome":"MAURICIO GONÇALVES TRINDADE","nomeUrna":"MAURICIO TRINDADE","partido":"PP","numero":"11300","votos":1,"percentual":0.02,"sqcand":"50001647069"}]}