{"populacao":3907,"votosValidos":2766,"abstencao":17.48,"prefeito":{"nome":"EDER ELÓI ALVES PENA","nomeUrna":"EDER DE TIQUIM","partido":"PSD","numero":"55","votos":2766,"percentual":100.0,"situacao":"Eleito","sqcand":"130002255227","vice":"ANTÔNIO JULIÃO LOPES","viceNomeUrna":"JULIÃO","partidoVice":"PSD","sqcandVice":"130002255226","coligacao":"PSD / MDB / UNIÃO / PC do B / PT / PV"},"vereadores":[{"nome":"ROMAR CHAVES CANAZART","nomeUrna":"ROMAR CANAZART","partido":"UNIÃO","numero":"44111","votos":265,"percentual":8.45,"situacao":"Eleito por QP","sqcand":"130002199291"},{"nome":"JOÃO DEHON ALVES COUTO","nomeUrna":"DEHON COUTO","partido":"PSD","numero":"55115","votos":255,"percentual":8.13,"situacao":"Eleito por QP","sqcand":"130002254954"},{"nome":"GERALDO EUSTÁQUIO NARDY","nomeUrna":"TAQUINHO NARDY","partido":"PSD","numero":"55610","votos":225,"percentual":7.17,"situacao":"Eleito por QP","sqcand":"130002254949"},{"nome":"PEDRO VAGNO PEREIRA","nomeUrna":"PEDRINHO DE PEDROCA","partido":"PODE","numero":"20000","votos":219,"percentual":6.98,"situacao":"Eleito por QP","sqcand":"130002150537"},{"nome":"JOSÉ DA PURIFICAÇÃO VIEIRA","nomeUrna":"LULU VIEIRA","partido":"PSD","numero":"55122","votos":205,"percentual":6.54,"situacao":"Eleito por QP","sqcand":"130002254955"},{"nome":"NONATO XARLEN MANTENA NORBERTO","nomeUrna":"NONATO","partido":"PSD","numero":"55244","votos":183,"percentual":5.84,"situacao":"Eleito por média","sqcand":"130002377591"},{"nome":"ARLINDO MARTINS FLORENTINO","nomeUrna":"ARLINDO DE ZÉ TIBUCINHO","partido":"UNIÃO","numero":"44756","votos":181,"percentual":5.77,"situacao":"Eleito por QP","sqcand":"130002199289"},{"nome":"REINALDO PEREIRA VIANA","nomeUrna":"REINALDO VIANA","partido":"UNIÃO","numero":"44610","votos":176,"percentual":5.61,"situacao":"Eleito por média","sqcand":"130002199292"},{"nome":"RENATO MIRANDA MARQUES","nomeUrna":"RENATO MARQUES","partido":"PSD","numero":"55123","votos":131,"percentual":4.18,"situacao":"Suplente","sqcand":"130002254956"},{"nome":"EDMILSON JOSÉ LOPES","nomeUrna":"EDMILSON","partido":"PODE","numero":"20666","votos":127,"percentual":4.05,"situacao":"Suplente","sqcand":"130002150535"},{"nome":"MAX VINÍCIUS RIBEIRO CARNEIRO","nomeUrna":"VINÍCIUS DE ZÉ MARIA","partido":"PT","numero":"13555","votos":124,"percentual":3.95,"situacao":"Eleito por QP","sqcand":"130002254973"},{"nome":"ANÍSIO ELISIÁRIO PAIVA RIBEIRO","nomeUrna":"ANÍSIO PAIVA","partido":"UNIÃO","numero":"44123","votos":87,"percentual":2.77,"situacao":"Suplente","sqcand":"130002199288"},{"nome":"JOSÉ RAIMUNDO LOPES","nomeUrna":"ZÉ RAIMUNDO DA CALIFÓRNIA","partido":"PT","numero":"13610","votos":87,"percentual":2.77,"situacao":"Suplente","sqcand":"130002254974"},{"nome":"FLÁVIO SOARES MIRANDA","nomeUrna":"FLAVINHO DE LADINHO DE QUINCA","partido":"UNIÃO","numero":"44440","votos":81,"percentual":2.58,"situacao":"Suplente","sqcand":"130002199290"},{"nome":"ROSÁRIA ISIDORIA DOS SANTOS BARCELOS","nomeUrna":"ROSÁRIA DE QUINCA PORTUGUÊS","partido":"UNIÃO","numero":"44000","votos":69,"percentual":2.2,"situacao":"Suplente","sqcand":"130002199293"},{"nome":"ANTÔNIO FRADE DE OLIVEIRA","nomeUrna":"ANTÔNIO DO CABOCLO","partido":"PSD","numero":"55300","votos":68,"percentual":2.17,"situacao":"Suplente","sqcand":"130002254953"},{"nome":"MARIA DO CARMO APARECIDA PEREIRA","nomeUrna":"DUCARMO DE DIM MÓL","partido":"UNIÃO","numero":"44444","votos":67,"percentual":2.14,"situacao":"Suplente","sqcand":"130002199287"},{"nome":"JOÃO SCHITINI GOMES NETO","nomeUrna":"JOÃOZINHO DE QUINZOLA","partido":"PODE","numero":"20444","votos":66,"percentual":2.1,"situacao":"Suplente","sqcand":"130002150541"},{"nome":"SAMUEL HENRIQUE DA SILVA ROSA","nomeUrna":"SAMUEL ROSA","partido":"PT","numero":"13123","votos":49,"percentual":1.56,"situacao":"Suplente","sqcand":"130002254968"},{"nome":"HIGO PAIVA SCHITINE","nomeUrna":"HIGO DE ZÉ MIGUEL","partido":"PODE","numero":"20222","votos":49,"percentual":1.56,"situacao":"Suplente","sqcand":"130002150536"},{"nome":"MARCIO ROBERTO DE OLIVEIRA","nomeUrna":"MARCINHO DE SILVIO","partido":"PODE","numero":"20123","votos":48,"percentual":1.53,"situacao":"Suplente","sqcand":"130002150538"},{"nome":"FABIO JUNIO BARROSO DOS SANTOS","nomeUrna":"FABINHO","partido":"UNIÃO","numero":"44680","votos":45,"percentual":1.43,"situacao":"Suplente","sqcand":"130002199285"},{"nome":"DOLGLAS MARCOS ANICETO","nomeUrna":"DOLGLAS DE PEDURO","partido":"PT","numero":"13777","votos":41,"percentual":1.31,"situacao":"Suplente","sqcand":"130002254969"},{"nome":"FELIPE AUGUSTO NERI","nomeUrna":"FILIPE DO SOUZA","partido":"UNIÃO","numero":"44555","votos":31,"percentual":0.99,"situacao":"Suplente","sqcand":"130002199286"},{"nome":"LAURA MARIA TOMAZ DA SILVA","nomeUrna":"LAURA DE DUDU","partido":"PSD","numero":"55015","votos":30,"percentual":0.96,"situacao":"Suplente","sqcand":"130002254952"},{"nome":"EDIVÂNIA APARECIDA EVANGELISTA SANTOS","nomeUrna":"EDIVÂNIA","partido":"PT","numero":"13300","votos":27,"percentual":0.86,"situacao":"Suplente","sqcand":"130002254975"},{"nome":"GEOVANO SANTANA MOREIRA","nomeUrna":"GEL DE TATÁ","partido":"PODE","numero":"20100","votos":25,"percentual":0.8,"situacao":"Suplente","sqcand":"130002150540"},{"nome":"FERNANDA CRISTINA DA FONSECA","nomeUrna":"FERNANDA DE PLÍNIO","partido":"UNIÃO","numero":"44333","votos":20,"percentual":0.64,"situacao":"Suplente","sqcand":"130002199294"},{"nome":"JANAÍNA FERREIRA DE ASSIS","nomeUrna":"JANAÍNA ASSIS","partido":"PT","numero":"13133","votos":14,"percentual":0.45,"situacao":"Suplente","sqcand":"130002254970"},{"nome":"ITAMAR MARCIANO DA SILVA","nomeUrna":"ITAMAR","partido":"PT","numero":"13666","votos":12,"percentual":0.38,"situacao":"Suplente","sqcand":"130002254976"},{"nome":"JANETE ISABEL MOREIRA","nomeUrna":"JANETE DE VICENTE","partido":"PSD","numero":"55455","votos":11,"percentual":0.35,"situacao":"Suplente","sqcand":"130002254951"},{"nome":"SANDRA REGINA DA SILVA","nomeUrna":"SANDRA DO POVO","partido":"PSD","numero":"55555","votos":11,"percentual":0.35,"situacao":"Suplente","sqcand":"130002254950"},{"nome":"CARLOS GOMES FAUSTINO","nomeUrna":"CARLINHOS DE FULÔ","partido":"PT","numero":"13999","votos":8,"percentual":0.26,"situacao":"Suplente","sqcand":"130002254972"},{"nome":"CARMEM LUCIA MAGALHÃES DE OLIVEIRA","nomeUrna":"CARMEN LUCIA DE JOÃO BOSCO","partido":"PODE","numero":"20111","votos":8,"percentual":0.26,"situacao":"Suplente","sqcand":"130002342658"},{"nome":"GERALDA DE FÁTIMA SANTOS","nomeUrna":"GERALDA NORA DE JAIME","partido":"PODE","numero":"20126","votos":5,"percentual":0.16,"situacao":"Suplente","sqcand":"130002150543"},{"nome":"CARLOS ROBERTO DOS SANTOS","nomeUrna":"CARLINHO BEIÇOLA","partido":"PT","numero":"13345","votos":4,"percentual":0.13,"situacao":"Suplente","sqcand":"130002254967"},{"nome":"EDILSON RESENDE CANAZART","nomeUrna":"EDILSON CANAZART","partido":"PSD","numero":"55655","votos":3,"percentual":0.1,"situacao":"Suplente","sqcand":"130002254948"},{"nome":"GERALDA MARGARIDA DOS SANTOS","nomeUrna":"NENZINHA","partido":"PODE","numero":"20610","votos":3,"percentual":0.1,"situacao":"Suplente","sqcand":"130002150542"},{"nome":"ELISIANE VANUSA BARRETO","nomeUrna":"LISA DE ZÉ BARRETO","partido":"PT","numero":"13333","votos":2,"percentual":0.06,"situacao":"Suplente","sqcand":"130002254971"}],"senadores":[{"nome":"ALEXANDRE SILVEIRA DE OLIVEIRA","nomeUrna":"ALEXANDRE SILVEIRA","partido":"PSD","numero":"555","votos":1394,"percentual":61.68,"sqcand":"130001713762"},{"nome":"CLEITON GONTIJO DE AZEVEDO","nomeUrna":"CLEITINHO","partido":"PSC","numero":"200","votos":596,"percentual":26.37,"sqcand":"130001671677"},{"nome":"MARCELO GUILHERME DE ARO FERREIRA","nomeUrna":"MARCELO ARO","partido":"PP","numero":"111","votos":255,"percentual":11.28,"sqcand":"130001644285"},{"nome":"BRUNO MARTUCHELE DE SALES","nomeUrna":"BRUNO MIRANDA","partido":"PDT","numero":"123","votos":7,"percentual":0.31,"sqcand":"130001644706"},{"nome":"SARA RAYANNE SILVA AZEVEDO","nomeUrna":"SARA AZEVEDO","partido":"PSOL","numero":"500","votos":5,"percentual":0.22,"sqcand":"130001615093"},{"nome":"ALTAMIRO ALVES DA SILVA","nomeUrna":"PASTOR ALTAMIRO ALVES","partido":"PTB","numero":"142","votos":3,"percentual":0.13,"sqcand":"130001610978"}],"deputadosFederais":[{"nome":"RODRIGO BATISTA DE CASTRO","nomeUrna":"RODRIGO DE CASTRO","partido":"UNIÃO","numero":"4450","votos":1253,"percentual":51.33,"sqcand":"130001607620"},{"nome":"IGOR TARCIANO TIMO","nomeUrna":"IGOR TIMO","partido":"PODE","numero":"1999","votos":299,"percentual":12.25,"sqcand":"130001634117"},{"nome":"EUCLYDES MARCOS PETTERSEN NETO","nomeUrna":"EUCLYDES PETTERSEN","partido":"PSC","numero":"2015","votos":212,"percentual":8.68,"sqcand":"130001671754"},{"nome":"DUARTE EUSTÁQUIO GONÇALVES JUNIOR","nomeUrna":"DUARTE JÚNIOR","partido":"PSC","numero":"2000","votos":118,"percentual":4.83,"sqcand":"130001671765"},{"nome":"NIKOLAS FERREIRA DE OLIVEIRA","nomeUrna":"NIKOLAS FERREIRA","partido":"PL","numero":"2222","votos":100,"percentual":4.1,"sqcand":"130001611005"},{"nome":"JOÃO CARLOS SIQUEIRA","nomeUrna":"PADRE JOÃO","partido":"PT","numero":"1315","votos":88,"percentual":3.61,"sqcand":"130001607276"},{"nome":"HERCILIO ARAUJO DINIZ FILHO","nomeUrna":"HERCILIO COELHO DINIZ","partido":"MDB","numero":"1515","votos":23,"percentual":0.94,"sqcand":"130001668912"},{"nome":"DJALMA AUGUSTO GOMES BASTOS","nomeUrna":"DJALMA BASTOS","partido":"PSD","numero":"5590","votos":18,"percentual":0.74,"sqcand":"130001604307"},{"nome":"ANDRE LUIS GASPAR JANONES","nomeUrna":"ANDRÉ JANONES","partido":"AVANTE","numero":"7040","votos":15,"percentual":0.61,"sqcand":"130001608227"},{"nome":"BRUNO SOUZA FARIAS","nomeUrna":"BRUNO FARIAS","partido":"AVANTE","numero":"7077","votos":15,"percentual":0.61,"sqcand":"130001603602"},{"nome":"DUDA SALABERT ROSA","nomeUrna":"DUDA SALABERT","partido":"PDT","numero":"1212","votos":13,"percentual":0.53,"sqcand":"130001606697"},{"nome":"MIGUEL ÂNGELO MONTEIRO ANDRADE","nomeUrna":"MIGUEL ÂNGELO","partido":"PT","numero":"1339","votos":13,"percentual":0.53,"sqcand":"130001607253"},{"nome":"ROGÉRIO CORREIA DE MOURA BAPTISTA","nomeUrna":"ROGÉRIO CORREIA","partido":"PT","numero":"1313","votos":12,"percentual":0.49,"sqcand":"130001607258"},{"nome":"RAFAEL REZENDE DE OLIVEIRA","nomeUrna":"PROFESSOR RAFAEL","partido":"PSOL","numero":"5078","votos":12,"percentual":0.49,"sqcand":"130001615154"},{"nome":"ALESSANDRA SILVA RIBEIRO","nomeUrna":"ALÊ SILVA","partido":"REPUBLICANOS","numero":"1000","votos":11,"percentual":0.45,"sqcand":"130001619742"},{"nome":"TIAGO ROGERIO DA SILVA FOGAÇA DE AGUIAR","nomeUrna":"TIAGO FOGAÇA","partido":"PATRIOTA","numero":"5122","votos":11,"percentual":0.45,"sqcand":"130001596025"},{"nome":"REGINALDO LÁZARO DE OLIVEIRA LOPES","nomeUrna":"REGINALDO LOPES","partido":"PT","numero":"1312","votos":10,"percentual":0.41,"sqcand":"130001607277"},{"nome":"STEFANO AGUIAR DOS SANTOS","nomeUrna":"STEFANO AGUIAR","partido":"PSD","numero":"5544","votos":7,"percentual":0.29,"sqcand":"130001604328"},{"nome":"FREDERICO BORGES DA COSTA","nomeUrna":"FRED COSTA","partido":"PATRIOTA","numero":"5133","votos":6,"percentual":0.25,"sqcand":"130001596009"},{"nome":"VILSON LUIZ DA SILVA","nomeUrna":"VILSON DA FETAEMG","partido":"PSB","numero":"4057","votos":6,"percentual":0.25,"sqcand":"130001613225"},{"nome":"LEONARDO SILVEIRA DE CASTRO PIRES","nomeUrna":"LEO BURGUES","partido":"UNIÃO","numero":"4455","votos":6,"percentual":0.25,"sqcand":"130001607631"},{"nome":"EDUARDO LUIZ BARROS BARBOSA","nomeUrna":"EDUARDO BARBOSA","partido":"PSDB","numero":"4535","votos":5,"percentual":0.2,"sqcand":"130001613364"},{"nome":"HERMES FREITAS DA COSTA","nomeUrna":"HERMES NORATINHO","partido":"PODE","numero":"1970","votos":5,"percentual":0.2,"sqcand":"130001634134"},{"nome":"LUIS HENRIQUE DE OLIVEIRA RESENDE","nomeUrna":"LUIS TIBÉ","partido":"AVANTE","numero":"7070","votos":4,"percentual":0.16,"sqcand":"130001603563"},{"nome":"MÁRIO LÚCIO HERINGER","nomeUrna":"DR MÁRIO HERINGER","partido":"PDT","numero":"1234","votos":4,"percentual":0.16,"sqcand":"130001606709"},{"nome":"PEDRO DOSHIKAZU PIANCHAO AIHARA","nomeUrna":"PEDRO AIHARA","partido":"PATRIOTA","numero":"5193","votos":4,"percentual":0.16,"sqcand":"130001596021"},{"nome":"SANDRO DRUMOND MACHADO","nomeUrna":"SANDRO FUSCA","partido":"PMN","numero":"3366","votos":4,"percentual":0.16,"sqcand":"130001606180"},{"nome":"FERNANDO DAMATA PIMENTEL","nomeUrna":"FERNANDO PIMENTEL","partido":"PT","numero":"1355","votos":4,"percentual":0.16,"sqcand":"130001607241"},{"nome":"MARINICE SANTOS","nomeUrna":"MARA","partido":"PSDB","numero":"4550","votos":4,"percentual":0.16,"sqcand":"130001613345"},{"nome":"CÉLIA NUNES CORREA","nomeUrna":"CÉLIA XAKRIABÁ","partido":"PSOL","numero":"5088","votos":4,"percentual":0.16,"sqcand":"130001615168"},{"nome":"RITA DE CÁSSIA SOUZA CARVALHO","nomeUrna":"CASSINHA CARVALHO","partido":"UNIÃO","numero":"4456","votos":4,"percentual":0.16,"sqcand":"130001607638"},{"nome":"ROSÂNGELA DE OLIVEIRA CAMPOS REIS","nomeUrna":"ROSÂNGELA REIS","partido":"PL","numero":"2215","votos":4,"percentual":0.16,"sqcand":"130001611025"},{"nome":"LINCOLN DINIZ PORTELA","nomeUrna":"LINCOLN PORTELA","partido":"PL","numero":"2233","votos":4,"percentual":0.16,"sqcand":"130001611001"},{"nome":"PAULO ABI-ACKEL","nomeUrna":"PAULO ABI-ACKEL","partido":"PSDB","numero":"4545","votos":3,"percentual":0.12,"sqcand":"130001613373"},{"nome":"WELITON FERNANDES PRADO","nomeUrna":"WELITON PRADO","partido":"PROS","numero":"9090","votos":3,"percentual":0.12,"sqcand":"130001607568"},{"nome":"GESINEY CAMPOS MOURA","nomeUrna":"GESINEY","partido":"PL","numero":"2256","votos":3,"percentual":0.12,"sqcand":"130001610995"},{"nome":"AÉCIO NEVES DA CUNHA","nomeUrna":"AÉCIO NEVES","partido":"PSDB","numero":"4500","votos":3,"percentual":0.12,"sqcand":"130001613348"},{"nome":"ANTONIO PINHEIRO NETO","nomeUrna":"PINHEIRINHO","partido":"PP","numero":"1122","votos":3,"percentual":0.12,"sqcand":"130001615436"},{"nome":"MESSIAS LOPES FERREIRA","nomeUrna":"MESSIAS FERREIRA","partido":"PSC","numero":"2025","votos":3,"percentual":0.12,"sqcand":"130001671785"},{"nome":"MARIA CECÍLIA FERREIRA DELFINO","nomeUrna":"CECÍLIA FERRAMENTA","partido":"PT","numero":"1377","votos":3,"percentual":0.12,"sqcand":"130001607269"},{"nome":"GUSTAVO MENDES DE MIRANDA","nomeUrna":"GUSTAVO MENDES","partido":"PT","numero":"1340","votos":3,"percentual":0.12,"sqcand":"130001607255"},{"nome":"GLEIDE ANDRADE DE OLIVEIRA","nomeUrna":"GLEIDE ANDRADE","partido":"PT","numero":"1311","votos":3,"percentual":0.12,"sqcand":"130001607246"},{"nome":"IZABELLA LOURENÇA AMORIM ROMUALDO","nomeUrna":"IZA LOURENÇA","partido":"PSOL","numero":"5000","votos":3,"percentual":0.12,"sqcand":"130001615181"},{"nome":"AELTON JOSE DE FREITAS","nomeUrna":"AELTON FREITAS","partido":"PP","numero":"1123","votos":3,"percentual":0.12,"sqcand":"130001615435"},{"nome":"BRUNO DOMINGUES DOS SANTOS","nomeUrna":"BISPO BRUNO SANTOS","partido":"PATRIOTA","numero":"5110","votos":3,"percentual":0.12,"sqcand":"130001596011"},{"nome":"GLEISER LUCIO BORONI SOARES","nomeUrna":"GLEISER BORONI","partido":"PATRIOTA","numero":"5130","votos":3,"percentual":0.12,"sqcand":"130001595976"},{"nome":"GERALDO JUNIO DO AMARAL","nomeUrna":"JUNIO AMARAL","partido":"PL","numero":"2238","votos":3,"percentual":0.12,"sqcand":"130001610992"},{"nome":"TALES MARCELO ALVES","nomeUrna":"GARI GATO","partido":"AVANTE","numero":"7020","votos":3,"percentual":0.12,"sqcand":"130001603589"},{"nome":"LUCAS DE VASCONCELOS GONZALEZ","nomeUrna":"LUCAS GONZALEZ","partido":"NOVO","numero":"3022","votos":3,"percentual":0.12,"sqcand":"130001598359"},{"nome":"WARLEY DE ARAÚJO MÓL","nomeUrna":"WARLEY MÓL","partido":"NOVO","numero":"3033","votos":3,"percentual":0.12,"sqcand":"130001598352"},{"nome":"RAFAEL TADEU SIMÕES","nomeUrna":"RAFAEL SIMOES","partido":"UNIÃO","numero":"4445","votos":2,"percentual":0.08,"sqcand":"130001607619"},{"nome":"GLYCON MOREIRA FRANCO","nomeUrna":"GLAYCON FRANCO","partido":"PV","numero":"4343","votos":2,"percentual":0.08,"sqcand":"130001607286"},{"nome":"ROBSON PAIVA ZANOLA","nomeUrna":"CABO ZANOLA","partido":"PSD","numero":"5520","votos":2,"percentual":0.08,"sqcand":"130001604338"},{"nome":"LUIZ GONZAGA RIBEIRO","nomeUrna":"SUBTENENTE GONZAGA","partido":"PSD","numero":"5522","votos":2,"percentual":0.08,"sqcand":"130001604329"},{"nome":"ANA CRISTINA DE LIMA PIMENTEL","nomeUrna":"ANA PIMENTEL","partido":"PT","numero":"1314","votos":2,"percentual":0.08,"sqcand":"130001607240"},{"nome":"PATRUS ANANIAS DE SOUSA","nomeUrna":"PATRUS ANANIAS","partido":"PT","numero":"1333","votos":2,"percentual":0.08,"sqcand":"130001607244"},{"nome":"ELIEL MARCIO DO CARMO","nomeUrna":"LEO MOTTA","partido":"REPUBLICANOS","numero":"1022","votos":2,"percentual":0.08,"sqcand":"130001619741"},{"nome":"HERCULANO ANGHINETTI","nomeUrna":"HERCULANO","partido":"REPUBLICANOS","numero":"1011","votos":2,"percentual":0.08,"sqcand":"130001619772"},{"nome":"DIMAS FABIANO TOLEDO JUNIOR","nomeUrna":"DIMAS FABIANO","partido":"PP","numero":"1111","votos":2,"percentual":0.08,"sqcand":"130001615433"},{"nome":"MARIA PIEDADE FERREIRA DA SILVA","nomeUrna":"DADINHA","partido":"PSDB","numero":"4526","votos":2,"percentual":0.08,"sqcand":"130001613350"},{"nome":"DARIO RICARDO BRAGA DE MOURA","nomeUrna":"DÁRIO","partido":"PSOL","numero":"5042","votos":2,"percentual":0.08,"sqcand":"130001615169"},{"nome":"WILSON MARTINS DE ASSIS","nomeUrna":"WILSON MARTINS","partido":"PP","numero":"1131","votos":2,"percentual":0.08,"sqcand":"130001615456"},{"nome":"JOSE VASCO FERREIRA DIAS","nomeUrna":"ZÉ DO RÁDIO","partido":"PP","numero":"1112","votos":2,"percentual":0.08,"sqcand":"130001615429"},{"nome":"ÁLVARO DAMIÃO VIEIRA DA PAZ","nomeUrna":"ÁLVARO DAMIÃO","partido":"UNIÃO","numero":"4400","votos":2,"percentual":0.08,"sqcand":"130001607617"},{"nome":"CLEUSA BERNADETH LARA CORREA","nomeUrna":"CLEUSA LARA","partido":"UNIÃO","numero":"4499","votos":2,"percentual":0.08,"sqcand":"130001607624"},{"nome":"DIEGO LEONARDO DE ANDRADE CARVALHO","nomeUrna":"DIEGO ANDRADE","partido":"PSD","numero":"5555","votos":2,"percentual":0.08,"sqcand":"130001604337"},{"nome":"MISAEL ARTUR FERREIRA VARELLA","nomeUrna":"MISAEL VARELLA","partido":"PSD","numero":"5505","votos":2,"percentual":0.08,"sqcand":"130001604325"},{"nome":"ARLAN DIAS MARTINS","nomeUrna":"ARLAN DO POVÃO","partido":"PDT","numero":"1290","votos":2,"percentual":0.08,"sqcand":"130001606693"},{"nome":"ROBERTO SILVA SOARES","nomeUrna":"ROBERTINHO SOARES","partido":"AVANTE","numero":"7089","votos":2,"percentual":0.08,"sqcand":"130001603581"},{"nome":"DÓRIS CAMARGO MARTINS DE ANDRADE","nomeUrna":"DÓRIS ANDRADE","partido":"NOVO","numero":"3004","votos":2,"percentual":0.08,"sqcand":"130001598358"},{"nome":"ERIKA CRISTINA LOPES","nomeUrna":"DRA ERIKA LOPES","partido":"PL","numero":"2227","votos":1,"percentual":0.04,"sqcand":"130001610989"},{"nome":"MOAMED RACHID GARIFF NOLETO DE QUEIROZ","nomeUrna":"MOAMED RACHID GARIFF","partido":"PROS","numero":"9099","votos":1,"percentual":0.04,"sqcand":"130001607564"},{"nome":"MARCELO EDUARDO FREITAS","nomeUrna":"DELEGADO MARCELO FREITAS","partido":"UNIÃO","numero":"4444","votos":1,"percentual":0.04,"sqcand":"130001607654"},{"nome":"SORAYA RIBEIRO PINTO","nomeUrna":"SORAYA PROFESSORA PROTETORA","partido":"PSD","numero":"5525","votos":1,"percentual":0.04,"sqcand":"130001604316"},{"nome":"DAVID ARAÚJO MACHADO","nomeUrna":"DAVID MACHADO","partido":"PSD","numero":"5565","votos":1,"percentual":0.04,"sqcand":"130001604301"},{"nome":"CLEUDES SOARES DE ALMEIDA","nomeUrna":"PROFESSORA CLEUDES","partido":"PSD","numero":"5540","votos":1,"percentual":0.04,"sqcand":"130001604327"},{"nome":"ANDERSON LUÍS COELHO","nomeUrna":"ANDERSON COELHO","partido":"PSD","numero":"5533","votos":1,"percentual":0.04,"sqcand":"130001604336"},{"nome":"NELI PEREIRA DE AQUINO","nomeUrna":"NELY AQUINO","partido":"PODE","numero":"1919","votos":1,"percentual":0.04,"sqcand":"130001634141"},{"nome":"GUILHERME NASSER SILVERIO","nomeUrna":"GUILHERME NASSER","partido":"PSB","numero":"4090","votos":1,"percentual":0.04,"sqcand":"130001613210"},{"nome":"JORGE BATISTA BENTO DA PAZ","nomeUrna":"JORGINHO","partido":"PSB","numero":"4040","votos":1,"percentual":0.04,"sqcand":"130001613217"},{"nome":"DANDARA TONANTZIN SILVA CASTRO","nomeUrna":"DANDARA","partido":"PT","numero":"1334","votos":1,"percentual":0.04,"sqcand":"130001607270"},{"nome":"RENATO PENHA DE OLIVEIRA","nomeUrna":"RENATO CORONEL","partido":"PMN","numero":"3370","votos":1,"percentual":0.04,"sqcand":"130001606193"},{"nome":"MARIO FERNANDO GONÇALVES NOGUEIRA","nomeUrna":"PROFESSOR MARIO PATRIOTA","partido":"REPUBLICANOS","numero":"1031","votos":1,"percentual":0.04,"sqcand":"130001619733"},{"nome":"RODRIGO GOMES","nomeUrna":"PROFESSOR RODRIGO GOMES","partido":"PTB","numero":"1423","votos":1,"percentual":0.04,"sqcand":"130001610874"},{"nome":"MÁRCIO EMÍDIO MARANGON","nomeUrna":"MÁRCIO MARANGON","partido":"PTB","numero":"1499","votos":1,"percentual":0.04,"sqcand":"130001610892"},{"nome":"JANICIA RIBEIRO SILVA","nomeUrna":"PASTORA JANE SILVA","partido":"PTB","numero":"1422","votos":1,"percentual":0.04,"sqcand":"130001610904"},{"nome":"LUCIANA MIRANDA BRITO ALEIXO","nomeUrna":"TIA LULUZINHA","partido":"PTB","numero":"1445","votos":1,"percentual":0.04,"sqcand":"130001610888"},{"nome":"ANA PAULA PROCOPIO JUNQUEIRA","nomeUrna":"ANA PAULA JUNQUEIRA LEAO","partido":"PP","numero":"1199","votos":1,"percentual":0.04,"sqcand":"130001615412"},{"nome":"RAILAND MARTINS","nomeUrna":"RAY MARTINS","partido":"PSC","numero":"2045","votos":1,"percentual":0.04,"sqcand":"130001671773"},{"nome":"KERLEY CRISTINA PEREIRA GOMES","nomeUrna":"KERLEY CRISTINA","partido":"PSC","numero":"2047","votos":1,"percentual":0.04,"sqcand":"130001724268"},{"nome":"ILACIR BICALHO DE BARROS","nomeUrna":"ILACIR BICALHO","partido":"PSC","numero":"2022","votos":1,"percentual":0.04,"sqcand":"130001671790"},{"nome":"KATIA REGINA OLIVEIRA DIAS","nomeUrna":"KATIA DIAS","partido":"PSC","numero":"2012","votos":1,"percentual":0.04,"sqcand":"130001671780"},{"nome":"ELIANE JOANA SANTIAGO","nomeUrna":"DRA ELIANE SANTIAGO","partido":"PT","numero":"1323","votos":1,"percentual":0.04,"sqcand":"130001607272"},{"nome":"EDNA CORREIA DE OLIVEIRA","nomeUrna":"EDNA GORUTUBA","partido":"PT","numero":"1388","votos":1,"percentual":0.04,"sqcand":"130001607280"},{"nome":"NILMARIO DE MIRANDA","nomeUrna":"NILMARIO MIRANDA","partido":"PT","numero":"1331","votos":1,"percentual":0.04,"sqcand":"130001607273"},{"nome":"DIVINO ANTÔNIO DE OLIVEIRA","nomeUrna":"DIVINO DE OLIVEIRA","partido":"PSDB","numero":"4520","votos":1,"percentual":0.04,"sqcand":"130001613375"},{"nome":"MIRIAM DE MELO THEOBALDO","nomeUrna":"MIRIAM THEOBALDO","partido":"PSDB","numero":"4502","votos":1,"percentual":0.04,"sqcand":"130001613353"},{"nome":"MARCELO CACIANO DA SILVA","nomeUrna":"MARCELO CACIANO","partido":"PP","numero":"1113","votos":1,"percentual":0.04,"sqcand":"130001615440"},{"nome":"CHARLLES THOMACELLI EVANGELISTA","nomeUrna":"CHARLLES EVANGELISTA","partido":"PP","numero":"1132","votos":1,"percentual":0.04,"sqcand":"130001615426"},{"nome":"FABIANO LOPES FERREIRA","nomeUrna":"FABIANO CAZECA","partido":"PATRIOTA","numero":"5154","votos":1,"percentual":0.04,"sqcand":"130001596001"},{"nome":"ELIFELETE LOPES DOS SANTOS","nomeUrna":"ELIFELETE TIA FÉ","partido":"PATRIOTA","numero":"5155","votos":1,"percentual":0.04,"sqcand":"130001738659"},{"nome":"SERGIO AUGUSTO SANTOS RODRIGUES","nomeUrna":"SERGIO SANTOS RODRIGUES","partido":"PODE","numero":"1921","votos":1,"percentual":0.04,"sqcand":"130001634150"},{"nome":"JOSE VALADARES BAHIA","nomeUrna":"JUCA BAHIA","partido":"PODE","numero":"1900","votos":1,"percentual":0.04,"sqcand":"130001634144"},{"nome":"EDVALDO DE SOUZA GOMIDES","nomeUrna":"DELEGADO FED. EDVALDO GOMIDES","partido":"PODE","numero":"1995","votos":1,"percentual":0.04,"sqcand":"130001634122"},{"nome":"SERGIO DE PINHO AMARAL","nomeUrna":"SERGIO PINHO AMARAL","partido":"PODE","numero":"1994","votos":1,"percentual":0.04,"sqcand":"130001634120"},{"nome":"JADER SAINT CLAIR DE ALMEIDA FILHO","nomeUrna":"JADER ALMEIDA","partido":"PODE","numero":"1969","votos":1,"percentual":0.04,"sqcand":"130001634157"},{"nome":"IRLAN CHAVES DE OLIVEIRA MELO","nomeUrna":"IRLAN MELO","partido":"PATRIOTA","numero":"5123","votos":1,"percentual":0.04,"sqcand":"130001596010"},{"nome":"ALFREDO TEIXEIRA DE LIMA FILHO","nomeUrna":"ALFREDO TEIXEIRA","partido":"UNIÃO","numero":"4440","votos":1,"percentual":0.04,"sqcand":"130001607616"},{"nome":"JOSE ANTONIO DE ALMEIDA","nomeUrna":"ZEZINHO","partido":"UNIÃO","numero":"4421","votos":1,"percentual":0.04,"sqcand":"130001607649"},{"nome":"LÍVIA OLIVEIRA VASCONCELOS","nomeUrna":"LÍVIA FLOR","partido":"PCB","numero":"2135","votos":1,"percentual":0.04,"sqcand":"130001615079"},{"nome":"MAIRA DOS SANTOS CARLOS","nomeUrna":"MAÍRA CARLOS","partido":"MDB","numero":"1520","votos":1,"percentual":0.04,"sqcand":"130001668939"},{"nome":"SAMUEL JOSÉ RODRIGUES DE VIANA","nomeUrna":"SAMUEL VIANA","partido":"PL","numero":"2244","votos":1,"percentual":0.04,"sqcand":"130001611024"},{"nome":"JOSÉ VITOR DE RESENDE AGUIAR","nomeUrna":"ZÉ VITOR","partido":"PL","numero":"2200","votos":1,"percentual":0.04,"sqcand":"130001610999"},{"nome":"MAURICIO LUIZ DE SOUZA","nomeUrna":"MAURICIO DO VOLEI","partido":"PL","numero":"2210","votos":1,"percentual":0.04,"sqcand":"130001611021"},{"nome":"JACQUELINE CALIXTO BARBOSA DE JESUS","nomeUrna":"JACQUELINE BRASIL","partido":"PDT","numero":"1231","votos":1,"percentual":0.04,"sqcand":"130001606675"},{"nome":"MILTON DE FREITAS CARVALHO JUNIOR","nomeUrna":"MILTINHO","partido":"PDT","numero":"1200","votos":1,"percentual":0.04,"sqcand":"130001606710"},{"nome":"WADSON NATHANIEL RIBEIRO","nomeUrna":"WADSON RIBEIRO","partido":"PC do B","numero":"6510","votos":1,"percentual":0.04,"sqcand":"130001607285"},{"nome":"SAVIO RODRIGUES FONTES","nomeUrna":"SÁVIO FONTES","partido":"AVANTE","numero":"7030","votos":1,"percentual":0.04,"sqcand":"130001603608"},{"nome":"WAGNER MARIANO JUNIOR","nomeUrna":"JUNINHO LOS HERMANOS","partido":"AVANTE","numero":"7050","votos":1,"percentual":0.04,"sqcand":"130001603583"},{"nome":"KLIBAS APARECIDO ANDRADE","nomeUrna":"KLIBAS RANCHOS","partido":"AVANTE","numero":"7075","votos":1,"percentual":0.04,"sqcand":"130001603590"},{"nome":"AMANDA BEATRIZ FOLTRAN","nomeUrna":"AMANDA GANEM","partido":"AVANTE","numero":"7079","votos":1,"percentual":0.04,"sqcand":"130001603598"},{"nome":"GILBERTO APARECIDO ABRAMO","nomeUrna":"GILBERTO ABRAMO","partido":"REPUBLICANOS","numero":"1010","votos":1,"percentual":0.04,"sqcand":"130001619779"}],"deputadosEstaduais":[{"nome":"TITO BRUNO MIRANDA TORRES DUARTE","nomeUrna":"TITO TORRES","partido":"PSD","numero":"55240","votos":1196,"percentual":51.95,"sqcand":"130001604353"},{"nome":"JOSÉ CÉLIO DE ALVARENGA","nomeUrna":"CELINHO SINTROCEL","partido":"PC do B","numero":"65112","votos":317,"percentual":13.77,"sqcand":"130001607400"},{"nome":"ROBERTO DIAS DE ANDRADE","nomeUrna":"ROBERTO ANDRADE","partido":"PATRIOTA","numero":"51222","votos":251,"percentual":10.9,"sqcand":"130001596287"},{"nome":"ADRIANO DE ALMEIDA ALVARENGA","nomeUrna":"ADRIANO ALVARENGA","partido":"PP","numero":"11123","votos":106,"percentual":4.6,"sqcand":"130001615635"},{"nome":"WHELTON PIMENTEL DE FREITAS","nomeUrna":"LELECO PIMENTEL","partido":"PT","numero":"13579","votos":61,"percentual":2.65,"sqcand":"130001607378"},{"nome":"BRUNO DE CASTRO ENGLER FLORENCIO DE ALMEIDA","nomeUrna":"BRUNO ENGLER","partido":"PL","numero":"22222","votos":41,"percentual":1.78,"sqcand":"130001619045"},{"nome":"IONE MARIA PINHEIRO","nomeUrna":"IONE PINHEIRO","partido":"UNIÃO","numero":"44141","votos":32,"percentual":1.39,"sqcand":"130001607721"},{"nome":"BEATRIZ DA SILVA CERQUEIRA","nomeUrna":"BEATRIZ CERQUEIRA","partido":"PT","numero":"13123","votos":22,"percentual":0.96,"sqcand":"130001607392"},{"nome":"MILTON TEODORO IRIAS JUNIOR","nomeUrna":"DR MILTON","partido":"AVANTE","numero":"70333","votos":21,"percentual":0.91,"sqcand":"130001603661"},{"nome":"THIAGO FELLIPE MOTTA COTA","nomeUrna":"THIAGO COTA","partido":"PDT","numero":"12000","votos":15,"percentual":0.65,"sqcand":"130001606759"},{"nome":"KAIQUE NASCIMENTO SANT ANNA","nomeUrna":"KAICÃO DA MASSA","partido":"PROS","numero":"90300","votos":14,"percentual":0.61,"sqcand":"130001607530"},{"nome":"MÁRCIO MOREIRA VICTOR","nomeUrna":"MÁRCIO VICTOR","partido":"PSDB","numero":"45240","votos":13,"percentual":0.56,"sqcand":"130001613321"},{"nome":"SHEILA APARECIDA PEDROSA DE MELLO OLIVEIRA","nomeUrna":"DELEGADA SHEILA","partido":"PL","numero":"22032","votos":10,"percentual":0.43,"sqcand":"130001619041"},{"nome":"JAMIR CALILI RIBEIRO","nomeUrna":"JAMIR CALILI RIBEIRO","partido":"PP","numero":"11033","votos":8,"percentual":0.35,"sqcand":"130001615618"},{"nome":"LUIZ HENRIQUE ALBERGARIA RODRIGUES","nomeUrna":"LUIZ ALBERGARIA","partido":"PRTB","numero":"28112","votos":8,"percentual":0.35,"sqcand":"130001612846"},{"nome":"LEANDRO ANDRADE GENARO OLIVEIRA","nomeUrna":"LEANDRO GENARO","partido":"PSD","numero":"55444","votos":7,"percentual":0.3,"sqcand":"130001604370"},{"nome":"BERNARDO MUCIDA OLIVEIRA","nomeUrna":"MUCIDA","partido":"PSB","numero":"40900","votos":6,"percentual":0.26,"sqcand":"130001613143"},{"nome":"DALTON LOREDO DE PAULA","nomeUrna":"DALTINHO LOREDO","partido":"REPUBLICANOS","numero":"10321","votos":6,"percentual":0.26,"sqcand":"130001634066"},{"nome":"TIAGO SANTANA CASSIANO","nomeUrna":"TIAGO SANTANA","partido":"PC do B","numero":"65653","votos":5,"percentual":0.22,"sqcand":"130001607405"},{"nome":"GUSTAVO DE VASCONCELLOS MOREIRA","nomeUrna":"GUSTAVO SANTANA","partido":"PL","numero":"22800","votos":5,"percentual":0.22,"sqcand":"130001619055"},{"nome":"OSVALDO LOPES DE OLIVEIRA JUNIOR","nomeUrna":"OSVALDO LOPES","partido":"PSD","numero":"55000","votos":5,"percentual":0.22,"sqcand":"130001604372"},{"nome":"MARIA VANUZIA MENDES SANTOS","nomeUrna":"MARIA VANUZIA","partido":"UNIÃO","numero":"44994","votos":5,"percentual":0.22,"sqcand":"130001607683"},{"nome":"ANDRE SOL ROCHA MENDES","nomeUrna":"JORNALISTA ANDRÉ ROCHA","partido":"PATRIOTA","numero":"51000","votos":5,"percentual":0.22,"sqcand":"130001596321"},{"nome":"CASSIO ANTONIO FERREIRA SOARES","nomeUrna":"CASSIO SOARES","partido":"PSD","numero":"55555","votos":5,"percentual":0.22,"sqcand":"130001604379"},{"nome":"RUBENS GONÇALVES DE BRITO","nomeUrna":"BIM DA AMBULÂNCIA","partido":"AVANTE","numero":"70193","votos":4,"percentual":0.17,"sqcand":"130001603688"},{"nome":"REINALDO DA SILVA OLIVEIRA","nomeUrna":"REINALDO DA REI RELOGIOS","partido":"PROS","numero":"90998","votos":4,"percentual":0.17,"sqcand":"130001607560"},{"nome":"WESLEY MOREIRA DE PINHO","nomeUrna":"WESLEY AUTO ESCOLA","partido":"PP","numero":"11777","votos":4,"percentual":0.17,"sqcand":"130001615650"},{"nome":"REINALDO LUCIO DA SILVA","nomeUrna":"INSTRUTOR REINALDO","partido":"PP","numero":"11323","votos":4,"percentual":0.17,"sqcand":"130001615626"},{"nome":"MACAÉ MARIA EVARISTO DOS SANTOS","nomeUrna":"MACAÉ EVARISTO","partido":"PT","numero":"13130","votos":4,"percentual":0.17,"sqcand":"130001607426"},{"nome":"FABIO JOSE DE OLIVEIRA","nomeUrna":"FÁBIO AVELAR","partido":"AVANTE","numero":"70123","votos":3,"percentual":0.13,"sqcand":"130001603664"},{"nome":"WASHINGTON FERNANDO RODRIGUES","nomeUrna":"SARGENTO RODRIGUES","partido":"PL","numero":"22122","votos":3,"percentual":0.13,"sqcand":"130001619068"},{"nome":"ALESSANDRA DINIZ PORTELA SILVEIRA","nomeUrna":"ALÊ PORTELA","partido":"PL","numero":"22333","votos":3,"percentual":0.13,"sqcand":"130001619043"},{"nome":"JOÃO VITOR XAVIER FAUSTINO","nomeUrna":"JOÃO VITOR XAVIER","partido":"CIDADANIA","numero":"23200","votos":3,"percentual":0.13,"sqcand":"130001613297"},{"nome":"PATRICIA MARIA DA COSTA REIS","nomeUrna":"DENTISTA PATRICIA REIS","partido":"PSD","numero":"55250","votos":3,"percentual":0.13,"sqcand":"130001604350"},{"nome":"DANIEL FIORAVANTE BARBOSA","nomeUrna":"DANIEL BARBOSA","partido":"PSDB","numero":"45355","votos":3,"percentual":0.13,"sqcand":"130001613311"},{"nome":"MAYCON JOAN DE SOUZA","nomeUrna":"MAYCON JUAN","partido":"PP","numero":"11112","votos":3,"percentual":0.13,"sqcand":"130001615605"},{"nome":"CÉLIO DA ASSUNÇÃO FROIS","nomeUrna":"DR. CÉLIO FROIS","partido":"PSC","numero":"20000","votos":3,"percentual":0.13,"sqcand":"130001671848"},{"nome":"ASTÉRIO ITABAYANA NETO","nomeUrna":"ASTÉRIO ITABAYANA NETO","partido":"NOVO","numero":"30330","votos":3,"percentual":0.13,"sqcand":"130001598564"},{"nome":"GUSTAVO ADOLFO ARANTES","nomeUrna":"ENFERMEIRO GUSTAVO ARANTES","partido":"PMB","numero":"35123","votos":3,"percentual":0.13,"sqcand":"130001669317"},{"nome":"JALYSON MAYCON GONÇALVES","nomeUrna":"SARGENTO JALYSON","partido":"PL","numero":"22190","votos":3,"percentual":0.13,"sqcand":"130001619057"},{"nome":"FREDERICO LUCAS MEIRELES ASSUNCAO","nomeUrna":"CABO MEIRELES","partido":"DC","numero":"27190","votos":3,"percentual":0.13,"sqcand":"130001611567"},{"nome":"MARCO ANTONIO VIEIRA GOMES","nomeUrna":"PROF. MARCO ANTÔNIO","partido":"NOVO","numero":"30023","votos":2,"percentual":0.09,"sqcand":"130001598594"},{"nome":"JOSE GUILHERME FERREIRA FILHO","nomeUrna":"ZÉ GUILHERME","partido":"PP","numero":"11111","votos":2,"percentual":0.09,"sqcand":"130001615639"},{"nome":"WELINTON SANDRO DE ABREU","nomeUrna":"WELINTON SAPÃO","partido":"PMN","numero":"33456","votos":2,"percentual":0.09,"sqcand":"130001605835"},{"nome":"GEDIR CHRISTIAN ROCHA","nomeUrna":"CORONEL GEDIR ROCHA","partido":"PMN","numero":"33133","votos":2,"percentual":0.09,"sqcand":"130001605804"},{"nome":"WILLIAN DE OLIVEIRA BRAGA","nomeUrna":"INSPETOR WILLIAN BRAGA","partido":"PROS","numero":"90090","votos":2,"percentual":0.09,"sqcand":"130001607546"},{"nome":"IOANNIS KONSTANTINOS GRAMMATIKOPOULOS","nomeUrna":"GREGO","partido":"PMN","numero":"33033","votos":2,"percentual":0.09,"sqcand":"130001605806"},{"nome":"JOSÉ ALOISIO DIAS","nomeUrna":"ALOISIO DIAS","partido":"REDE","numero":"18100","votos":2,"percentual":0.09,"sqcand":"130001615230"},{"nome":"CHARLES DOS SANTOS","nomeUrna":"CHARLES SANTOS","partido":"REPUBLICANOS","numero":"10100","votos":2,"percentual":0.09,"sqcand":"130001634030"},{"nome":"ADRIANO MARTINS DE OLIVEIRA","nomeUrna":"ADRIANO MARTINS","partido":"PSD","numero":"55650","votos":2,"percentual":0.09,"sqcand":"130001604375"},{"nome":"IRINEU INACIO DA SILVA","nomeUrna":"PROFESSOR IRINEU","partido":"PATRIOTA","numero":"51027","votos":2,"percentual":0.09,"sqcand":"130001596301"},{"nome":"LEONÍDIO HENRIQUE CORREA BOUÇAS","nomeUrna":"LEONÍDIO BOUÇAS","partido":"PSDB","numero":"45999","votos":2,"percentual":0.09,"sqcand":"130001613290"},{"nome":"IGOR LUIZ SANDIM GONZAGA","nomeUrna":"IGOR SANDIM","partido":"PODE","numero":"19999","votos":2,"percentual":0.09,"sqcand":"130001634218"},{"nome":"ADRIANA DA CRUZ FREITAS","nomeUrna":"ADRIANA D CRUZ","partido":"AVANTE","numero":"70313","votos":2,"percentual":0.09,"sqcand":"130001603703"},{"nome":"AVELINO RIBEIRO DA CRUZ","nomeUrna":"VEVE","partido":"PP","numero":"11070","votos":2,"percentual":0.09,"sqcand":"130001615604"},{"nome":"MÁRCIO ALMEIDA BERNARDINO","nomeUrna":"MÁRCIO BERNARDINO","partido":"NOVO","numero":"30234","votos":2,"percentual":0.09,"sqcand":"130001598597"},{"nome":"ANDREIA DE JESUS SILVA","nomeUrna":"ANDREIA DE JESUS","partido":"PT","numero":"13050","votos":2,"percentual":0.09,"sqcand":"130001607391"},{"nome":"CHRISTIANO AUGUSTO XAVIER FERREIRA","nomeUrna":"DELEGADO CHRISTIANO XAVIER","partido":"PSD","numero":"55333","votos":2,"percentual":0.09,"sqcand":"130001604365"},{"nome":"DANIEL APARECIDO DE ARAÚJO CABRAL","nomeUrna":"DANIEL CABRAL","partido":"PC do B","numero":"65000","votos":1,"percentual":0.04,"sqcand":"130001607401"},{"nome":"MOARA CORREA SABOIA","nomeUrna":"MOARA SABOIA","partido":"PT","numero":"13600","votos":1,"percentual":0.04,"sqcand":"130001607435"},{"nome":"MARIA ALVES DE SOUZA","nomeUrna":"MARIA ALVES","partido":"PT","numero":"13567","votos":1,"percentual":0.04,"sqcand":"130001607428"},{"nome":"VALDIR BATISTA DA SILVA","nomeUrna":"VALDIR BATISTA","partido":"PT","numero":"13266","votos":1,"percentual":0.04,"sqcand":"130001607396"},{"nome":"CARLOS MAGNO RIBEIRO COSTA","nomeUrna":"MAGNO","partido":"PT","numero":"13450","votos":1,"percentual":0.04,"sqcand":"130001607393"},{"nome":"EDSON RODRIGUES GONÇALVES","nomeUrna":"EDSON SORÓ","partido":"PT","numero":"13300","votos":1,"percentual":0.04,"sqcand":"130001607379"},{"nome":"SÁVIO JOSÉ DO CARMO SILVA","nomeUrna":"SÁVIO JOSÉ","partido":"PT","numero":"13013","votos":1,"percentual":0.04,"sqcand":"130001607383"},{"nome":"DIMAS ANTÔNIO DE SOUZA","nomeUrna":"PROF DIMAS","partido":"PT","numero":"13400","votos":1,"percentual":0.04,"sqcand":"130001607431"},{"nome":"MARIA TERESA DOS SANTOS","nomeUrna":"DONA TEREZA","partido":"PT","numero":"13033","votos":1,"percentual":0.04,"sqcand":"130001607387"},{"nome":"SÂMIA MACEDO FERREIRA","nomeUrna":"SÂMIA DO AMIGO LIVRO","partido":"PT","numero":"13131","votos":1,"percentual":0.04,"sqcand":"130001607377"},{"nome":"JOAO IZAEL QUIRINO COELHO","nomeUrna":"JOAO IZAEL","partido":"PMN","numero":"33022","votos":1,"percentual":0.04,"sqcand":"130001605824"},{"nome":"MARCELIA PRISCA DE CARVALHO FERREIRA","nomeUrna":"MARCELIA DO QUERITE","partido":"PMN","numero":"33555","votos":1,"percentual":0.04,"sqcand":"130001605810"},{"nome":"SANDRO LÚCIO FONSECA","nomeUrna":"CORONEL SANDRO","partido":"PL","numero":"22011","votos":1,"percentual":0.04,"sqcand":"130001619065"},{"nome":"RAFAEL MARTINS DE SOUZA","nomeUrna":"RAFAEL MARTINS","partido":"PSD","numero":"55031","votos":1,"percentual":0.04,"sqcand":"130001604380"},{"nome":"LERIS FELISBERTO BRAGA","nomeUrna":"LERIS BRAGA","partido":"REDE","numero":"18007","votos":1,"percentual":0.04,"sqcand":"130001615241"},{"nome":"WELBERT PEREIRA DE FARIA","nomeUrna":"BETO ALEGRIA","partido":"REDE","numero":"18123","votos":1,"percentual":0.04,"sqcand":"130001615253"},{"nome":"CARLOS WELTH PIMENTA DE FIGUEIREDO","nomeUrna":"CARLOS PIMENTA","partido":"PDT","numero":"12369","votos":1,"percentual":0.04,"sqcand":"130001606724"},{"nome":"CARLOS HENRIQUE ALVES DA SILVA","nomeUrna":"CARLOS HENRIQUE","partido":"REPUBLICANOS","numero":"10123","votos":1,"percentual":0.04,"sqcand":"130001634019"},{"nome":"MAURO HENRIQUE TRAMONTE","nomeUrna":"MAURO TRAMONTE","partido":"REPUBLICANOS","numero":"10800","votos":1,"percentual":0.04,"sqcand":"130001634063"},{"nome":"RILTON RAMOS HILDEBRANDO","nomeUrna":"PROFESSOR RILTON HILDEBRANDO","partido":"PDT","numero":"12001","votos":1,"percentual":0.04,"sqcand":"130001606729"},{"nome":"AVELIN ROSANA ROLIM CORREIA DE OLIVEIRA","nomeUrna":"AVELIN KAMBIWÁ","partido":"PDT","numero":"12626","votos":1,"percentual":0.04,"sqcand":"130001606732"},{"nome":"HELIO MEDEIROS CORREA","nomeUrna":"HELINHO DA FARMACIA","partido":"PSD","numero":"55055","votos":1,"percentual":0.04,"sqcand":"130001604361"},{"nome":"MARCOS LEONARDO CONDÉ","nomeUrna":"DR LEONARDO CONDÉ","partido":"UNIÃO","numero":"44144","votos":1,"percentual":0.04,"sqcand":"130001607727"},{"nome":"JÚLIO CEZAR PEREIRA SOUZA","nomeUrna":"JULIO FAVELA","partido":"UNIÃO","numero":"44554","votos":1,"percentual":0.04,"sqcand":"130001607738"},{"nome":"CAIRO MONTEIRO PEREIRA","nomeUrna":"CAIRO MONTEIRO","partido":"UNIÃO","numero":"44560","votos":1,"percentual":0.04,"sqcand":"130001607674"},{"nome":"FABIO DOS SANTOS BOSI","nomeUrna":"BALINHA DO AÇOUGUE","partido":"UNIÃO","numero":"44321","votos":1,"percentual":0.04,"sqcand":"130001607734"},{"nome":"MARISTELA APARECIDA DUTRA","nomeUrna":"MARISTELA DUTRA","partido":"PATRIOTA","numero":"51122","votos":1,"percentual":0.04,"sqcand":"130001596320"},{"nome":"CARLOS LINDOMAR DE SOUSA","nomeUrna":"LINDOMAR","partido":"PATRIOTA","numero":"51023","votos":1,"percentual":0.04,"sqcand":"130001596307"},{"nome":"GUSTAVO DA CUNHA PEREIRA VALADARES","nomeUrna":"GUSTAVO VALADARES","partido":"PMN","numero":"33333","votos":1,"percentual":0.04,"sqcand":"130001605805"},{"nome":"LUCIANO BARBOSA VIANA","nomeUrna":"LUCIANO  VIANA","partido":"PSB","numero":"40500","votos":1,"percentual":0.04,"sqcand":"130001613134"},{"nome":"JOSÉ PEDRO CORDEIRO","nomeUrna":"ZE PEDRO","partido":"PSB","numero":"40555","votos":1,"percentual":0.04,"sqcand":"130001613120"},{"nome":"ANDERSON LUIZ COSTA","nomeUrna":"ANDERSON COSTA","partido":"PP","numero":"11311","votos":1,"percentual":0.04,"sqcand":"130001615624"},{"nome":"JOSE CHEREM","nomeUrna":"ZÉ CHEREM","partido":"PP","numero":"11155","votos":1,"percentual":0.04,"sqcand":"130001615609"},{"nome":"WESLEY DE JESUS SILVA","nomeUrna":"WESLEY DE JESUS","partido":"PP","numero":"11999","votos":1,"percentual":0.04,"sqcand":"130001615591"},{"nome":"MARIO KNICHALLA NETO","nomeUrna":"MARIO KNICHALLA CAÇADOR","partido":"PP","numero":"11357","votos":1,"percentual":0.04,"sqcand":"130001615603"},{"nome":"LUCIANO DE OLIVEIRA E SILVA","nomeUrna":"DR. LUCIANO","partido":"PSC","numero":"20150","votos":1,"percentual":0.04,"sqcand":"130001671851"},{"nome":"FERNANDA RIBEIRO DE SALLES","nomeUrna":"REPORTER FERNANDA SALLES","partido":"REPUBLICANOS","numero":"10700","votos":1,"percentual":0.04,"sqcand":"130001634041"},{"nome":"DOMINGOS SAVIO DE MENDONÇA","nomeUrna":"CEL MENDONÇA","partido":"REPUBLICANOS","numero":"10190","votos":1,"percentual":0.04,"sqcand":"130001634034"},{"nome":"ALESSANDRO OTÁVIO DE SOUZA RIBEIRO NEVES","nomeUrna":"ALESSANDRO RIBEIRO","partido":"MDB","numero":"15151","votos":1,"percentual":0.04,"sqcand":"130001678159"},{"nome":"TALLIA SOBRAL NUNES","nomeUrna":"TALLIA SOBRAL","partido":"PSOL","numero":"50000","votos":1,"percentual":0.04,"sqcand":"130001615275"},{"nome":"LEONARDO LUCIO MORAIS","nomeUrna":"CABO THÉO DO ISCAC","partido":"PTB","numero":"14190","votos":1,"percentual":0.04,"sqcand":"130001645077"},{"nome":"MARCOS JOSERALDO LEMOS","nomeUrna":"MARQUINHO LEMOS","partido":"PT","numero":"13139","votos":1,"percentual":0.04,"sqcand":"130001607427"},{"nome":"CRISTIANO TADEU DA SILVEIRA","nomeUrna":"CRISTIANO SILVEIRA","partido":"PT","numero":"13120","votos":1,"percentual":0.04,"sqcand":"130001607361"},{"nome":"JEAN MARK FREIRE SILVA","nomeUrna":"DR. JEAN FREIRE","partido":"PT","numero":"13100","votos":1,"percentual":0.04,"sqcand":"130001607423"},{"nome":"ELIZEU SILVA CORDEIRO","nomeUrna":"BIG JHOOW","partido":"SOLIDARIEDADE","numero":"77007","votos":1,"percentual":0.04,"sqcand":"130001613033"},{"nome":"SIDNEI JOSÉ DE ARAÚJO","nomeUrna":"SIDNEI DA FORANIA","partido":"PL","numero":"22020","votos":1,"percentual":0.04,"sqcand":"130001619079"},{"nome":"SEBASTIÃO CALIXTO FILHO","nomeUrna":"DR SEBASTIÃO","partido":"PL","numero":"22789","votos":1,"percentual":0.04,"sqcand":"130001619066"},{"nome":"CAROLINE FIGUEIREDO COSTA","nomeUrna":"CAROL FIGUEIREDO","partido":"PL","numero":"22120","votos":1,"percentual":0.04,"sqcand":"130001619021"}]}