{"populacao":19893,"votosValidos":15874,"abstencao":16.78,"prefeito":{"nome":"MARCOS ANTONIO DA SILVA LIMA","nomeUrna":"MARCÃO","partido":"PSB","numero":"40","votos":9299,"percentual":58.58,"situacao":"Eleito","sqcand":"60001902921","vice":"SIRDINEIDE PRADO SARAIVA DE QUEIROZ","viceNomeUrna":"NEIDINHA","partidoVice":"MDB","sqcandVice":"60001902920","coligacao":"PSB / MDB / PC do B / PT / PV"},"vereadores":[{"nome":"RODRIGO MELLO MARINHO","nomeUrna":"RODRIGO MELLO","partido":"PSB","numero":"40678","votos":1097,"percentual":6.96,"situacao":"Eleito por QP","sqcand":"60001991666"},{"nome":"LUCIANO PEREIRA DE SOUSA","nomeUrna":"LUCIANO BEDEU","partido":"PSB","numero":"40000","votos":949,"percentual":6.02,"situacao":"Eleito por QP","sqcand":"60001991671"},{"nome":"FRANCISCA EDMIRTA DE NEGREIROS","nomeUrna":"EDMIRTA NEGREIROS","partido":"PSD","numero":"55555","votos":890,"percentual":5.65,"situacao":"Eleito por QP","sqcand":"60002154130"},{"nome":"MARCIO DE ARAUJO COSTA","nomeUrna":"MARCIO PACHOLA","partido":"PSD","numero":"55000","votos":816,"percentual":5.18,"situacao":"Eleito por QP","sqcand":"60002154124"},{"nome":"MAYCON ANTONIO JOSE DE SOUZA ALCANTARA","nomeUrna":"MAYCON CAMBIRIBA","partido":"PSD","numero":"55333","votos":801,"percentual":5.09,"situacao":"Eleito por QP","sqcand":"60002154127"},{"nome":"ADRIANO FEITOSA SOUSA","nomeUrna":"ADRIANO FEITOSA","partido":"PSB","numero":"40444","votos":682,"percentual":4.33,"situacao":"Eleito por QP","sqcand":"60001991668"},{"nome":"ADELMO PEREIRA DE CARVALHO","nomeUrna":"ADELMO","partido":"MDB","numero":"15000","votos":680,"percentual":4.32,"situacao":"Eleito por QP","sqcand":"60002104748"},{"nome":"JOSE JOCIER MARQUES DE SOUZA","nomeUrna":"JUCIER","partido":"PSB","numero":"40111","votos":673,"percentual":4.27,"situacao":"Eleito por QP","sqcand":"60001991675"},{"nome":"JOSE NOGUEIRA JUNIOR","nomeUrna":"PROFESSOR JUNIOR","partido":"PSB","numero":"40456","votos":607,"percentual":3.85,"situacao":"Eleito por média","sqcand":"60001991669"},{"nome":"ANTONIO LUCIANO DE SOUSA","nomeUrna":"LUCIANO ANDRÉ","partido":"PSD","numero":"55888","votos":494,"percentual":3.14,"situacao":"Eleito por média","sqcand":"60002154126"},{"nome":"ZACARIAS EDIVALDO DA SILVA GOMES","nomeUrna":"ZACARIAS DA AMBULÂNCIA","partido":"PSD","numero":"55123","votos":480,"percentual":3.05,"situacao":"Suplente","sqcand":"60002154131"},{"nome":"ALAN ANTUNES MELO","nomeUrna":"ALAN MELO","partido":"PSD","numero":"55234","votos":461,"percentual":2.93,"situacao":"Suplente","sqcand":"60002154135"},{"nome":"CARLOS AUGUSTO MESQUITA CAMELO","nomeUrna":"CARLOS AMADEU","partido":"PSB","numero":"40123","votos":425,"percentual":2.7,"situacao":"Suplente","sqcand":"60001991673"},{"nome":"ADECIO PEREIRA DE CARVALHO","nomeUrna":"ADECIO PEREIRA","partido":"PSD","numero":"55456","votos":386,"percentual":2.45,"situacao":"Suplente","sqcand":"60002154134"},{"nome":"FRANCISCO ALEX VIANA DE SOUSA","nomeUrna":"ALEX PÉ NA GRAXA","partido":"MDB","numero":"15444","votos":368,"percentual":2.34,"situacao":"Suplente","sqcand":"60002104753"},{"nome":"GUSTAVO SILVA RODRIGUES","nomeUrna":"GUSTAVO DO DR ORISMAR","partido":"MDB","numero":"15777","votos":364,"percentual":2.31,"situacao":"Suplente","sqcand":"60002104749"},{"nome":"LINDOMAR DE ARAUJO BRITO","nomeUrna":"LINDOMAR BRITO","partido":"PT","numero":"13000","votos":343,"percentual":2.18,"situacao":"Eleito por QP","sqcand":"60001940298"},{"nome":"RODRIGO SALES BONFIM","nomeUrna":"RODRIGÃO","partido":"PSD","numero":"55100","votos":328,"percentual":2.08,"situacao":"Suplente","sqcand":"60002154125"},{"nome":"MARIA ERIVANDA FRANCA DE OLIVEIRA","nomeUrna":"VANDINHA DO SINDICATO","partido":"PT","numero":"13134","votos":298,"percentual":1.89,"situacao":"Suplente","sqcand":"60001940304"},{"nome":"ANTONIO EDVAR DE PAULA","nomeUrna":"EDVAR DA PINDOBA","partido":"PT","numero":"13456","votos":294,"percentual":1.87,"situacao":"Suplente","sqcand":"60001940299"},{"nome":"JOSE CARPEGIANE FERREIRA DE SOUSA","nomeUrna":"GIANE DO LIMÃO","partido":"PSD","numero":"55999","votos":293,"percentual":1.86,"situacao":"Suplente","sqcand":"60002154133"},{"nome":"ANTONIO FRANCISCO DA FONSECA LOPES","nomeUrna":"TOINHO DA BETÂNIA","partido":"PP","numero":"11555","votos":281,"percentual":1.78,"situacao":"Não eleito","sqcand":"60002086507"},{"nome":"MARLETE FERREIRA DA SILVA","nomeUrna":"MARLETE SILVA","partido":"MDB","numero":"15555","votos":278,"percentual":1.76,"situacao":"Suplente","sqcand":"60002104747"},{"nome":"MARIA GLEICILENE FEIJO FERNANDES","nomeUrna":"TIA GLEICE","partido":"PSB","numero":"40222","votos":270,"percentual":1.71,"situacao":"Suplente","sqcand":"60001991670"},{"nome":"FRANCISCO LEANDRO DE OLIVEIRA ALVES","nomeUrna":"LEANDRO DO SEU MESSIAS","partido":"MDB","numero":"15222","votos":240,"percentual":1.52,"situacao":"Suplente","sqcand":"60002104751"},{"nome":"JOSE TARCISIO RIBEIRO DE LIMA","nomeUrna":"CIZIM","partido":"PT","numero":"13111","votos":239,"percentual":1.52,"situacao":"Suplente","sqcand":"60001940303"},{"nome":"ANTONIO EVERARDO OLIVEIRA DOS SANTOS","nomeUrna":"EVERARDO BOGAS","partido":"PSB","numero":"40888","votos":239,"percentual":1.52,"situacao":"Suplente","sqcand":"60001991677"},{"nome":"ANDRELINE PORTELA DA SILVA MORAIS","nomeUrna":"ANDRELINE PORTELA","partido":"PSB","numero":"40100","votos":235,"percentual":1.49,"situacao":"Suplente","sqcand":"60001991667"},{"nome":"ANTONIO JOSE FERNANDES LIMA","nomeUrna":"ANTONIO JOSE DA AUGUSTA BRITO","partido":"PT","numero":"13123","votos":216,"percentual":1.37,"situacao":"Suplente","sqcand":"60001940300"},{"nome":"FRANCISCO DE ASSIS DE PAIVA FERREIRA","nomeUrna":"KIKA PAIVA","partido":"PP","numero":"11222","votos":157,"percentual":1.0,"situacao":"Não eleito","sqcand":"60002086511"},{"nome":"PAULO ROBERTO FONTES MOREIRA","nomeUrna":"ROBERTO DA FRANÇA","partido":"PSB","numero":"40190","votos":153,"percentual":0.97,"situacao":"Suplente","sqcand":"60001991672"},{"nome":"MARIA CLARICE DA SILVA ALVES","nomeUrna":"MISSIONARIA CLARICE","partido":"MDB","numero":"15333","votos":137,"percentual":0.87,"situacao":"Suplente","sqcand":"60002104752"},{"nome":"KEILA ANGELA SAMPAIO DE SOUSA","nomeUrna":"KEILA SAMPAIO","partido":"PSD","numero":"55789","votos":109,"percentual":0.69,"situacao":"Suplente","sqcand":"60002154129"},{"nome":"ANTONIA EMMANUELA MENDONÇA BATISTA","nomeUrna":"DRA MANU","partido":"PSB","numero":"40128","votos":98,"percentual":0.62,"situacao":"Suplente","sqcand":"60001991676"},{"nome":"FRANCISCO BEZERRA NETO","nomeUrna":"BELO DO ÔNIBUS","partido":"MDB","numero":"15124","votos":88,"percentual":0.56,"situacao":"Suplente","sqcand":"60002104750"},{"nome":"JOANA DARC GUEDES DE MENDONÇA","nomeUrna":"DRA JOANA","partido":"PSB","numero":"40333","votos":81,"percentual":0.51,"situacao":"Suplente","sqcand":"60001991674"},{"nome":"ATILA CARVALHO LIRA","nomeUrna":"ATILA DO GELO","partido":"PT","numero":"13777","votos":73,"percentual":0.46,"situacao":"Suplente","sqcand":"60001940305"},{"nome":"ANTONIO PORCIANO DE ARAUJO","nomeUrna":"PORCIANO","partido":"PP","numero":"11157","votos":71,"percentual":0.45,"situacao":"Não eleito","sqcand":"60002086506"},{"nome":"PAULO FRANCISCO DE SA","nomeUrna":"PAULO SÁ","partido":"PP","numero":"11111","votos":68,"percentual":0.43,"situacao":"Não eleito","sqcand":"60002086510"},{"nome":"VIRGILIO NEPOMUCENO NETO","nomeUrna":"VIRGILIO","partido":"PT","numero":"13413","votos":66,"percentual":0.42,"situacao":"Suplente","sqcand":"60001940302"},{"nome":"MARIA ELIZETE DA SILVA SOUSA","nomeUrna":"DETINHA DA PINDOBA","partido":"PSD","numero":"55222","votos":63,"percentual":0.4,"situacao":"Suplente","sqcand":"60002154128"},{"nome":"MARIA MARLUCIA DAMASIO RODRIGUES","nomeUrna":"MARLUCIA DO PREFEITINHO","partido":"PP","numero":"11444","votos":54,"percentual":0.34,"situacao":"Não eleito","sqcand":"60002086509"},{"nome":"SANDRA MARTINS DE LIMA","nomeUrna":"SANDRA DO CAIÇARA","partido":"PSD","numero":"55777","votos":44,"percentual":0.28,"situacao":"Suplente","sqcand":"60002154132"},{"nome":"EMILIANA NEGREIROS DE ALCÂNTARA","nomeUrna":"PROFESSORA EMILIANA","partido":"MDB","numero":"15123","votos":43,"percentual":0.27,"situacao":"Suplente","sqcand":"60002104746"},{"nome":"MARGARIDA MARIA SANTANA DE OLIVEIRA","nomeUrna":"MAGÁ DO APOIO","partido":"PP","numero":"11113","votos":41,"percentual":0.26,"situacao":"Não eleito","sqcand":"60002086508"},{"nome":"SANDRA MARIA DE SOUSA","nomeUrna":"SANDRA ROMÃO","partido":"PP","numero":"11333","votos":32,"percentual":0.2,"situacao":"Não eleito","sqcand":"60002086512"},{"nome":"MARIO FELIX DE SOUSA","nomeUrna":"MARINHO IBIAPINA","partido":"PP","numero":"11000","votos":30,"percentual":0.19,"situacao":"Não eleito","sqcand":"60002086513"},{"nome":"MARIA SALETE ALMEIDA DA SILVA","nomeUrna":"SALETE DA BICICLETINHA","partido":"PT","numero":"13333","votos":16,"percentual":0.1,"situacao":"Suplente","sqcand":"60001940297"},{"nome":"SALETE PEREIRA DA SILVA","nomeUrna":"SALETE PEREIRA","partido":"PT","numero":"13999","votos":14,"percentual":0.09,"situacao":"Suplente","sqcand":"60001940301"}],"senadores":[{"nome":"CAMILO SOBREIRA DE SANTANA","nomeUrna":"CAMILO","partido":"PT","numero":"131","votos":8350,"percentual":67.89,"sqcand":"60001633582"},{"nome":"KAMILA CARDOSO DE SOUZA RIBEIRO","nomeUrna":"KAMILA CARDOSO","partido":"AVANTE","numero":"700","votos":2002,"percentual":16.28,"sqcand":"60001633970"},{"nome":"ERIKA GONÇALVES AMORIM","nomeUrna":"ERIKA AMORIM","partido":"PSD","numero":"555","votos":1948,"percentual":15.84,"sqcand":"60001731829"}],"deputadosFederais":[{"nome":"EUNÍCIO LOPES DE OLIVEIRA","nomeUrna":"EUNÍCIO","partido":"MDB","numero":"1533","votos":3437,"percentual":27.58,"sqcand":"60001643110"},{"nome":"MARCOS ROBÉRIO RIBEIRO MONTEIRO","nomeUrna":"ROBÉRIO MONTEIRO","partido":"PDT","numero":"1233","votos":2686,"percentual":21.56,"sqcand":"60001603485"},{"nome":"ANTONIO LUIZ RODRIGUES MANO JUNIOR","nomeUrna":"JÚNIOR MANO","partido":"PL","numero":"2255","votos":1244,"percentual":9.98,"sqcand":"60001614151"},{"nome":"JOSE NOBRE GUIMARAES","nomeUrna":"GUIMARÃES DO PT","partido":"PT","numero":"1322","votos":801,"percentual":6.43,"sqcand":"60001619124"},{"nome":"ANTONIO IDILVAN DE LIMA ALENCAR","nomeUrna":"IDILVAN","partido":"PDT","numero":"1213","votos":531,"percentual":4.26,"sqcand":"60001603469"},{"nome":"ANDRÉ FERNANDES DE MOURA","nomeUrna":"ANDRÉ FERNANDES","partido":"PL","numero":"2222","votos":492,"percentual":3.95,"sqcand":"60001614161"},{"nome":"MOSES HAENDEL MELO RODRIGUES","nomeUrna":"MOSES RODRIGUES","partido":"UNIÃO","numero":"4488","votos":472,"percentual":3.79,"sqcand":"60001608894"},{"nome":"CARLOS MATOS LIMA","nomeUrna":"CARLOS MATOS","partido":"UNIÃO","numero":"4410","votos":275,"percentual":2.21,"sqcand":"60001608900"},{"nome":"CÉLIO STUDART BARBOSA","nomeUrna":"CÉLIO STUDART","partido":"PSD","numero":"5511","votos":237,"percentual":1.9,"sqcand":"60001601189"},{"nome":"JAZIEL PEREIRA DE SOUSA","nomeUrna":"DR JAZIEL","partido":"PL","numero":"2277","votos":200,"percentual":1.61,"sqcand":"60001614163"},{"nome":"DOMINGOS GOMES DE AGUIAR NETO","nomeUrna":"DOMINGOS NETO","partido":"PSD","numero":"5555","votos":160,"percentual":1.28,"sqcand":"60001601183"},{"nome":"RONALDO MANCHADO MARTINS","nomeUrna":"RONALDO MARTINS","partido":"REPUBLICANOS","numero":"1010","votos":155,"percentual":1.24,"sqcand":"60001608853"},{"nome":"LUIZ GASTÃO BITTENCOURT DA SILVA","nomeUrna":"LUIZ GASTÃO","partido":"PSD","numero":"5533","votos":136,"percentual":1.09,"sqcand":"60001601188"},{"nome":"LUIZIANNE DE OLIVEIRA LINS","nomeUrna":"LUIZIANNE LINS","partido":"PT","numero":"1313","votos":105,"percentual":0.84,"sqcand":"60001619128"},{"nome":"ANA PAULA BRANDÃO DA SILVA FARIAS","nomeUrna":"ENFERMEIRA ANA PAULA","partido":"PDT","numero":"1292","votos":97,"percentual":0.78,"sqcand":"60001603468"},{"nome":"MARIA GORETE PEREIRA","nomeUrna":"GORETE PEREIRA","partido":"PL","numero":"2233","votos":95,"percentual":0.76,"sqcand":"60001614153"},{"nome":"ANTONIO AGINALDO DE OLIVEIRA","nomeUrna":"CORONEL AGINALDO","partido":"PL","numero":"2210","votos":88,"percentual":0.71,"sqcand":"60001614162"},{"nome":"FRANCISCO VAIDON OLIVEIRA","nomeUrna":"VAIDON OLIVEIRA","partido":"UNIÃO","numero":"4455","votos":73,"percentual":0.59,"sqcand":"60001608892"},{"nome":"FRANCISCO DANILO BASTOS FORTE","nomeUrna":"DANILO FORTE","partido":"UNIÃO","numero":"4447","votos":73,"percentual":0.59,"sqcand":"60001608893"},{"nome":"INÁCIO FRANCISCO DE ASSIS NUNES ARRUDA","nomeUrna":"INÁCIO ARRUDA","partido":"PC do B","numero":"6565","votos":62,"percentual":0.5,"sqcand":"60001619126"},{"nome":"MAYRA ISABEL CORREIA PINHEIRO","nomeUrna":"DRA. MAYRA PINHEIRO","partido":"PL","numero":"2200","votos":58,"percentual":0.47,"sqcand":"60001614165"},{"nome":"FRANCISCO DE ASSIS CAVALCANTE NOGUEIRA","nomeUrna":"DELEGADO CAVALCANTE","partido":"PL","numero":"2201","votos":55,"percentual":0.44,"sqcand":"60001614170"},{"nome":"JOÃO ALFREDO TELLES MELO","nomeUrna":"JOÃO ALFREDO","partido":"PSOL","numero":"5001","votos":53,"percentual":0.43,"sqcand":"60001613063"},{"nome":"JOSÉ LEÔNIDAS DE MENEZES CRISTINO","nomeUrna":"LEÔNIDAS CRISTINO","partido":"PDT","numero":"1212","votos":52,"percentual":0.42,"sqcand":"60001603475"},{"nome":"JOSE AIRTON FELIX CIRILO DA SILVA","nomeUrna":"JOSE AIRTON","partido":"PT","numero":"1333","votos":50,"percentual":0.4,"sqcand":"60001619120"},{"nome":"FERNANDA ENEIDA PESSOA CARACAS DE SOUZA","nomeUrna":"FERNANDA PESSOA","partido":"UNIÃO","numero":"4477","votos":46,"percentual":0.37,"sqcand":"60001608882"},{"nome":"ANTONIO JOSÉ AGUIAR ALBUQUERQUE","nomeUrna":"AJ ALBUQUERQUE","partido":"PP","numero":"1111","votos":44,"percentual":0.35,"sqcand":"60001619170"},{"nome":"DAYANY BITTENCOURT SANTIL","nomeUrna":"DAYANY DO CAPITÃO","partido":"UNIÃO","numero":"4456","votos":43,"percentual":0.35,"sqcand":"60001608898"},{"nome":"JULIERME LIMA DE SENA","nomeUrna":"JULIERME SENA","partido":"UNIÃO","numero":"4422","votos":43,"percentual":0.35,"sqcand":"60001608899"},{"nome":"EDUARDO HENRIQUE MAIA BISMARCK","nomeUrna":"EDUARDO BISMARCK","partido":"PDT","numero":"1214","votos":42,"percentual":0.34,"sqcand":"60001603472"},{"nome":"NOELIO DA ROCHA OLIVEIRA","nomeUrna":"SOLDADO NOELIO","partido":"UNIÃO","numero":"4490","votos":40,"percentual":0.32,"sqcand":"60001608884"},{"nome":"HEITOR RODRIGO PEREIRA FREIRE","nomeUrna":"HEITOR FREIRE","partido":"UNIÃO","numero":"4444","votos":34,"percentual":0.27,"sqcand":"60001608890"},{"nome":"PRISCILA BEZERRA DA COSTA","nomeUrna":"PRISCILA COSTA","partido":"PL","numero":"2288","votos":28,"percentual":0.22,"sqcand":"60001614167"},{"nome":"DENIS ANDERSON DA ROCHA BEZERRA","nomeUrna":"DENIS BEZERRA","partido":"PSB","numero":"4000","votos":26,"percentual":0.21,"sqcand":"60001603454"},{"nome":"ANDRÉ PEIXOTO FIGUEIREDO LIMA","nomeUrna":"ANDRÉ FIGUEIREDO","partido":"PDT","numero":"1234","votos":25,"percentual":0.2,"sqcand":"60001603484"},{"nome":"JOSÉ ARNON CRUZ BEZERRA DE MENEZES","nomeUrna":"ARNON BEZERRA","partido":"PDT","numero":"1251","votos":22,"percentual":0.18,"sqcand":"60001634339"},{"nome":"JOSÉ TARSO MAGNO TEIXEIRA DA SILVA","nomeUrna":"TARSO MAGNO","partido":"PP","numero":"1123","votos":18,"percentual":0.14,"sqcand":"60001619165"},{"nome":"CHRISTIANNE MARIE AGUIAR COELHO","nomeUrna":"CHRISTIANNE COELHO","partido":"PT","numero":"1321","votos":15,"percentual":0.12,"sqcand":"60001619125"},{"nome":"FRANCISCO ANTÔNIO PEREIRA GOMES","nomeUrna":"CHICO ANTÔNIO","partido":"AVANTE","numero":"7040","votos":13,"percentual":0.1,"sqcand":"60001634087"},{"nome":"JOICIANA SOUSA MATOS CANUTO","nomeUrna":"JOICIANA CANUTO SEREIA","partido":"PODE","numero":"1924","votos":12,"percentual":0.1,"sqcand":"60001633781"},{"nome":"FRANCISCO WAGNER LOBO PEREIRA","nomeUrna":"PROF WAGNER LOBO","partido":"REPUBLICANOS","numero":"1090","votos":12,"percentual":0.1,"sqcand":"60001608864"},{"nome":"REGINA CLÁUDIA TABOSA FERREIRA GOMES","nomeUrna":"CLAUDIA GOMES","partido":"PSDB","numero":"4555","votos":12,"percentual":0.1,"sqcand":"60001723392"},{"nome":"RONDINELLE PEREIRA DE FREITAS","nomeUrna":"NELINHO","partido":"MDB","numero":"1522","votos":11,"percentual":0.09,"sqcand":"60001643127"},{"nome":"GABRIEL LIMA DE AGUIAR","nomeUrna":"GABRIEL BIOLOGIA","partido":"PSOL","numero":"5055","votos":11,"percentual":0.09,"sqcand":"60001613061"},{"nome":"YURY BRUNO ALENCAR ARAÚJO","nomeUrna":"YURY DO PAREDÃO","partido":"PL","numero":"2211","votos":10,"percentual":0.08,"sqcand":"60001614155"},{"nome":"AGRIPINO RODRIGUES GOMES MAGALHAES","nomeUrna":"DR. AGRIPINO MAGALHÃES","partido":"UNIÃO","numero":"4433","votos":10,"percentual":0.08,"sqcand":"60001608888"},{"nome":"LUIZ CARLOS CARDOSO DO NASCIMENTO JUNIOR","nomeUrna":"LUIZ CARLOS JR","partido":"UNIÃO","numero":"4400","votos":9,"percentual":0.07,"sqcand":"60001608887"},{"nome":"NATÁLIA SOARES RIOS","nomeUrna":"NATÁLIA RIOS","partido":"PDT","numero":"1232","votos":9,"percentual":0.07,"sqcand":"60001603465"},{"nome":"ANA LIDIA RODRIGUES LIMA","nomeUrna":"LÍDIA DO BORA DE RUMA","partido":"PSOL","numero":"5044","votos":8,"percentual":0.06,"sqcand":"60001613079"},{"nome":"AILTON CLAÉCIO LOPES DANTAS","nomeUrna":"AILTON LOPES","partido":"PSOL","numero":"5050","votos":8,"percentual":0.06,"sqcand":"60001613070"},{"nome":"MARIA DO ROSÁRIO RAMALHO GARCIA","nomeUrna":"ROSÂNIA RAMALHO","partido":"PDT","numero":"1222","votos":8,"percentual":0.06,"sqcand":"60001603478"},{"nome":"CARLOS MAURO BENEVIDES FILHO","nomeUrna":"MAURO FILHO","partido":"PDT","numero":"1221","votos":7,"percentual":0.06,"sqcand":"60001603470"},{"nome":"MARIA DALILA DE SOUZA FERNANDES","nomeUrna":"DALILA ELOY","partido":"AVANTE","numero":"7090","votos":7,"percentual":0.06,"sqcand":"60001634096"},{"nome":"DAMIAO SOARES TENORIO","nomeUrna":"DAMIÃO TENORIO","partido":"UNIÃO","numero":"4445","votos":6,"percentual":0.05,"sqcand":"60001608879"},{"nome":"ADELITTA MONTEIRO NUNES","nomeUrna":"ADELITA MONTEIRO","partido":"PSOL","numero":"5013","votos":6,"percentual":0.05,"sqcand":"60001613067"},{"nome":"MATHEUS SOARES NORONHA","nomeUrna":"MATHEUS NORONHA","partido":"PL","numero":"2299","votos":6,"percentual":0.05,"sqcand":"60001614168"},{"nome":"MARIA CRERINEUMA DE OLIVEIRA SILVA","nomeUrna":"CLERYNEUMA","partido":"PDT","numero":"1255","votos":6,"percentual":0.05,"sqcand":"60001603479"},{"nome":"ADRIELLY DE PAULA TEIXEIRA","nomeUrna":"ADRIELLY TEIXEIRA","partido":"PDT","numero":"1245","votos":6,"percentual":0.05,"sqcand":"60001603467"},{"nome":"FRANCISCO NILSON ALVES DINIZ","nomeUrna":"DR NILSON DINIZ","partido":"PDT","numero":"1299","votos":6,"percentual":0.05,"sqcand":"60001603481"},{"nome":"FRANCISCO RODRIGO DE MATOS DE SOUZA","nomeUrna":"PR RODRIGO MATOS","partido":"REPUBLICANOS","numero":"1016","votos":6,"percentual":0.05,"sqcand":"60001608854"},{"nome":"MANOEL PARENTE DE HOLANDA","nomeUrna":"PARENTE","partido":"PMB","numero":"3550","votos":5,"percentual":0.04,"sqcand":"60001645990"},{"nome":"MORONI BING TORGAN","nomeUrna":"MORONI","partido":"CIDADANIA","numero":"2323","votos":5,"percentual":0.04,"sqcand":"60001723397"},{"nome":"TADEU MAGELA DE OLIVEIRA","nomeUrna":"TADEU OLIVEIRA","partido":"PL","numero":"2244","votos":4,"percentual":0.03,"sqcand":"60001614166"},{"nome":"FRANCISCO ANTONIO FERREIRA LOPES","nomeUrna":"KIM LOPES","partido":"PT","numero":"1323","votos":4,"percentual":0.03,"sqcand":"60001619132"},{"nome":"JOSÉ ERONILDO NARCISO DA SILVA","nomeUrna":"ERON NARCISO","partido":"MDB","numero":"1531","votos":4,"percentual":0.03,"sqcand":"60001643125"},{"nome":"XISTO SOARES DE OLIVEIRA","nomeUrna":"XISTO","partido":"PP","numero":"1133","votos":4,"percentual":0.03,"sqcand":"60001619167"},{"nome":"FRANCISCO EDIVAN NONATO DA SILVA","nomeUrna":"PASTOR EDIVAN","partido":"AVANTE","numero":"7000","votos":4,"percentual":0.03,"sqcand":"60001634088"},{"nome":"MANOEL ALVES DE OLIVEIRA","nomeUrna":"LASKADIM","partido":"PROS","numero":"9000","votos":4,"percentual":0.03,"sqcand":"60001619090"},{"nome":"VALDERLAN ALVES DE SOUZA","nomeUrna":"VANDERLAN ALVES","partido":"UNIÃO","numero":"4411","votos":4,"percentual":0.03,"sqcand":"60001608897"},{"nome":"FRANCISCO DAS CHAGAS RODRIGUES ALVES","nomeUrna":"NENEM DA SEFAZ","partido":"PL","numero":"2225","votos":3,"percentual":0.02,"sqcand":"60001614158"},{"nome":"LEDA VASCONCELOS CARVALHO","nomeUrna":"LEDA VASCONCELOS","partido":"PT","numero":"1331","votos":3,"percentual":0.02,"sqcand":"60001619129"},{"nome":"REGINA MAURA VILLELA BARBOZA","nomeUrna":"REGINA VILLELA","partido":"MDB","numero":"1588","votos":3,"percentual":0.02,"sqcand":"60001643126"},{"nome":"CICERO ANTÔNIO PINHEIRO DOS SANTOS","nomeUrna":"CÍCERO ANIMAL DAS PISTAS","partido":"MDB","numero":"1580","votos":3,"percentual":0.02,"sqcand":"60001643122"},{"nome":"ÉRICO JOVINO SALES","nomeUrna":"ÉRICO JOVINO","partido":"MDB","numero":"1500","votos":3,"percentual":0.02,"sqcand":"60001643117"},{"nome":"CARLOS ALBERTO ALVES ROCHA","nomeUrna":"ROBERTO RIZZO","partido":"PP","numero":"1177","votos":3,"percentual":0.02,"sqcand":"60001619164"},{"nome":"FRANCISCO NELHO BEZERRA","nomeUrna":"NELHO BEZERRA","partido":"UNIÃO","numero":"4406","votos":3,"percentual":0.02,"sqcand":"60001608891"},{"nome":"JULIO BRIZZI NETO","nomeUrna":"JULIO BRIZZI","partido":"PDT","numero":"1201","votos":3,"percentual":0.02,"sqcand":"60001603476"},{"nome":"KELVYA COSTA ALBUQUERQUE","nomeUrna":"KELVYA ALBUQUERQUE","partido":"PSD","numero":"5566","votos":3,"percentual":0.02,"sqcand":"60001601194"},{"nome":"FRANCISCA ELIANE BRAZ DE CARVALHO","nomeUrna":"ELIANE BRAZ","partido":"PSD","numero":"5588","votos":3,"percentual":0.02,"sqcand":"60001601192"},{"nome":"VANESSA FALCÃO DE SOUZA CASTELO LIMA","nomeUrna":"BISPA VANESSA LIMA","partido":"REPUBLICANOS","numero":"1000","votos":3,"percentual":0.02,"sqcand":"60001608850"},{"nome":"FELIPE MONTEIRO ANDRADE ARAÚJO","nomeUrna":"DR FELIPE MONTEIRO","partido":"REPUBLICANOS","numero":"1012","votos":3,"percentual":0.02,"sqcand":"60001608863"},{"nome":"GABRIELLA PAIVA DOS SANTOS","nomeUrna":"PROFESSORA GABRIELLA","partido":"REPUBLICANOS","numero":"1044","votos":3,"percentual":0.02,"sqcand":"60001608856"},{"nome":"DANIELE PIMENTEL DE OLIVEIRA","nomeUrna":"DANIELE PIMENTEL","partido":"PSB","numero":"4077","votos":3,"percentual":0.02,"sqcand":"60001603459"},{"nome":"KARLA PATRICIA MATOS CORREIA","nomeUrna":"PATRICIA MARXS","partido":"UNIÃO","numero":"4466","votos":2,"percentual":0.02,"sqcand":"60001608880"},{"nome":"MARIA DE LOURDES PAZ FELIX","nomeUrna":"LOURDINHA FELIX","partido":"PT","numero":"1311","votos":2,"percentual":0.02,"sqcand":"60001619134"},{"nome":"MICHAEL GANDHI MONTEIRO DOS SANTOS","nomeUrna":"PROFESSOR GANDHI","partido":"MDB","numero":"1599","votos":2,"percentual":0.02,"sqcand":"60001643114"},{"nome":"JOSÉ GERALDO DE QUEIROS","nomeUrna":"COWBOY QUEIROZ","partido":"PTB","numero":"1400","votos":2,"percentual":0.02,"sqcand":"60001668482"},{"nome":"DIANA HELENA SOARES ROCHA MARINHO SARAIVA","nomeUrna":"DIANA MARINHO","partido":"PODE","numero":"1933","votos":2,"percentual":0.02,"sqcand":"60001633772"},{"nome":"ANNA KARINA CAVALCANTE DE OLIVEIRA","nomeUrna":"ANNA KARINA VOZES FEMINISTAS","partido":"PSOL","numero":"5005","votos":2,"percentual":0.02,"sqcand":"60001613071"},{"nome":"ROBERTA MENEZES SOUSA","nomeUrna":"ROBERTA MENEZES","partido":"PSOL","numero":"5088","votos":2,"percentual":0.02,"sqcand":"60001613064"},{"nome":"RAIMUNDO GOMES FARIAS","nomeUrna":"GOMES FARIAS","partido":"PP","numero":"1112","votos":2,"percentual":0.02,"sqcand":"60001619173"},{"nome":"ELINETE TORRES DA SILVA","nomeUrna":"ELINETE TORRES","partido":"PP","numero":"1113","votos":2,"percentual":0.02,"sqcand":"60001619159"},{"nome":"RAFAEL AURELIANO GONÇALVES BRANCO","nomeUrna":"RAFAEL BRANCO","partido":"PP","numero":"1100","votos":2,"percentual":0.02,"sqcand":"60001619160"},{"nome":"MARCOS ANTÔNIO DE ARAÚJO MENDONÇA","nomeUrna":"DR MARCOS","partido":"AVANTE","numero":"7011","votos":2,"percentual":0.02,"sqcand":"60001634106"},{"nome":"JOSÉ ALEXANDRE OLIVEIRA SOBREIRA","nomeUrna":"ALEXANDRE SOBREIRA","partido":"AVANTE","numero":"7070","votos":2,"percentual":0.02,"sqcand":"60001634090"},{"nome":"CARLOS EDUARDO MARTINS TORRES","nomeUrna":"DR CADU","partido":"AVANTE","numero":"7007","votos":2,"percentual":0.02,"sqcand":"60001634104"},{"nome":"ELAYNE SILVA CARVALHO","nomeUrna":"ELAYNE CARVALHO","partido":"PDT","numero":"1269","votos":2,"percentual":0.02,"sqcand":"60001603482"},{"nome":"NAUMI GOMES DE AMORIM","nomeUrna":"NAUMI AMORIM","partido":"PSD","numero":"5500","votos":2,"percentual":0.02,"sqcand":"60001601196"},{"nome":"FABIANO MAGALHÃES DE MESQUITA","nomeUrna":"FABIANO LOBO","partido":"PSD","numero":"5515","votos":2,"percentual":0.02,"sqcand":"60001601190"},{"nome":"MARCOS ANTONIO MORAES LIMA","nomeUrna":"MARCOS LIMA","partido":"PSD","numero":"5522","votos":2,"percentual":0.02,"sqcand":"60001601181"},{"nome":"ERLAN MARTINS DOS SANTOS","nomeUrna":"ERLAN BASTOS","partido":"REPUBLICANOS","numero":"1020","votos":2,"percentual":0.02,"sqcand":"60001608860"},{"nome":"ABRAÃO GOMES DA SILVA","nomeUrna":"PASTOR ABRAÃO","partido":"REPUBLICANOS","numero":"1023","votos":2,"percentual":0.02,"sqcand":"60001608858"},{"nome":"ALANDERSON DE CASTRO MANGUEIRA","nomeUrna":"ALANDERSON MANGUEIRA","partido":"PSB","numero":"4012","votos":2,"percentual":0.02,"sqcand":"60001603455"},{"nome":"VERONICA DO AMARAL MADEIRO BATISTA","nomeUrna":"DRA VERONICA AMARAL","partido":"PL","numero":"2227","votos":1,"percentual":0.01,"sqcand":"60001614152"},{"nome":"FRANCISCO DERIVALDO GONÇALVES LIMA","nomeUrna":"VALDIM GONÇALVES","partido":"PL","numero":"2220","votos":1,"percentual":0.01,"sqcand":"60001614159"},{"nome":"JOSÉ SUDERLAN DE CASTRO LIMA","nomeUrna":"SUDERLAN CASTRO","partido":"PMN","numero":"3389","votos":1,"percentual":0.01,"sqcand":"60001692742"},{"nome":"CELSO FARIAS FERREIRA","nomeUrna":"CELSO FARIAS","partido":"PT","numero":"1326","votos":1,"percentual":0.01,"sqcand":"60001619136"},{"nome":"MAX SWELL VERAS RIBEIRO","nomeUrna":"MAXSWELL","partido":"PT","numero":"1399","votos":1,"percentual":0.01,"sqcand":"60001619138"},{"nome":"PAULO EMILIO CORDEIRO CAMPOS","nomeUrna":"PAULO EMILIO","partido":"PT","numero":"1353","votos":1,"percentual":0.01,"sqcand":"60001619121"},{"nome":"CARLOS ANDRÉ SOARES FERNANDES","nomeUrna":"CARLOS DJ","partido":"AGIR","numero":"3615","votos":1,"percentual":0.01,"sqcand":"60001712973"},{"nome":"CELSO DOS SANTOS","nomeUrna":"CELSO SANTOS","partido":"PL","numero":"2266","votos":1,"percentual":0.01,"sqcand":"60001614169"},{"nome":"LUIZ CLAUDIO ALVES BRITO","nomeUrna":"DOM CLAUDIO","partido":"MDB","numero":"1556","votos":1,"percentual":0.01,"sqcand":"60001643112"},{"nome":"FRANCISCO CÉSAR NOGUEIRA DA SILVA","nomeUrna":"CÉSAR DO VALE","partido":"MDB","numero":"1513","votos":1,"percentual":0.01,"sqcand":"60001643124"},{"nome":"EDINA NOGUEIRA DE CASTRO ROCHA","nomeUrna":"EDINA NOGUEIRA","partido":"PTB","numero":"1433","votos":1,"percentual":0.01,"sqcand":"60001668470"},{"nome":"JOSÉ AIRTON MACEDO DE SOUSA","nomeUrna":"PROFESSOR AIRTON MACEDO","partido":"PTB","numero":"1425","votos":1,"percentual":0.01,"sqcand":"60001668476"},{"nome":"FRANCISCO ROBERTO DOS SANTOS","nomeUrna":"ROBERTO SANTOS","partido":"PCB","numero":"2123","votos":1,"percentual":0.01,"sqcand":"60001692687"},{"nome":"GILBERTO LINARD ROCHA JÚNIOR","nomeUrna":"MATHEUS LINARD","partido":"PODE","numero":"1919","votos":1,"percentual":0.01,"sqcand":"60001633783"},{"nome":"LINIK SUED CARVALHO DA MOTA","nomeUrna":"SUED CARVALHO","partido":"UP","numero":"8080","votos":1,"percentual":0.01,"sqcand":"60001634340"},{"nome":"MAYA ELIZ SOUSA LIMA","nomeUrna":"MAYA ELIZ","partido":"PSOL","numero":"5007","votos":1,"percentual":0.01,"sqcand":"60001613077"},{"nome":"ANTONIA GUEDES CABRAL AGUIAR ROCHA","nomeUrna":"TOINHA ROCHA","partido":"REDE","numero":"1818","votos":1,"percentual":0.01,"sqcand":"60001613069"},{"nome":"CICERO JOHNNY ALVES MOTA","nomeUrna":"JOHNNY DO SOMOS DO INTERIOR","partido":"REDE","numero":"1888","votos":1,"percentual":0.01,"sqcand":"60001613066"},{"nome":"JOSÉ VALBERTO LEITE ESMERALDO","nomeUrna":"VALBERTO DO SERRANO","partido":"AVANTE","numero":"7078","votos":1,"percentual":0.01,"sqcand":"60001634099"},{"nome":"PEDRO SÉRGIO TEIXEIRA DANTAS","nomeUrna":"SÉRGIO DANTAS","partido":"PP","numero":"1122","votos":1,"percentual":0.01,"sqcand":"60001619161"},{"nome":"FRANCISCO HERMANO LEANDRO DA SILVA GOMES","nomeUrna":"HERMANO GOMES","partido":"AVANTE","numero":"7060","votos":1,"percentual":0.01,"sqcand":"60001634089"},{"nome":"ANTONIO NIERTON QUEIROZ GUERRA","nomeUrna":"NIERTON GUERRA","partido":"PATRIOTA","numero":"5133","votos":1,"percentual":0.01,"sqcand":"60001619144"},{"nome":"SAMILA BRAGA CAVALCANTE","nomeUrna":"SÂMILA MÃE DO GABRIEL","partido":"UNIÃO","numero":"4499","votos":1,"percentual":0.01,"sqcand":"60001608881"},{"nome":"IANNA FERNANDES DE ALMEIDA BRANDÃO","nomeUrna":"IANNA BRANDÃO","partido":"PDT","numero":"1285","votos":1,"percentual":0.01,"sqcand":"60001603474"},{"nome":"KARINA CORDEIRO DE SOUZA RODRIGUES","nomeUrna":"ENFERMEIRA KARINA","partido":"PDT","numero":"1252","votos":1,"percentual":0.01,"sqcand":"60001603477"},{"nome":"ADAIL FERNANDES VIEIRA JUNIOR","nomeUrna":"ADAIL JR","partido":"PDT","numero":"1277","votos":1,"percentual":0.01,"sqcand":"60001603487"},{"nome":"CINTHIA BELINO OLIVEIRA DA COSTA","nomeUrna":"DRA CINTHIA BELINO","partido":"PSC","numero":"2022","votos":1,"percentual":0.01,"sqcand":"60001645841"},{"nome":"ANDRÉ LUIZ BARBOSA AZEVEDO","nomeUrna":"ANDRÉ PEZÃO","partido":"PSC","numero":"2033","votos":1,"percentual":0.01,"sqcand":"60001645832"},{"nome":"GERALDO AMANCIO PEREIRA","nomeUrna":"POETA GERALDO AMANCIO","partido":"PSD","numero":"5567","votos":1,"percentual":0.01,"sqcand":"60001601184"},{"nome":"MARIA JOSÉ MAIA","nomeUrna":"DRA MAZÉ MAIA","partido":"PSD","numero":"5577","votos":1,"percentual":0.01,"sqcand":"60001601185"},{"nome":"CRISTIANE COLARES MUNIZ","nomeUrna":"ENFERMEIRA CRISTIANE COLARES","partido":"REPUBLICANOS","numero":"1013","votos":1,"percentual":0.01,"sqcand":"60001608855"},{"nome":"SAMUEL LIMA PAULO DO RAMO","nomeUrna":"SAMUEL LIMA ","partido":"NOVO","numero":"3000","votos":1,"percentual":0.01,"sqcand":"60001595308"},{"nome":"MARCIO BARROS MAIA","nomeUrna":"MÁRCIO BARROS","partido":"PMB","numero":"3500","votos":1,"percentual":0.01,"sqcand":"60001645991"},{"nome":"RAIMUNDO GERSON DOS SANTOS LIMA","nomeUrna":"SARGENTO GERSON","partido":"PSDB","numero":"4512","votos":1,"percentual":0.01,"sqcand":"60001723388"},{"nome":"ANDERSON PEROBA GOMES","nomeUrna":"DOUTOR ANDERSON PEROBA","partido":"CIDADANIA","numero":"2300","votos":1,"percentual":0.01,"sqcand":"60001723390"},{"nome":"FRANCISCO CARLOS MACEDO TAVARES","nomeUrna":"DR CARLOS MACEDO","partido":"PSB","numero":"4040","votos":1,"percentual":0.01,"sqcand":"60001603462"},{"nome":"MARÍLIA FREIRE PAIVA","nomeUrna":"MARILIA DO POSTO","partido":"PSB","numero":"4088","votos":1,"percentual":0.01,"sqcand":"60001603450"},{"nome":"PAULO DE TARSO FACO BEZERRA","nomeUrna":"PAULO FACÓ","partido":"PSB","numero":"4010","votos":1,"percentual":0.01,"sqcand":"60001603443"},{"nome":"HEITOR CLAUDIO PORTELA DE HOLANDA","nomeUrna":"HEITOR HOLANDA","partido":"PSB","numero":"4050","votos":1,"percentual":0.01,"sqcand":"60001603445"}],"deputadosEstaduais":[{"nome":"ANTONIO ALYSSON DE AGUIAR PAULA","nomeUrna":"ALYSSON AGUIAR","partido":"PC do B","numero":"65700","votos":3789,"percentual":32.06,"sqcand":"60001633672"},{"nome":"AGOSTINHO FREDERICO TIN CARMO GOMES","nomeUrna":"TIN GOMES","partido":"PDT","numero":"12600","votos":2760,"percentual":23.36,"sqcand":"60001603539"},{"nome":"SERGIO DE ARAÚJO LIMA AGUIAR","nomeUrna":"SERGIO AGUIAR","partido":"PDT","numero":"12888","votos":1759,"percentual":14.89,"sqcand":"60001603516"},{"nome":"OSCAR SPINDOLA RODRIGUES JUNIOR","nomeUrna":"DR. OSCAR RODRIGUES","partido":"UNIÃO","numero":"44888","votos":285,"percentual":2.41,"sqcand":"60001608929"},{"nome":"PAULO WAGNER AGUIAR COSTA","nomeUrna":"PAULO WAGNER","partido":"UNIÃO","numero":"44000","votos":244,"percentual":2.06,"sqcand":"60001608934"},{"nome":"ALCIDES FERNANDES DA SILVA","nomeUrna":"PR.ALCIDES FERNANDES","partido":"PL","numero":"22222","votos":213,"percentual":1.8,"sqcand":"60001633829"},{"nome":"SILVANA OLIVEIRA DE SOUSA","nomeUrna":"DRA SILVANA","partido":"PL","numero":"22777","votos":189,"percentual":1.6,"sqcand":"60001633828"},{"nome":"ORTUAM FIDELES DE ALBUQUERQUE","nomeUrna":"ORTUAM FIDELES","partido":"PSDB","numero":"45413","votos":179,"percentual":1.51,"sqcand":"60001723728"},{"nome":"ANTONIO ALMIR BIÉ DA SILVA","nomeUrna":"ALMIR BIÉ","partido":"PP","numero":"11113","votos":143,"percentual":1.21,"sqcand":"60001619181"},{"nome":"DAVID DE ALBUQUERQUE DURAND","nomeUrna":"DAVID DURAND","partido":"REPUBLICANOS","numero":"10123","votos":140,"percentual":1.18,"sqcand":"60001608816"},{"nome":"ANTONIO VALDENIZO DA COSTA","nomeUrna":"NIZO ","partido":"PT","numero":"13777","votos":132,"percentual":1.12,"sqcand":"60001633657"},{"nome":"DANIEL BORGES DA SILVA","nomeUrna":"DANIEL BORGES","partido":"AVANTE","numero":"70321","votos":124,"percentual":1.05,"sqcand":"60001634405"},{"nome":"CARMELO SILVEIRA CARNEIRO LEÃO NETO","nomeUrna":"CARMELO NETO","partido":"PL","numero":"22022","votos":119,"percentual":1.01,"sqcand":"60001633791"},{"nome":"HENRIQUE SÁVIO PEREIRA PONTES","nomeUrna":"SÁVIO PONTES","partido":"PSD","numero":"55111","votos":117,"percentual":0.99,"sqcand":"60001613532"},{"nome":"JOSÉ DE ARAUJO DANTAS FILHO","nomeUrna":"TENENTE DANTAS","partido":"CIDADANIA","numero":"23190","votos":107,"percentual":0.91,"sqcand":"60001723719"},{"nome":"AGENOR GOMES DE ARAUJO NETO","nomeUrna":"AGENOR NETO","partido":"MDB","numero":"15888","votos":86,"percentual":0.73,"sqcand":"60001635809"},{"nome":"RENATO ROSENO DE OLIVEIRA","nomeUrna":"RENATO ROSENO","partido":"PSOL","numero":"50500","votos":70,"percentual":0.59,"sqcand":"60001613104"},{"nome":"MARCELO FERREIRA MOREIRA","nomeUrna":"DR MARCELO","partido":"PL","numero":"22422","votos":65,"percentual":0.55,"sqcand":"60001633813"},{"nome":"ROMEU ALDIGUERI DE ARRUDA COELHO","nomeUrna":"ROMEU ALDIGUERI","partido":"PDT","numero":"12456","votos":64,"percentual":0.54,"sqcand":"60001603528"},{"nome":"MARTA BRANDÃO DA SILVA","nomeUrna":"MARTINHA - A SAÚDE RESISTE","partido":"CIDADANIA","numero":"23192","votos":61,"percentual":0.52,"sqcand":"60001723716"},{"nome":"FRANCISCO TANCREDO DE OLIVEIRA","nomeUrna":"TAM DE OLIVEIRA","partido":"AVANTE","numero":"70000","votos":43,"percentual":0.36,"sqcand":"60001634415"},{"nome":"JOÃO JAIME GOMES MARINHO DE ANDRADE","nomeUrna":"JOÃO JAIME","partido":"PP","numero":"11000","votos":42,"percentual":0.36,"sqcand":"60001619178"},{"nome":"MOISES BRAZ RICARDO","nomeUrna":"MOISES BRAZ","partido":"PT","numero":"13333","votos":38,"percentual":0.32,"sqcand":"60001633642"},{"nome":"MARCOS MARCEL RODRIGUES SOBREIRA","nomeUrna":"MARCOS SOBREIRA","partido":"PDT","numero":"12333","votos":35,"percentual":0.3,"sqcand":"60001603545"},{"nome":"LIA FERREIRA GOMES","nomeUrna":"LIA GOMES","partido":"PDT","numero":"12345","votos":34,"percentual":0.29,"sqcand":"60001603543"},{"nome":"REGINAURO SOUSA NASCIMENTO","nomeUrna":"SARGENTO REGINAURO","partido":"UNIÃO","numero":"44190","votos":33,"percentual":0.28,"sqcand":"60001608935"},{"nome":"ANÍZIO SANTOS DE MELO","nomeUrna":"PROFESSOR ANÍZIO","partido":"PC do B","numero":"65013","votos":33,"percentual":0.28,"sqcand":"60001633644"},{"nome":"FRANCISCO CLAUDIO SANTOS DE ANDRADE","nomeUrna":"PROFESSOR CLAUDIO CHANDELLE","partido":"PMN","numero":"33890","votos":32,"percentual":0.27,"sqcand":"60001646069"},{"nome":"FRANCISCO DAVID VASCONCELOS CARNEIRO","nomeUrna":"DAVID PROARMAS","partido":"PL","numero":"22556","votos":32,"percentual":0.27,"sqcand":"60001633823"},{"nome":"JULIANA DE HOLANDA LUCENA RODRIGUES","nomeUrna":"JULIANA LUCENA","partido":"PT","numero":"13555","votos":31,"percentual":0.26,"sqcand":"60001633675"},{"nome":"BRUNO TORQUATO PEDROSA","nomeUrna":"BRUNO PEDROSA","partido":"PDT","numero":"12999","votos":30,"percentual":0.25,"sqcand":"60001603532"},{"nome":"JOLNÊ BINDA PRAXEDES","nomeUrna":"PRAXEDES","partido":"PL","numero":"22322","votos":25,"percentual":0.21,"sqcand":"60001633803"},{"nome":"MANOEL MISSIAS BEZERRA","nomeUrna":"MISSIAS DO MST","partido":"PT","numero":"13123","votos":24,"percentual":0.2,"sqcand":"60001633648"},{"nome":"THIAGO CAMILO CIRIACO","nomeUrna":"THIAGO CIRIACO","partido":"PMN","numero":"33888","votos":24,"percentual":0.2,"sqcand":"60001646046"},{"nome":"DANNIEL LOPES DE OLIVEIRA SOUSA","nomeUrna":"DANNIEL OLIVEIRA","partido":"MDB","numero":"15333","votos":24,"percentual":0.2,"sqcand":"60001635805"},{"nome":"JOSÉ FIRMO CAMURÇA NETO","nomeUrna":"FIRMO CAMURÇA","partido":"UNIÃO","numero":"44777","votos":23,"percentual":0.19,"sqcand":"60001608940"},{"nome":"JOÃO SALMITO FILHO","nomeUrna":"SALMITO","partido":"PDT","numero":"12500","votos":23,"percentual":0.19,"sqcand":"60001603518"},{"nome":"FRANCISCO ADRIANO PEREIRA DE ABREU","nomeUrna":"ADRIANNO IMPERADOR","partido":"UNIÃO","numero":"44774","votos":23,"percentual":0.19,"sqcand":"60001608913"},{"nome":"ELVILO ARAUJO DE OLIVEIRA","nomeUrna":"GORDIM ARAUJO","partido":"PSDB","numero":"45111","votos":19,"percentual":0.16,"sqcand":"60001723713"},{"nome":"FRANCISCO CLAUDIO PINTO PINHO","nomeUrna":"CLÁUDIO PINHO","partido":"PDT","numero":"12123","votos":19,"percentual":0.16,"sqcand":"60001603529"},{"nome":"RICARDO CÉLIO CHAGAS BEZERRA","nomeUrna":"CORONEL BEZERRA","partido":"UNIÃO","numero":"44456","votos":19,"percentual":0.16,"sqcand":"60001608939"},{"nome":"JOSÉ RIBEIRO DOS SANTOS","nomeUrna":"JOSÉ RIBEIRO","partido":"AVANTE","numero":"70600","votos":19,"percentual":0.16,"sqcand":"60001634397"},{"nome":"JOSÉ JEOVÁ SOUTO MOTA","nomeUrna":"JEOVÁ MOTA","partido":"PDT","numero":"12444","votos":18,"percentual":0.15,"sqcand":"60001603522"},{"nome":"GABRIELLA PEQUENO COSTA GOMES DE AGUIAR","nomeUrna":"GABRIELLA AGUIAR","partido":"PSD","numero":"55555","votos":17,"percentual":0.14,"sqcand":"60001613538"},{"nome":"JOSÉ CAVALCANTE CARDOSO NETO","nomeUrna":"PROFESSOR CARDOSO NETO","partido":"UNIÃO","numero":"44027","votos":15,"percentual":0.13,"sqcand":"60001608922"},{"nome":"JORGE LUIZ CAVALCANTE DE BRITO PINHEIRO","nomeUrna":"JORGE PINHEIRO","partido":"PSDB","numero":"45000","votos":14,"percentual":0.12,"sqcand":"60001723714"},{"nome":"ISABELLE LÚCIA AGUIAR FERMANIAN MUNGUBA","nomeUrna":"ISABELLE MUNGUBA","partido":"UNIÃO","numero":"44447","votos":14,"percentual":0.12,"sqcand":"60001608905"},{"nome":"EVANDRO SÁ BARRETO LEITÃO","nomeUrna":"EVANDRO LEITÃO","partido":"PDT","numero":"12000","votos":14,"percentual":0.12,"sqcand":"60001603535"},{"nome":"JOSE ACRISIO DE SENA","nomeUrna":"ACRISIO SENA","partido":"PT","numero":"13132","votos":14,"percentual":0.12,"sqcand":"60001633668"},{"nome":"EDILARDO EUFRASIO DA CRUZ","nomeUrna":"EDILARDO EUFRASIO","partido":"MDB","numero":"15000","votos":14,"percentual":0.12,"sqcand":"60001635815"},{"nome":"LARISSA MARIA FERNANDES GASPAR DA COSTA","nomeUrna":"LARISSA GASPAR","partido":"PT","numero":"13133","votos":13,"percentual":0.11,"sqcand":"60001633656"},{"nome":"ALBERTO LIMA DA SILVA","nomeUrna":"ALBERTO LIMA","partido":"AVANTE","numero":"70070","votos":13,"percentual":0.11,"sqcand":"60001634425"},{"nome":"LEONARDO DE SOUZA XAVIER","nomeUrna":"LÉO SURICATE","partido":"PSOL","numero":"50013","votos":13,"percentual":0.11,"sqcand":"60001613103"},{"nome":"JULIO CESAR COSTA LIMA JUNIOR","nomeUrna":"JULINHO","partido":"PT","numero":"13789","votos":12,"percentual":0.1,"sqcand":"60001633659"},{"nome":"FRANCISCO JOSE QUEIROZ MAIA FILHO","nomeUrna":"QUEIROZ FILHO","partido":"PDT","numero":"12300","votos":12,"percentual":0.1,"sqcand":"60001603536"},{"nome":"MARIA EMILIA PESSOA DE LIMA CARNEIRO","nomeUrna":"EMILIA PESSOA","partido":"PSDB","numero":"45123","votos":10,"percentual":0.08,"sqcand":"60001723722"},{"nome":"MARCOS LUIZ DE OLIVEIRA","nomeUrna":"MARQUINHO TIRADENTES","partido":"AVANTE","numero":"70345","votos":10,"percentual":0.08,"sqcand":"60001634395"},{"nome":"FERNANDO HUGO DA SILVA COLARES","nomeUrna":"DEP FERNANDO HUGO - DR HUGO","partido":"PSD","numero":"55678","votos":9,"percentual":0.08,"sqcand":"60001613523"},{"nome":"JOSIVAN ALVES DO NASCIMENTO","nomeUrna":"JOSIVAN CLUBE","partido":"PMN","numero":"33200","votos":9,"percentual":0.08,"sqcand":"60001646059"},{"nome":"LUANA RÉGIA DE FREITAS LIMA","nomeUrna":"LUANA RIBEIRO","partido":"CIDADANIA","numero":"23123","votos":9,"percentual":0.08,"sqcand":"60001723725"},{"nome":"FRANCISCO ANTONIO BRITO MONÇÃO","nomeUrna":"TONY BRITO","partido":"UNIÃO","numero":"44123","votos":9,"percentual":0.08,"sqcand":"60001608911"},{"nome":"MARIANA VIEIRA LACERDA","nomeUrna":"MARI LACERDA","partido":"PT","numero":"13131","votos":9,"percentual":0.08,"sqcand":"60001633660"},{"nome":"MARIA DENISE ROCHA MENEZES","nomeUrna":"DRA. DENISE","partido":"PT","numero":"13013","votos":9,"percentual":0.08,"sqcand":"60001633650"},{"nome":"JOSE JACOME CARNEIRO ALBUQUERQUE","nomeUrna":"ZEZINHO ALBUQUERQUE","partido":"PP","numero":"11111","votos":7,"percentual":0.06,"sqcand":"60001619179"},{"nome":"ORIEL GUIMARAES NUNES FILHO","nomeUrna":"ORIEL FILHO","partido":"PDT","numero":"12555","votos":7,"percentual":0.06,"sqcand":"60001603523"},{"nome":"VILMAR PEREIRA BATISTA","nomeUrna":"VILMAR BATISTA","partido":"PSDB","numero":"45700","votos":7,"percentual":0.06,"sqcand":"60001727604"},{"nome":"DIEGO BARRETO MOREIRA","nomeUrna":"DIEGO BARRETO","partido":"PSDB","numero":"45333","votos":7,"percentual":0.06,"sqcand":"60001723724"},{"nome":"HEITOR CORREIA FÉRRER","nomeUrna":"HEITOR FÉRRER","partido":"UNIÃO","numero":"44333","votos":7,"percentual":0.06,"sqcand":"60001608921"},{"nome":"FRANCISCO JOSÉ DE SOUSA CRONEMBERGES","nomeUrna":"SARGENTO BERG","partido":"UNIÃO","numero":"44700","votos":7,"percentual":0.06,"sqcand":"60001608936"},{"nome":"DANILO LOPES FERREIRA LIMA","nomeUrna":"DANILO LOPES","partido":"AVANTE","numero":"70007","votos":7,"percentual":0.06,"sqcand":"60001634412"},{"nome":"JACQUELINE FERREIRA GOUVEIA","nomeUrna":"JACQUELINE GOUVEIA","partido":"MDB","numero":"15120","votos":7,"percentual":0.06,"sqcand":"60001635816"},{"nome":"CLAUDIA MARIA DIAS PINHEIRO","nomeUrna":"CLAUDIA DIAS","partido":"PDT","numero":"12321","votos":7,"percentual":0.06,"sqcand":"60001603527"},{"nome":"JOSÉ ERIVALDO XAVIER TRAVASSOS","nomeUrna":"CÔNSUL DO POVO","partido":"PSDB","numero":"45300","votos":6,"percentual":0.05,"sqcand":"60001723723"},{"nome":"GUILHERME DE FIGUEIREDO SAMPAIO","nomeUrna":"GUILHERME SAMPAIO","partido":"PT","numero":"13234","votos":6,"percentual":0.05,"sqcand":"60001633635"},{"nome":"MARTA MARIA DO SOCORRO LIMA BARROS GONÇALVES","nomeUrna":"MARTA GONÇALVES","partido":"PL","numero":"22555","votos":6,"percentual":0.05,"sqcand":"60001633816"},{"nome":"MOÉSIO LOIOLA DE MELO","nomeUrna":"MOÉSIO LOIOLA","partido":"PP","numero":"11999","votos":6,"percentual":0.05,"sqcand":"60001619183"},{"nome":"LUCÍLVIO GIRÃO SALES","nomeUrna":"DR. LUCÍLVIO GIRÃO","partido":"PSD","numero":"55234","votos":5,"percentual":0.04,"sqcand":"60001613535"},{"nome":"FRANCISCO DE ASSIS DINIZ","nomeUrna":"DE ASSIS DINIZ","partido":"PT","numero":"13456","votos":5,"percentual":0.04,"sqcand":"60001633671"},{"nome":"FRANCISCO NAUGUSTO FREIRE SILVA","nomeUrna":"NAUGUSTO CABELEIREIRO","partido":"UNIÃO","numero":"44565","votos":5,"percentual":0.04,"sqcand":"60001608933"},{"nome":"GILBERTO MOREIRA DA PAZ FILHO","nomeUrna":"GILBERTO DE GRANJA","partido":"UNIÃO","numero":"44441","votos":5,"percentual":0.04,"sqcand":"60001608920"},{"nome":"ANTONIO HENRIQUE DA SILVA","nomeUrna":"ANTONIO HENRIQUE","partido":"PDT","numero":"12111","votos":5,"percentual":0.04,"sqcand":"60001603547"},{"nome":"MAGNOLIA DE SOUSA ROCHA","nomeUrna":"MAGNOLIA ROCHA","partido":"UNIÃO","numero":"44567","votos":5,"percentual":0.04,"sqcand":"60001608908"},{"nome":"JULIANA ALVES","nomeUrna":"CACIKA IRÊ","partido":"PC do B","numero":"65234","votos":5,"percentual":0.04,"sqcand":"60001633664"},{"nome":"RAIMUNDO ANTONIO DE SOUZA","nomeUrna":"RAIR DE SOUZA","partido":"MDB","numero":"15111","votos":5,"percentual":0.04,"sqcand":"60001635793"},{"nome":"RONALDO DA SILVA CARACAS","nomeUrna":"CORONEL RONALDO CARACAS","partido":"PTB","numero":"14888","votos":5,"percentual":0.04,"sqcand":"60001668699"},{"nome":"LUIZ HENRIQUE CASTELO LIMA","nomeUrna":"APÓSTOLO LUIZ HENRIQUE","partido":"REPUBLICANOS","numero":"10000","votos":4,"percentual":0.03,"sqcand":"60001608819"},{"nome":"GEILSON PEREIRA LIMA","nomeUrna":"SARGENTO GEILSON","partido":"PL","numero":"22888","votos":4,"percentual":0.03,"sqcand":"60001633794"},{"nome":"RAIMUNDO NONATO FERREIRA ARAGÃO","nomeUrna":"FERREIRA ARAGÃO","partido":"PSDB","numero":"45999","votos":4,"percentual":0.03,"sqcand":"60001723731"},{"nome":"ANTONIO VIANEY SANTIAGO DA COSTA","nomeUrna":"VIANEY DO VALE","partido":"PSDB","numero":"45555","votos":4,"percentual":0.03,"sqcand":"60001723720"},{"nome":"ANDERSON FELÍCIO DE ALBUQUERQUE","nomeUrna":"ANDERSON FELÍCIO","partido":"UNIÃO","numero":"44543","votos":4,"percentual":0.03,"sqcand":"60001608910"},{"nome":"TERESINHA DE JESUS DOS SANTOS","nomeUrna":"PROFESSORA TERESINHA","partido":"PT","numero":"13130","votos":4,"percentual":0.03,"sqcand":"60001633670"},{"nome":"ANTÔNIO STÊNIO VASCONCELOS MAGALHÃES","nomeUrna":"STÊNIO MAGALHÃES","partido":"PC do B","numero":"65100","votos":4,"percentual":0.03,"sqcand":"60001633662"},{"nome":"MIRISLANDIA SALMITO CAMPOS","nomeUrna":"MIRIS SALMITO","partido":"PMN","numero":"33300","votos":3,"percentual":0.03,"sqcand":"60001646078"},{"nome":"EDUARDO CÉSAR BEZERRA DIÓGENES","nomeUrna":"DUDU DIÓGENES","partido":"PL","numero":"22380","votos":3,"percentual":0.03,"sqcand":"60001633792"},{"nome":"JACQUELINE LIMA DOS SANTOS","nomeUrna":"JACK LIMA","partido":"PL","numero":"22123","votos":3,"percentual":0.03,"sqcand":"60001633795"},{"nome":"PEDRO VICTOR COLARES GOMES DE MATOS","nomeUrna":"PEDRO MATOS","partido":"PL","numero":"22111","votos":3,"percentual":0.03,"sqcand":"60001633805"},{"nome":"MARCELO RIBEIRO TORRES","nomeUrna":"MARCELO DA GRANJA","partido":"UNIÃO","numero":"44789","votos":3,"percentual":0.03,"sqcand":"60001608928"},{"nome":"ENEAS CAMPOS GOES","nomeUrna":"ENEAS GOES","partido":"UNIÃO","numero":"44444","votos":3,"percentual":0.03,"sqcand":"60001608923"},{"nome":"FÁTIMA MARIA VIDIGAL RIBEIRO","nomeUrna":"IRMÃ FÁTIMA RIBEIRO","partido":"UNIÃO","numero":"44122","votos":3,"percentual":0.03,"sqcand":"60001608916"},{"nome":"TAÍS ALVES DE LIMA MATOS","nomeUrna":"DRA TAÍS MATOS","partido":"PC do B","numero":"65000","votos":3,"percentual":0.03,"sqcand":"60001633647"},{"nome":"CARLOS BRUNILDO DE OLIVEIRA","nomeUrna":"APÓSTOLO CARLOS BRUNILDO","partido":"REPUBLICANOS","numero":"10122","votos":3,"percentual":0.03,"sqcand":"60001608827"},{"nome":"LILIANE LIMA DA SILVA","nomeUrna":"ENFERMEIRA LILI DO NOSSA VOZ","partido":"AGIR","numero":"36192","votos":3,"percentual":0.03,"sqcand":"60001713046"},{"nome":"JOSEFA MEDEIROS FARIAS","nomeUrna":"JÔ FARIAS","partido":"PT","numero":"13258","votos":2,"percentual":0.02,"sqcand":"60001633653"},{"nome":"FERNANDO MATOS SANTANA","nomeUrna":"FERNANDO SANTANA","partido":"PT","numero":"13222","votos":2,"percentual":0.02,"sqcand":"60001633655"},{"nome":"VALDEMIRO BARBOSA LIMA JUNIOR","nomeUrna":"BARBOSINHA","partido":"PMN","numero":"33233","votos":2,"percentual":0.02,"sqcand":"60001646082"},{"nome":"STUART CASTRO FARIAS LIMA","nomeUrna":"STUART CASTRO","partido":"AVANTE","numero":"70222","votos":2,"percentual":0.02,"sqcand":"60001634432"},{"nome":"LEONARDO FRANKLIN NOGUEIRA PINHEIRO","nomeUrna":"LEONARDO PINHEIRO","partido":"PP","numero":"11444","votos":2,"percentual":0.02,"sqcand":"60001619175"},{"nome":"LUCAS NOCRATO SOARES","nomeUrna":"APOLLO VICZ","partido":"PSD","numero":"55011","votos":2,"percentual":0.02,"sqcand":"60001613525"},{"nome":"ARIMATÉA COSTA BEZERRA","nomeUrna":"ARI COWBOY","partido":"PL","numero":"22122","votos":2,"percentual":0.02,"sqcand":"60001633831"},{"nome":"ANDRÉ LUIZ DIÓGENES MATOS","nomeUrna":"ANDRÉ ADT","partido":"PL","numero":"22909","votos":2,"percentual":0.02,"sqcand":"60001633789"},{"nome":"ALOÍSIO ANTÔNIO GOMES DE MATOS BRASIL","nomeUrna":"DR. ALOÍSIO","partido":"UNIÃO","numero":"44555","votos":2,"percentual":0.02,"sqcand":"60001608941"},{"nome":"GUILHERME SAMPAIO LANDIM","nomeUrna":"GUILHERME LANDIM","partido":"PDT","numero":"12114","votos":2,"percentual":0.02,"sqcand":"60001603525"},{"nome":"CAMILA RODRIGUES TEIXEIRA MOTA","nomeUrna":"CAMILA MOTA","partido":"UNIÃO","numero":"44321","votos":2,"percentual":0.02,"sqcand":"60001608904"},{"nome":"FRANCISCO OSMAR DIÓGENES BAQUIT","nomeUrna":"OSMAR BAQUIT","partido":"PDT","numero":"12222","votos":2,"percentual":0.02,"sqcand":"60001603520"},{"nome":"CARLOS AUGUSTO ARAGÃO DE ARAÚJO","nomeUrna":"AUGUSTO ARAGÃO","partido":"AVANTE","numero":"70111","votos":2,"percentual":0.02,"sqcand":"60001634406"},{"nome":"ROBERTO LIRA MONTE","nomeUrna":"ROBERTO LIRA","partido":"AVANTE","numero":"70677","votos":2,"percentual":0.02,"sqcand":"60001634418"},{"nome":"MARTULINA SILVA FREITAS","nomeUrna":"MARTA FREITAS","partido":"PV","numero":"43123","votos":2,"percentual":0.02,"sqcand":"60001633666"},{"nome":"FRANCISCO ANTÔNIO COSTA EMILIANO","nomeUrna":"CHICO DO POSTO","partido":"AVANTE","numero":"70400","votos":2,"percentual":0.02,"sqcand":"60001634402"},{"nome":"MARGARIDA MARIA TORRES CORREIA","nomeUrna":"MARGARIDA TORRES","partido":"AVANTE","numero":"70027","votos":2,"percentual":0.02,"sqcand":"60001730658"},{"nome":"CLAUDIA HELENA JORGE DE LIMA LEITE","nomeUrna":"CLAUDIA HELENA","partido":"MDB","numero":"15331","votos":2,"percentual":0.02,"sqcand":"60001635791"},{"nome":"ZULEIDE FERNANDES DE QUEIROZ","nomeUrna":"ZULEIDE QUEIROZ","partido":"PSOL","numero":"50444","votos":2,"percentual":0.02,"sqcand":"60001613095"},{"nome":"ANTONIO PINHEIRO GRANJA","nomeUrna":"ANTONIO GRANJA","partido":"PDT","numero":"12100","votos":2,"percentual":0.02,"sqcand":"60001603541"},{"nome":"GUILHERME BISMARCK","nomeUrna":"GUILHERME BISMARCK","partido":"PDT","numero":"12144","votos":2,"percentual":0.02,"sqcand":"60001603538"},{"nome":"JANE RUTH CHAVES NASCIMENTO VIANA","nomeUrna":"JANNE RUTH","partido":"PDT","numero":"12344","votos":2,"percentual":0.02,"sqcand":"60001603544"},{"nome":"MANOEL DUCA DA SILVEIRA NETO","nomeUrna":"DUQUINHA","partido":"REPUBLICANOS","numero":"10124","votos":2,"percentual":0.02,"sqcand":"60001608820"},{"nome":"EUVALDO REIS DA COSTA","nomeUrna":"EVALDO COSTA","partido":"REPUBLICANOS","numero":"10190","votos":2,"percentual":0.02,"sqcand":"60001608828"},{"nome":"RAIMUNDA HILMA ARAUJO LIRA COUTINHO","nomeUrna":"HILMA COUTINHO","partido":"PP","numero":"11333","votos":2,"percentual":0.02,"sqcand":"60001619176"},{"nome":"PAULO JOSÉ FELIX DA SILVA","nomeUrna":"PAULÃO DA ACADEMIA","partido":"PMN","numero":"33211","votos":1,"percentual":0.01,"sqcand":"60001646062"},{"nome":"ISAQUE FARIAS RABELO","nomeUrna":"DR. ISAQUE RABELO","partido":"NOVO","numero":"30000","votos":1,"percentual":0.01,"sqcand":"60001595309"},{"nome":"FELIPE AGUIAR FONSECA DA MOTA","nomeUrna":"FELIPE MOTA","partido":"UNIÃO","numero":"44111","votos":1,"percentual":0.01,"sqcand":"60001608946"},{"nome":"EWERTON VINICIUS SANTOS DUARTE","nomeUrna":"VINICIUS DUARTE","partido":"PSD","numero":"55100","votos":1,"percentual":0.01,"sqcand":"60001613524"},{"nome":"FRANCISCO PEREIRA TORRES","nomeUrna":"DR TORRES","partido":"PSD","numero":"55222","votos":1,"percentual":0.01,"sqcand":"60001613536"},{"nome":"LUIZ OCELO CAMPOS BEZERRA","nomeUrna":"LUIZ OCELO","partido":"PSB","numero":"40400","votos":1,"percentual":0.01,"sqcand":"60001603499"},{"nome":"THIAGO DE PAIVA SALES","nomeUrna":"DR THIAGO SALES","partido":"PL","numero":"22333","votos":1,"percentual":0.01,"sqcand":"60001633800"},{"nome":"PAULO RICARDO FARIAS PROTASIO","nomeUrna":"PAULO PROTÁSIO","partido":"PSB","numero":"40888","votos":1,"percentual":0.01,"sqcand":"60001603512"},{"nome":"RUBEM SÉRGIO DE ARAÚJO","nomeUrna":"CABO RUBEM RUBINHO","partido":"PL","numero":"22190","votos":1,"percentual":0.01,"sqcand":"60001633798"},{"nome":"SIMONE FERREIRA MATIAS BESERRA","nomeUrna":"SIMONE MATIAS","partido":"PL","numero":"22345","votos":1,"percentual":0.01,"sqcand":"60001633808"},{"nome":"VIVIANE DOS SANTOS SILVA","nomeUrna":"VIVIANE SILVA","partido":"PL","numero":"22700","votos":1,"percentual":0.01,"sqcand":"60001733412"},{"nome":"MARIA DO PERPÉTUO SOCORRO AGUIAR GERMANO","nomeUrna":"PERPÉTUA AGUIAR","partido":"PL","numero":"22444","votos":1,"percentual":0.01,"sqcand":"60001633826"},{"nome":"LEIA SIMONE MOURA DE ARAUJO","nomeUrna":"LEIA SIMONE","partido":"PROS","numero":"90123","votos":1,"percentual":0.01,"sqcand":"60001619112"},{"nome":"CÂNDIDO ALEXANDRINO BARRETO NETO","nomeUrna":"CANDIDO ALEXANDRINO","partido":"UNIÃO","numero":"44999","votos":1,"percentual":0.01,"sqcand":"60001608945"},{"nome":"VILMARO LEITE DE LIMA","nomeUrna":"VILMARO LEITE","partido":"PROS","numero":"90000","votos":1,"percentual":0.01,"sqcand":"60001619118"},{"nome":"JOÃO PAULO DE MENEZES FURTADO","nomeUrna":"JOÃO PAULO","partido":"UNIÃO","numero":"44666","votos":1,"percentual":0.01,"sqcand":"60001608931"},{"nome":"PRISCILA LINHARES ROCHA","nomeUrna":"PRISCILA ROCHA","partido":"UNIÃO","numero":"44556","votos":1,"percentual":0.01,"sqcand":"60001608932"},{"nome":"ANTONIO BOSCO PEREIRA CID","nomeUrna":"BOSCO CID","partido":"UNIÃO","numero":"44345","votos":1,"percentual":0.01,"sqcand":"60001608943"},{"nome":"FORSYTH VASCONCELOS E SILVA SANTOS","nomeUrna":"DR FORSYTH","partido":"UNIÃO","numero":"44600","votos":1,"percentual":0.01,"sqcand":"60001608924"},{"nome":"FRANCISCO LEITÃO MOURA","nomeUrna":"DOUTOR LEITÃO","partido":"CIDADANIA","numero":"23333","votos":1,"percentual":0.01,"sqcand":"60001723726"},{"nome":"MARIA SELMA DE MELO SILVA","nomeUrna":"SELMA SILVA","partido":"PV","numero":"43024","votos":1,"percentual":0.01,"sqcand":"60001633639"},{"nome":"WALTER LIMA FROTA CAVALCANTE","nomeUrna":"WALTER CAVALCANTE","partido":"PV","numero":"43640","votos":1,"percentual":0.01,"sqcand":"60001633641"},{"nome":"ADRIANIZIO PAULO DE OLIVEIRA ALVES","nomeUrna":"CORONEL ADRIANIZIO PAULO","partido":"AVANTE","numero":"70777","votos":1,"percentual":0.01,"sqcand":"60001725786"},{"nome":"THIAGO HIGOR DE ALMEIDA FREITAS","nomeUrna":"THIAGUINHO MALA MANSA","partido":"AVANTE","numero":"70200","votos":1,"percentual":0.01,"sqcand":"60001634428"},{"nome":"AGENOR DE CASTRO COSTA","nomeUrna":"CAPITÃO AGENOR","partido":"AVANTE","numero":"70762","votos":1,"percentual":0.01,"sqcand":"60001634434"},{"nome":"PEDRO NETO LOBO SOARES","nomeUrna":"PEDRO LOBO","partido":"PT","numero":"13111","votos":1,"percentual":0.01,"sqcand":"60001633676"},{"nome":"ANA KAROLYNE RODRIGUES BEZERRA","nomeUrna":"PRETA KAROL","partido":"PT","numero":"13138","votos":1,"percentual":0.01,"sqcand":"60001633669"},{"nome":"FRANCISCO JUAREZ CRUZ DE VASCONCELOS FILHO","nomeUrna":"DR. JUAREZ VASCONCELOS","partido":"PT","numero":"13444","votos":1,"percentual":0.01,"sqcand":"60001633674"},{"nome":"FELIPE AGUIAR DE MENESES","nomeUrna":"FELIPE AGUIAR","partido":"MDB","numero":"15555","votos":1,"percentual":0.01,"sqcand":"60001635818"},{"nome":"FRANCISCO ERIVANDO DOS SANTOS","nomeUrna":"PROFESSOR SULA","partido":"MDB","numero":"15001","votos":1,"percentual":0.01,"sqcand":"60001635795"},{"nome":"LEONARDO ARAÚJO DE SOUZA","nomeUrna":"LEONARDO ARAÚJO","partido":"MDB","numero":"15151","votos":1,"percentual":0.01,"sqcand":"60001635807"},{"nome":"SILVIA HELENA FREIRE DE PAIVA SOUZA","nomeUrna":"SILVINHA PAIVA","partido":"MDB","numero":"15015","votos":1,"percentual":0.01,"sqcand":"60001635811"},{"nome":"SABRINA MILANE VERAS CAMPOS","nomeUrna":"SABRINA VERAS","partido":"MDB","numero":"15777","votos":1,"percentual":0.01,"sqcand":"60001635800"},{"nome":"ISABEL CRISTINA SILVA DE SOUSA","nomeUrna":"CRISTINA É TEMPO DE AQUILOMBAR","partido":"PSOL","numero":"50123","votos":1,"percentual":0.01,"sqcand":"60001613099"},{"nome":"ADRIANA GERONIMO VIEIRA SILVA","nomeUrna":"ADRIANA GERONIMO","partido":"PSOL","numero":"50777","votos":1,"percentual":0.01,"sqcand":"60001613097"},{"nome":"CARLOS DOUGLAS DA SILVA SOUZA","nomeUrna":"DOUGLAS","partido":"PSOL","numero":"50321","votos":1,"percentual":0.01,"sqcand":"60001613087"},{"nome":"ADRIANO BENTO DA SILVA","nomeUrna":"ADRIANO BENTO ","partido":"PTB","numero":"14400","votos":1,"percentual":0.01,"sqcand":"60001668688"},{"nome":"AUGUSTO LÚCIO DE FREITAS","nomeUrna":"AUGUSTO PIRABIBU","partido":"PTB","numero":"14111","votos":1,"percentual":0.01,"sqcand":"60001668696"},{"nome":"LUIZA DE MARILLAC LIMA FERREIRA","nomeUrna":"MARILLAC LIMA","partido":"PDT","numero":"12330","votos":1,"percentual":0.01,"sqcand":"60001603530"},{"nome":"RAFAEL PEREIRA MACHADO","nomeUrna":"RAFAEL RR","partido":"PDT","numero":"12422","votos":1,"percentual":0.01,"sqcand":"60001614172"},{"nome":"FRANCISCO VILDAN GARCIA DE SOUZA","nomeUrna":"POEIRA DO ICÓ","partido":"AGIR","numero":"36222","votos":1,"percentual":0.01,"sqcand":"60001713035"},{"nome":"JOSEMAR COELHO LIMA","nomeUrna":"JOTA LIMA JUMENTIM AMARELO","partido":"PDT","numero":"12011","votos":1,"percentual":0.01,"sqcand":"60001603519"},{"nome":"FRANCISCO ALEX CARLOS PAIVA","nomeUrna":"ALEX PAIVA","partido":"REPUBLICANOS","numero":"10275","votos":1,"percentual":0.01,"sqcand":"60001608835"},{"nome":"SARAH RODRIGUES OLIVEIRA","nomeUrna":"SARAH PRETA SIMOA","partido":"UP","numero":"80180","votos":1,"percentual":0.01,"sqcand":"60001634341"},{"nome":"FRANCISCO ANTONIO GIRLANDO AIRES RODRIGUES","nomeUrna":"GIRLANDO RODRIGUES","partido":"REPUBLICANOS","numero":"10102","votos":1,"percentual":0.01,"sqcand":"60001608837"},{"nome":"ANTONIO SERGIO FREITAS RODRIGUES","nomeUrna":"SÉRGIO FREITAS","partido":"PP","numero":"11777","votos":1,"percentual":0.01,"sqcand":"60001619182"},{"nome":"PAULO VICTOR TAVARES GURGEL","nomeUrna":"DR VICTOR GURGEL","partido":"PP","numero":"11222","votos":1,"percentual":0.01,"sqcand":"60001619186"},{"nome":"GODOFREDO CASTRO DE OLIVEIRA","nomeUrna":"GODOFREDO PEPEY","partido":"REPUBLICANOS","numero":"10700","votos":1,"percentual":0.01,"sqcand":"60001608838"},{"nome":"ANTONIO INACIO DE OLIVEIRA JUNIOR","nomeUrna":"INACIO OLIVEIRA","partido":"PSOL","numero":"50555","votos":1,"percentual":0.01,"sqcand":"60001613086"}]}